Workbook

Sheet master-sheet-football
A1: University URL wiki | B1: University | C1: Common Name | D1: Nickname | E1: City | F1: State | G1: Type | H1: Subdivision | I1: Primary | J1: University URL sport-ref | K1: Roster count 2025 | L1: Roster count 2024 | M1: Roster count 2023
A2: https://en.wikipedia.org/wiki/Abilene_Christian_University | B2: Abilene Christian University | C2: Abilene Christian | D2: Wildcats | E2: Abilene | F2: TX | G2: Private | H2: FCS | I2: Western Athletic Conference | J2: {=XLOOKUP(B2, 'name-mapping-football'!C:C, 'name-mapping-football'!A:A, "")}
A3: https://en.wikipedia.org/wiki/Alabama_A%26M_University | B3: Alabama Agricultural and Mechanical University | C3: Alabama A&M | D3: Bulldogs | E3: Normal | F3: AL | G3: Public | H3: FCS | I3: Southwestern Athletic Conference | J3: {=XLOOKUP(B3, 'name-mapping-football'!C:C, 'name-mapping-football'!A:A, "")}
A4: https://en.wikipedia.org/wiki/Alabama_State_University | B4: Alabama State University | C4: Alabama State | D4: Hornets | E4: Montgomery | F4: AL | G4: Public | H4: FCS | I4: Southwestern Athletic Conference | J4: {=XLOOKUP(B4, 'name-mapping-football'!C:C, 'name-mapping-football'!A:A, "")}
A5: https://en.wikipedia.org/wiki/Alcorn_State_University | B5: Alcorn State University | C5: Alcorn State | D5: Braves | E5: Lorman | F5: MS | G5: Public | H5: FCS | I5: Southwestern Athletic Conference | J5: {=XLOOKUP(B5, 'name-mapping-football'!C:C, 'name-mapping-football'!A:A, "")}
A6: https://en.wikipedia.org/wiki/American_University | B6: American University | C6: American | D6: Eagles | E6: Washington | F6: DC | G6: Private | H6: Non-football | I6: Patriot League | J6: {=XLOOKUP(B6, 'name-mapping-football'!C:C, 'name-mapping-football'!A:A, "")} | K6: 0 | L6: 0 | M6: 0
A7: https://en.wikipedia.org/wiki/Appalachian_State_University | B7: Appalachian State University | C7: Appalachian State | D7: Mountaineers | E7: Boone | F7: NC | G7: Public | H7: FBS | I7: Sun Belt Conference | J7: {=XLOOKUP(B7, 'name-mapping-football'!C:C, 'name-mapping-football'!A:A, "")} -> https://www.sports-reference.com/cfb/schools/appalachian-state/
A8: https://en.wikipedia.org/wiki/Arizona_State_University | B8: Arizona State University | C8: Arizona State | D8: Sun Devils | E8: Tempe | F8: AZ | G8: Public | H8: FBS | I8: Big 12 Conference | J8: {=XLOOKUP(B8, 'name-mapping-football'!C:C, 'name-mapping-football'!A:A, "")} -> https://www.sports-reference.com/cfb/schools/arizona-state/
A9: https://en.wikipedia.org/wiki/Arkansas_State_University | B9: Arkansas State University | C9: Arkansas State | D9: Red Wolves | E9: Jonesboro | F9: AR | G9: Public | H9: FBS | I9: Sun Belt Conference | J9: {=XLOOKUP(B9, 'name-mapping-football'!C:C, 'name-mapping-football'!A:A, "")} -> https://www.sports-reference.com/cfb/schools/arkansas-state/
A10: https://en.wikipedia.org/wiki/Auburn_University | B10: Auburn University | C10: Auburn | D10: Tigers | E10: Auburn | F10: AL | G10: Public | H10: FBS | I10: Southeastern Conference | J10: {=XLOOKUP(B10, 'name-mapping-football'!C:C, 'name-mapping-football'!A:A, "")} -> https://www.sports-reference.com/cfb/schools/auburn/
A11: https://en.wikipedia.org/wiki/Austin_Peay_State_University | B11: Austin Peay State University | C11: Austin Peay | D11: Governors | E11: Clarksville | F11: TN | G11: Public | H11: FCS | I11: Atlantic Sun Conference | J11: {=XLOOKUP(B11, 'name-mapping-football'!C:C, 'name-mapping-football'!A:A, "")}
A12: https://en.wikipedia.org/wiki/Ball_State_University | B12: Ball State University | C12: Ball State | D12: Cardinals | E12: Muncie | F12: IN | G12: Public | H12: FBS | I12: Mid-American Conference | J12: {=XLOOKUP(B12, 'name-mapping-football'!C:C, 'name-mapping-football'!A:A, "")} -> https://www.sports-reference.com/cfb/schools/ball-state/
A13: https://en.wikipedia.org/wiki/Baylor_University | B13: Baylor University | C13: Baylor | D13: Bears | E13: Waco | F13: TX | G13: Private | H13: FBS | I13: Big 12 Conference | J13: {=XLOOKUP(B13, 'name-mapping-football'!C:C, 'name-mapping-football'!A:A, "")} -> https://www.sports-reference.com/cfb/schools/baylor/
A14: https://en.wikipedia.org/wiki/Bellarmine_University | B14: Bellarmine University | C14: Bellarmine | D14: Knights | E14: Louisville | F14: KY | G14: Private | H14: Non-football | I14: Atlantic Sun Conference | J14: {=XLOOKUP(B14, 'name-mapping-football'!C:C, 'name-mapping-football'!A:A, "")} | K14: 0 | L14: 0 | M14: 0
A15: https://en.wikipedia.org/wiki/Belmont_University | B15: Belmont University | C15: Belmont | D15: Bruins | E15: Nashville | F15: TN | G15: Private | H15: Non-football | I15: Missouri Valley Conference | J15: {=XLOOKUP(B15, 'name-mapping-football'!C:C, 'name-mapping-football'!A:A, "")} | K15: 0 | L15: 0 | M15: 0
A16: https://en.wikipedia.org/wiki/Bethune%E2%80%93Cookman_University | B16: Bethune–Cookman University | C16: Bethune–Cookman | D16: Wildcats | E16: Daytona Beach | F16: FL | G16: Private | H16: FCS | I16: Southwestern Athletic Conference | J16: {=XLOOKUP(B16, 'name-mapping-football'!C:C, 'name-mapping-football'!A:A, "")}
A17: https://en.wikipedia.org/wiki/Boise_State_University | B17: Boise State University | C17: Boise State | D17: Broncos | E17: Boise | F17: ID | G17: Public | H17: FBS | I17: Mountain West Conference | J17: {=XLOOKUP(B17, 'name-mapping-football'!C:C, 'name-mapping-football'!A:A, "")} -> https://www.sports-reference.com/cfb/schools/boise-state/
A18: https://en.wikipedia.org/wiki/Boston_College | B18: Boston College | C18: Boston College | D18: Eagles | E18: Chestnut Hill | F18: MA | G18: Private | H18: FBS | I18: Atlantic Coast Conference | J18: {=XLOOKUP(B18, 'name-mapping-football'!C:C, 'name-mapping-football'!A:A, "")} -> https://www.sports-reference.com/cfb/schools/boston-college/
A19: https://en.wikipedia.org/wiki/Boston_University | B19: Boston University | C19: Boston University | D19: Terriers | E19: Boston | F19: MA | G19: Private | H19: Non-football | I19: Patriot League | J19: {=XLOOKUP(B19, 'name-mapping-football'!C:C, 'name-mapping-football'!A:A, "")} | K19: 0 | L19: 0 | M19: 0
A20: https://en.wikipedia.org/wiki/Bowling_Green_State_University | B20: Bowling Green State University | C20: Bowling Green | D20: Falcons | E20: Bowling Green | F20: OH | G20: Public | H20: FBS | I20: Mid-American Conference | J20: {=XLOOKUP(B20, 'name-mapping-football'!C:C, 'name-mapping-football'!A:A, "")} -> https://www.sports-reference.com/cfb/schools/bowling-green-state/
A21: https://en.wikipedia.org/wiki/Bradley_University | B21: Bradley University | C21: Bradley | D21: Braves | E21: Peoria | F21: IL | G21: Private | H21: Non-football | I21: Missouri Valley Conference | J21: {=XLOOKUP(B21, 'name-mapping-football'!C:C, 'name-mapping-football'!A:A, "")} | K21: 0 | L21: 0 | M21: 0
A22: https://en.wikipedia.org/wiki/Brigham_Young_University | B22: Brigham Young University | C22: BYU | D22: Cougars | E22: Provo | F22: UT | G22: Private | H22: FBS | I22: Big 12 Conference | J22: {=XLOOKUP(B22, 'name-mapping-football'!C:C, 'name-mapping-football'!A:A, "")} -> https://www.sports-reference.com/cfb/schools/brigham-young/
A23: https://en.wikipedia.org/wiki/Brown_University | B23: Brown University | C23: Brown | D23: Bears | E23: Providence | F23: RI | G23: Private | H23: FCS | I23: Ivy League | J23: {=XLOOKUP(B23, 'name-mapping-football'!C:C, 'name-mapping-football'!A:A, "")}
A24: https://en.wikipedia.org/wiki/Bryant_University | B24: Bryant University | C24: Bryant | D24: Bulldogs | E24: Smithfield | F24: RI | G24: Private | H24: FCS | I24: America East Conference | J24: {=XLOOKUP(B24, 'name-mapping-football'!C:C, 'name-mapping-football'!A:A, "")}
A25: https://en.wikipedia.org/wiki/Bucknell_University | B25: Bucknell University | C25: Bucknell | D25: Bison | E25: Lewisburg | F25: PA | G25: Private | H25: FCS | I25: Patriot League | J25: {=XLOOKUP(B25, 'name-mapping-football'!C:C, 'name-mapping-football'!A:A, "")}
A26: https://en.wikipedia.org/wiki/Butler_University | B26: Butler University | C26: Butler | D26: Bulldogs | E26: Indianapolis | F26: IN | G26: Private | H26: FCS | I26: Big East Conference | J26: {=XLOOKUP(B26, 'name-mapping-football'!C:C, 'name-mapping-football'!A:A, "")}
A27: https://en.wikipedia.org/wiki/California_Baptist_University | B27: California Baptist University | C27: Cal Baptist | D27: Lancers | E27: Riverside | F27: CA | G27: Private | H27: Non-football | I27: Western Athletic Conference | J27: {=XLOOKUP(B27, 'name-mapping-football'!C:C, 'name-mapping-football'!A:A, "")} | K27: 0 | L27: 0 | M27: 0
A28: https://en.wikipedia.org/wiki/California_Polytechnic_State_University,_San_Luis_Obispo | B28: California Polytechnic State University | C28: Cal Poly | D28: Mustangs | E28: San Luis Obispo | F28: CA | G28: Public | H28: FCS | I28: Big West Conference | J28: {=XLOOKUP(B28, 'name-mapping-football'!C:C, 'name-mapping-football'!A:A, "")}
A29: https://en.wikipedia.org/wiki/California_State_University,_Bakersfield | B29: California State University, Bakersfield | C29: Bakersfield | D29: Roadrunners | E29: Bakersfield | F29: CA | G29: Public | H29: Non-football | I29: Big West Conference | J29: {=XLOOKUP(B29, 'name-mapping-football'!C:C, 'name-mapping-football'!A:A, "")} | K29: 0 | L29: 0 | M29: 0
A30: https://en.wikipedia.org/wiki/California_State_University,_Fresno | B30: California State University, Fresno | C30: Fresno State | D30: Bulldogs | E30: Fresno | F30: CA | G30: Public | H30: FBS | I30: Mountain West Conference | J30: {=XLOOKUP(B30, 'name-mapping-football'!C:C, 'name-mapping-football'!A:A, "")} -> https://www.sports-reference.com/cfb/schools/fresno-state/
A31: https://en.wikipedia.org/wiki/California_State_University,_Fullerton | B31: California State University, Fullerton | C31: Cal State Fullerton | D31: Titans | E31: Fullerton | F31: CA | G31: Public | H31: Non-football | I31: Big West Conference | J31: {=XLOOKUP(B31, 'name-mapping-football'!C:C, 'name-mapping-football'!A:A, "")} | K31: 0 | L31: 0 | M31: 0
A32: https://en.wikipedia.org/wiki/California_State_University,_Long_Beach | B32: California State University, Long Beach | C32: Long Beach State | D32: Beach | E32: Long Beach | F32: CA | G32: Public | H32: Non-football | I32: Big West Conference | J32: {=XLOOKUP(B32, 'name-mapping-football'!C:C, 'name-mapping-football'!A:A, "")} | K32: 0 | L32: 0 | M32: 0
A33: https://en.wikipedia.org/wiki/California_State_University,_Northridge | B33: California State University, Northridge | C33: Cal State Northridge / CSUN | D33: Matadors | E33: Northridge | F33: CA | G33: Public | H33: Non-football | I33: Big West Conference | J33: {=XLOOKUP(B33, 'name-mapping-football'!C:C, 'name-mapping-football'!A:A, "")} | K33: 0 | L33: 0 | M33: 0
A34: https://en.wikipedia.org/wiki/California_State_University,_Sacramento | B34: California State University, Sacramento | C34: Sacramento State | D34: Hornets | E34: Sacramento | F34: CA | G34: Public | H34: FCS | I34: Big Sky Conference | J34: {=XLOOKUP(B34, 'name-mapping-football'!C:C, 'name-mapping-football'!A:A, "")}
A35: https://en.wikipedia.org/wiki/Campbell_University | B35: Campbell University | C35: Campbell | D35: Fighting Camels | E35: Buies Creek | F35: NC | G35: Private | H35: FCS | I35: Coastal Athletic Association | J35: {=XLOOKUP(B35, 'name-mapping-football'!C:C, 'name-mapping-football'!A:A, "")}
A36: https://en.wikipedia.org/wiki/Canisius_University | B36: Canisius University | C36: Canisius | D36: Golden Griffins | E36: Buffalo | F36: NY | G36: Private | H36: Non-football | I36: Metro Atlantic Athletic Conference | J36: {=XLOOKUP(B36, 'name-mapping-football'!C:C, 'name-mapping-football'!A:A, "")} | K36: 0 | L36: 0 | M36: 0
A37: https://en.wikipedia.org/wiki/Central_Connecticut_State_University | B37: Central Connecticut State University | C37: Central Connecticut | D37: Blue Devils | E37: New Britain | F37: CT | G37: Public | H37: FCS | I37: NEC | J37: {=XLOOKUP(B37, 'name-mapping-football'!C:C, 'name-mapping-football'!A:A, "")}
A38: https://en.wikipedia.org/wiki/Central_Michigan_University | B38: Central Michigan University | C38: Central Michigan | D38: Chippewas | E38: Mount Pleasant | F38: MI | G38: Public | H38: FBS | I38: Mid-American Conference | J38: {=XLOOKUP(B38, 'name-mapping-football'!C:C, 'name-mapping-football'!A:A, "")} -> https://www.sports-reference.com/cfb/schools/central-michigan/
A39: https://en.wikipedia.org/wiki/Charleston_Southern_University | B39: Charleston Southern University | C39: Charleston Southern | D39: Buccaneers | E39: North Charleston | F39: SC | G39: Private | H39: FCS | I39: Big South Conference | J39: {=XLOOKUP(B39, 'name-mapping-football'!C:C, 'name-mapping-football'!A:A, "")}
A40: https://en.wikipedia.org/wiki/Chicago_State_University | B40: Chicago State University | C40: Chicago State | D40: Cougars | E40: Chicago | F40: IL | G40: Public | H40: Non-football | I40: NEC | J40: {=XLOOKUP(B40, 'name-mapping-football'!C:C, 'name-mapping-football'!A:A, "")} | K40: 0 | L40: 0 | M40: 0
A41: https://en.wikipedia.org/wiki/Clemson_University | B41: Clemson University | C41: Clemson | D41: Tigers | E41: Clemson | F41: SC | G41: Public | H41: FBS | I41: Atlantic Coast Conference | J41: {=XLOOKUP(B41, 'name-mapping-football'!C:C, 'name-mapping-football'!A:A, "")} -> https://www.sports-reference.com/cfb/schools/clemson/
A42: https://en.wikipedia.org/wiki/Cleveland_State_University | B42: Cleveland State University | C42: Cleveland State | D42: Vikings | E42: Cleveland | F42: OH | G42: Public | H42: Non-football | I42: Horizon League | J42: {=XLOOKUP(B42, 'name-mapping-football'!C:C, 'name-mapping-football'!A:A, "")} | K42: 0 | L42: 0 | M42: 0
A43: https://en.wikipedia.org/wiki/Coastal_Carolina_University | B43: Coastal Carolina University | C43: Coastal Carolina | D43: Chanticleers | E43: Conway | F43: SC | G43: Public | H43: FBS | I43: Sun Belt Conference | J43: {=XLOOKUP(B43, 'name-mapping-football'!C:C, 'name-mapping-football'!A:A, "")} -> https://www.sports-reference.com/cfb/schools/coastal-carolina/
A44: https://en.wikipedia.org/wiki/Colgate_University | B44: Colgate University | C44: Colgate | D44: Raiders | E44: Hamilton | F44: NY | G44: Private | H44: FCS | I44: Patriot League | J44: {=XLOOKUP(B44, 'name-mapping-football'!C:C, 'name-mapping-football'!A:A, "")}
A45: https://en.wikipedia.org/wiki/College_of_Charleston | B45: College of Charleston | C45: Charleston | D45: Cougars | E45: Charleston | F45: SC | G45: Public | H45: Non-football | I45: Coastal Athletic Association | J45: {=XLOOKUP(B45, 'name-mapping-football'!C:C, 'name-mapping-football'!A:A, "")} | K45: 0 | L45: 0 | M45: 0
A46: https://en.wikipedia.org/wiki/College_of_the_Holy_Cross | B46: College of the Holy Cross | C46: Holy Cross | D46: Crusaders | E46: Worcester | F46: MA | G46: Private | H46: FCS | I46: Patriot League | J46: {=XLOOKUP(B46, 'name-mapping-football'!C:C, 'name-mapping-football'!A:A, "")}
A47: https://en.wikipedia.org/wiki/Colorado_State_University | B47: Colorado State University | C47: Colorado State | D47: Rams | E47: Fort Collins | F47: CO | G47: Public | H47: FBS | I47: Mountain West Conference | J47: {=XLOOKUP(B47, 'name-mapping-football'!C:C, 'name-mapping-football'!A:A, "")} -> https://www.sports-reference.com/cfb/schools/colorado-state/
A48: https://en.wikipedia.org/wiki/Columbia_University | B48: Columbia University in the City of New York | C48: Columbia | D48: Lions | E48: New York | F48: NY | G48: Private | H48: FCS | I48: Ivy League | J48: {=XLOOKUP(B48, 'name-mapping-football'!C:C, 'name-mapping-football'!A:A, "")}
A49: https://en.wikipedia.org/wiki/Coppin_State_University | B49: Coppin State University | C49: Coppin State | D49: Eagles | E49: Baltimore | F49: MD | G49: Public | H49: Non-football | I49: Mid-Eastern Athletic Conference | J49: {=XLOOKUP(B49, 'name-mapping-football'!C:C, 'name-mapping-football'!A:A, "")} | K49: 0 | L49: 0 | M49: 0
A50: https://en.wikipedia.org/wiki/Cornell_University | B50: Cornell University | C50: Cornell | D50: Big Red | E50: Ithaca | F50: NY | G50: Private | H50: FCS | I50: Ivy League | J50: {=XLOOKUP(B50, 'name-mapping-football'!C:C, 'name-mapping-football'!A:A, "")}
A51: https://en.wikipedia.org/wiki/Creighton_University | B51: Creighton University | C51: Creighton | D51: Bluejays | E51: Omaha | F51: NE | G51: Private | H51: Non-football | I51: Big East Conference | J51: {=XLOOKUP(B51, 'name-mapping-football'!C:C, 'name-mapping-football'!A:A, "")} | K51: 0 | L51: 0 | M51: 0
A52: https://en.wikipedia.org/wiki/Dartmouth_College | B52: Dartmouth College | C52: Dartmouth | D52: Big Green | E52: Hanover | F52: NH | G52: Private | H52: FCS | I52: Ivy League | J52: {=XLOOKUP(B52, 'name-mapping-football'!C:C, 'name-mapping-football'!A:A, "")}
A53: https://en.wikipedia.org/wiki/Davidson_College | B53: Davidson College | C53: Davidson | D53: Wildcats | E53: Davidson | F53: NC | G53: Private | H53: FCS | I53: Atlantic 10 Conference | J53: {=XLOOKUP(B53, 'name-mapping-football'!C:C, 'name-mapping-football'!A:A, "")}
A54: https://en.wikipedia.org/wiki/Delaware_State_University | B54: Delaware State University | C54: Delaware State | D54: Hornets | E54: Dover | F54: DE | G54: Public | H54: FCS | I54: Mid-Eastern Athletic Conference | J54: {=XLOOKUP(B54, 'name-mapping-football'!C:C, 'name-mapping-football'!A:A, "")}
A55: https://en.wikipedia.org/wiki/DePaul_University | B55: DePaul University | C55: DePaul | D55: Blue Demons | E55: Chicago | F55: IL | G55: Private | H55: Non-football | I55: Big East Conference | J55: {=XLOOKUP(B55, 'name-mapping-football'!C:C, 'name-mapping-football'!A:A, "")} | K55: 0 | L55: 0 | M55: 0
A56: https://en.wikipedia.org/wiki/Drake_University | B56: Drake University | C56: Drake | D56: Bulldogs | E56: Des Moines | F56: IA | G56: Private | H56: FCS | I56: Missouri Valley Conference | J56: {=XLOOKUP(B56, 'name-mapping-football'!C:C, 'name-mapping-football'!A:A, "")}
A57: https://en.wikipedia.org/wiki/Drexel_University | B57: Drexel University | C57: Drexel | D57: Dragons | E57: Philadelphia | F57: PA | G57: Private | H57: Non-football | I57: Coastal Athletic Association | J57: {=XLOOKUP(B57, 'name-mapping-football'!C:C, 'name-mapping-football'!A:A, "")} | K57: 0 | L57: 0 | M57: 0
A58: https://en.wikipedia.org/wiki/Duke_University | B58: Duke University | C58: Duke | D58: Blue Devils | E58: Durham | F58: NC | G58: Private | H58: FBS | I58: Atlantic Coast Conference | J58: {=XLOOKUP(B58, 'name-mapping-football'!C:C, 'name-mapping-football'!A:A, "")} -> https://www.sports-reference.com/cfb/schools/duke/
A59: https://en.wikipedia.org/wiki/Duquesne_University | B59: Duquesne University of the Holy Spirit | C59: Duquesne | D59: Dukes | E59: Pittsburgh | F59: PA | G59: Private | H59: FCS | I59: Atlantic 10 Conference | J59: {=XLOOKUP(B59, 'name-mapping-football'!C:C, 'name-mapping-football'!A:A, "")}
A60: https://en.wikipedia.org/wiki/East_Carolina_University | B60: East Carolina University | C60: East Carolina | D60: Pirates | E60: Greenville | F60: NC | G60: Public | H60: FBS | I60: American Conference | J60: {=XLOOKUP(B60, 'name-mapping-football'!C:C, 'name-mapping-football'!A:A, "")} -> https://www.sports-reference.com/cfb/schools/east-carolina/
A61: https://en.wikipedia.org/wiki/Eastern_Illinois_University | B61: Eastern Illinois University | C61: Eastern Illinois | D61: Panthers | E61: Charleston | F61: IL | G61: Public | H61: FCS | I61: Ohio Valley Conference | J61: {=XLOOKUP(B61, 'name-mapping-football'!C:C, 'name-mapping-football'!A:A, "")}
A62: https://en.wikipedia.org/wiki/Eastern_Kentucky_University | B62: Eastern Kentucky University | C62: Eastern Kentucky | D62: Colonels | E62: Richmond | F62: KY | G62: Public | H62: FCS | I62: Atlantic Sun Conference | J62: {=XLOOKUP(B62, 'name-mapping-football'!C:C, 'name-mapping-football'!A:A, "")}
A63: https://en.wikipedia.org/wiki/Eastern_Michigan_University | B63: Eastern Michigan University | C63: Eastern Michigan | D63: Eagles | E63: Ypsilanti | F63: MI | G63: Public | H63: FBS | I63: Mid-American Conference | J63: {=XLOOKUP(B63, 'name-mapping-football'!C:C, 'name-mapping-football'!A:A, "")} -> https://www.sports-reference.com/cfb/schools/eastern-michigan/
A64: https://en.wikipedia.org/wiki/Eastern_Washington_University | B64: Eastern Washington University | C64: Eastern Washington | D64: Eagles | E64: Cheney | F64: WA | G64: Public | H64: FCS | I64: Big Sky Conference | J64: {=XLOOKUP(B64, 'name-mapping-football'!C:C, 'name-mapping-football'!A:A, "")}
A65: https://en.wikipedia.org/wiki/East_Tennessee_State_University | B65: East Tennessee State University | C65: East Tennessee State | D65: Buccaneers | E65: Johnson City | F65: TN | G65: Public | H65: FCS | I65: Southern Conference | J65: {=XLOOKUP(B65, 'name-mapping-football'!C:C, 'name-mapping-football'!A:A, "")}
A66: https://en.wikipedia.org/wiki/East_Texas_A%26M_University | B66: East Texas A&M University | C66: East Texas A&M | D66: Lions | E66: Commerce | F66: TX | G66: Public | H66: FCS | I66: Southland Conference | J66: {=XLOOKUP(B66, 'name-mapping-football'!C:C, 'name-mapping-football'!A:A, "")}
A67: https://en.wikipedia.org/wiki/Elon_University | B67: Elon University | C67: Elon | D67: Phoenix | E67: Elon | F67: NC | G67: Private | H67: FCS | I67: Coastal Athletic Association | J67: {=XLOOKUP(B67, 'name-mapping-football'!C:C, 'name-mapping-football'!A:A, "")}
A68: https://en.wikipedia.org/wiki/Fairfield_University | B68: Fairfield University | C68: Fairfield | D68: Stags | E68: Fairfield | F68: CT | G68: Private | H68: Non-football | I68: Metro Atlantic Athletic Conference | J68: {=XLOOKUP(B68, 'name-mapping-football'!C:C, 'name-mapping-football'!A:A, "")} | K68: 0 | L68: 0 | M68: 0
A69: https://en.wikipedia.org/wiki/Fairleigh_Dickinson_University | B69: Fairleigh Dickinson University | C69: Fairleigh Dickinson | D69: Knights | E69: Hackensack | F69: NJ | G69: Private | H69: Non-football | I69: NEC | J69: {=XLOOKUP(B69, 'name-mapping-football'!C:C, 'name-mapping-football'!A:A, "")} | K69: 0 | L69: 0 | M69: 0
A70: https://en.wikipedia.org/wiki/Florida_A%26M_University | B70: Florida Agricultural and Mechanical University | C70: Florida A&M | D70: Rattlers | E70: Tallahassee | F70: FL | G70: Public | H70: FCS | I70: Southwestern Athletic Conference | J70: {=XLOOKUP(B70, 'name-mapping-football'!C:C, 'name-mapping-football'!A:A, "")}
A71: https://en.wikipedia.org/wiki/Florida_Atlantic_University | B71: Florida Atlantic University | C71: Florida Atlantic | D71: Owls | E71: Boca Raton | F71: FL | G71: Public | H71: FBS | I71: American Conference | J71: {=XLOOKUP(B71, 'name-mapping-football'!C:C, 'name-mapping-football'!A:A, "")} -> https://www.sports-reference.com/cfb/schools/florida-atlantic/
A72: https://en.wikipedia.org/wiki/Florida_Gulf_Coast_University | B72: Florida Gulf Coast University | C72: FGCU | D72: Eagles | E72: Fort Myers | F72: FL | G72: Public | H72: Non-football | I72: Atlantic Sun Conference | J72: {=XLOOKUP(B72, 'name-mapping-football'!C:C, 'name-mapping-football'!A:A, "")} | K72: 0 | L72: 0 | M72: 0
A73: https://en.wikipedia.org/wiki/Florida_International_University | B73: Florida International University | C73: FIU | D73: Panthers | E73: Miami | F73: FL | G73: Public | H73: FBS | I73: Conference USA | J73: {=XLOOKUP(B73, 'name-mapping-football'!C:C, 'name-mapping-football'!A:A, "")} -> https://www.sports-reference.com/cfb/schools/florida-international/
A74: https://en.wikipedia.org/wiki/Florida_State_University | B74: Florida State University | C74: Florida State | D74: Seminoles | E74: Tallahassee | F74: FL | G74: Public | H74: FBS | I74: Atlantic Coast Conference | J74: {=XLOOKUP(B74, 'name-mapping-football'!C:C, 'name-mapping-football'!A:A, "")} -> https://www.sports-reference.com/cfb/schools/florida-state/
A75: https://en.wikipedia.org/wiki/Fordham_University | B75: Fordham University | C75: Fordham | D75: Rams | E75: Bronx | F75: NY | G75: Private | H75: FCS | I75: Atlantic 10 Conference | J75: {=XLOOKUP(B75, 'name-mapping-football'!C:C, 'name-mapping-football'!A:A, "")}
A76: https://en.wikipedia.org/wiki/Furman_University | B76: Furman University | C76: Furman | D76: Paladins | E76: Greenville | F76: SC | G76: Private | H76: FCS | I76: Southern Conference | J76: {=XLOOKUP(B76, 'name-mapping-football'!C:C, 'name-mapping-football'!A:A, "")}
A77: https://en.wikipedia.org/wiki/Gardner%E2%80%93Webb_University | B77: Gardner–Webb University | C77: Gardner–Webb | D77: Runnin' Bulldogs | E77: Boiling Springs | F77: NC | G77: Private | H77: FCS | I77: Big South Conference | J77: {=XLOOKUP(B77, 'name-mapping-football'!C:C, 'name-mapping-football'!A:A, "")}
A78: https://en.wikipedia.org/wiki/George_Mason_University | B78: George Mason University | C78: George Mason | D78: Patriots | E78: Fairfax | F78: VA | G78: Public | H78: Non-football | I78: Atlantic 10 Conference | J78: {=XLOOKUP(B78, 'name-mapping-football'!C:C, 'name-mapping-football'!A:A, "")} | K78: 0 | L78: 0 | M78: 0
A79: https://en.wikipedia.org/wiki/Georgetown_University | B79: Georgetown University | C79: Georgetown | D79: Hoyas | E79: Washington | F79: DC | G79: Private | H79: FCS | I79: Big East Conference | J79: {=XLOOKUP(B79, 'name-mapping-football'!C:C, 'name-mapping-football'!A:A, "")}
A80: https://en.wikipedia.org/wiki/Georgia_Tech | B80: Georgia Institute of Technology | C80: Georgia Tech | D80: Yellow Jackets | E80: Atlanta | F80: GA | G80: Public | H80: FBS | I80: Atlantic Coast Conference | J80: {=XLOOKUP(B80, 'name-mapping-football'!C:C, 'name-mapping-football'!A:A, "")} -> https://www.sports-reference.com/cfb/schools/georgia-tech/
A81: https://en.wikipedia.org/wiki/Georgia_Southern_University | B81: Georgia Southern University | C81: Georgia Southern | D81: Eagles | E81: Statesboro | F81: GA | G81: Public | H81: FBS | I81: Sun Belt Conference | J81: {=XLOOKUP(B81, 'name-mapping-football'!C:C, 'name-mapping-football'!A:A, "")} -> https://www.sports-reference.com/cfb/schools/georgia-southern/
A82: https://en.wikipedia.org/wiki/Georgia_State_University | B82: Georgia State University | C82: Georgia State | D82: Panthers | E82: Atlanta | F82: GA | G82: Public | H82: FBS | I82: Sun Belt Conference | J82: {=XLOOKUP(B82, 'name-mapping-football'!C:C, 'name-mapping-football'!A:A, "")} -> https://www.sports-reference.com/cfb/schools/georgia-state/
A83: https://en.wikipedia.org/wiki/Gonzaga_University | B83: Gonzaga University | C83: Gonzaga | D83: Bulldogs | E83: Spokane | F83: WA | G83: Private | H83: Non-football | I83: West Coast Conference | J83: {=XLOOKUP(B83, 'name-mapping-football'!C:C, 'name-mapping-football'!A:A, "")} | K83: 0 | L83: 0 | M83: 0
A84: https://en.wikipedia.org/wiki/Grambling_State_University | B84: Grambling State University | C84: Grambling State | D84: Tigers | E84: Grambling | F84: LA | G84: Public | H84: FCS | I84: Southwestern Athletic Conference | J84: {=XLOOKUP(B84, 'name-mapping-football'!C:C, 'name-mapping-football'!A:A, "")}
A85: https://en.wikipedia.org/wiki/Grand_Canyon_University | B85: Grand Canyon University | C85: Grand Canyon | D85: Antelopes | E85: Phoenix | F85: AZ | G85: Private | H85: Non-football | I85: Mountain West Conference | J85: {=XLOOKUP(B85, 'name-mapping-football'!C:C, 'name-mapping-football'!A:A, "")} | K85: 0 | L85: 0 | M85: 0
A86: https://en.wikipedia.org/wiki/Hampton_University | B86: Hampton University | C86: Hampton | D86: Pirates | E86: Hampton | F86: VA | G86: Private | H86: FCS | I86: Coastal Athletic Association | J86: {=XLOOKUP(B86, 'name-mapping-football'!C:C, 'name-mapping-football'!A:A, "")}
A87: https://en.wikipedia.org/wiki/Harvard_University | B87: Harvard University | C87: Harvard | D87: Crimson | E87: Cambridge | F87: MA | G87: Private | H87: FCS | I87: Ivy League | J87: {=XLOOKUP(B87, 'name-mapping-football'!C:C, 'name-mapping-football'!A:A, "")}
A88: https://en.wikipedia.org/wiki/High_Point_University | B88: High Point University | C88: High Point | D88: Panthers | E88: High Point | F88: NC | G88: Private | H88: Non-football | I88: Big South Conference | J88: {=XLOOKUP(B88, 'name-mapping-football'!C:C, 'name-mapping-football'!A:A, "")} | K88: 0 | L88: 0 | M88: 0
A89: https://en.wikipedia.org/wiki/Hofstra_University | B89: Hofstra University | C89: Hofstra | D89: Pride | E89: Hempstead | F89: NY | G89: Private | H89: Non-football | I89: Coastal Athletic Association | J89: {=XLOOKUP(B89, 'name-mapping-football'!C:C, 'name-mapping-football'!A:A, "")} | K89: 0 | L89: 0 | M89: 0
A90: https://en.wikipedia.org/wiki/Houston_Christian_University | B90: Houston Christian University | C90: Houston Christian | D90: Huskies | E90: Houston | F90: TX | G90: Private | H90: FCS | I90: Southland Conference | J90: {=XLOOKUP(B90, 'name-mapping-football'!C:C, 'name-mapping-football'!A:A, "")}
A91: https://en.wikipedia.org/wiki/Howard_University | B91: Howard University | C91: Howard | D91: Bison | E91: Washington | F91: DC | G91: Private | H91: FCS | I91: Mid-Eastern Athletic Conference | J91: {=XLOOKUP(B91, 'name-mapping-football'!C:C, 'name-mapping-football'!A:A, "")}
A92: https://en.wikipedia.org/wiki/Idaho_State_University | B92: Idaho State University | C92: Idaho State | D92: Bengals | E92: Pocatello | F92: ID | G92: Public | H92: FCS | I92: Big Sky Conference | J92: {=XLOOKUP(B92, 'name-mapping-football'!C:C, 'name-mapping-football'!A:A, "")}
A93: https://en.wikipedia.org/wiki/Illinois_State_University | B93: Illinois State University | C93: Illinois State | D93: Redbirds | E93: Normal | F93: IL | G93: Public | H93: FCS | I93: Missouri Valley Conference | J93: {=XLOOKUP(B93, 'name-mapping-football'!C:C, 'name-mapping-football'!A:A, "")}
A94: https://en.wikipedia.org/wiki/Indiana_State_University | B94: Indiana State University | C94: Indiana State | D94: Sycamores | E94: Terre Haute | F94: IN | G94: Public | H94: FCS | I94: Missouri Valley Conference | J94: {=XLOOKUP(B94, 'name-mapping-football'!C:C, 'name-mapping-football'!A:A, "")}
A95: https://en.wikipedia.org/wiki/Indiana_University_Bloomington | B95: Indiana University Bloomington | C95: Indiana | D95: Hoosiers | E95: Bloomington | F95: IN | G95: Public | H95: FBS | I95: Big Ten Conference | J95: {=XLOOKUP(B95, 'name-mapping-football'!C:C, 'name-mapping-football'!A:A, "")} -> https://www.sports-reference.com/cfb/schools/indiana/
A96: https://en.wikipedia.org/wiki/Indiana_University_Indianapolis | B96: Indiana University Indianapolis | C96: IU Indy | D96: Jaguars | E96: Indianapolis | F96: IN | G96: Public | H96: Non-football | I96: Horizon League | J96: {=XLOOKUP(B96, 'name-mapping-football'!C:C, 'name-mapping-football'!A:A, "")} | K96: 0 | L96: 0 | M96: 0
A97: https://en.wikipedia.org/wiki/Iona_University | B97: Iona University | C97: Iona | D97: Gaels | E97: New Rochelle | F97: NY | G97: Private | H97: Non-football | I97: Metro Atlantic Athletic Conference | J97: {=XLOOKUP(B97, 'name-mapping-football'!C:C, 'name-mapping-football'!A:A, "")} | K97: 0 | L97: 0 | M97: 0
A98: https://en.wikipedia.org/wiki/Iowa_State_University | B98: Iowa State University of Science and Technology | C98: Iowa State | D98: Cyclones | E98: Ames | F98: IA | G98: Public | H98: FBS | I98: Big 12 Conference | J98: {=XLOOKUP(B98, 'name-mapping-football'!C:C, 'name-mapping-football'!A:A, "")} -> https://www.sports-reference.com/cfb/schools/iowa-state/
A99: https://en.wikipedia.org/wiki/Jackson_State_University | B99: Jackson State University | C99: Jackson State | D99: Tigers | E99: Jackson | F99: MS | G99: Public | H99: FCS | I99: Southwestern Athletic Conference | J99: {=XLOOKUP(B99, 'name-mapping-football'!C:C, 'name-mapping-football'!A:A, "")}
A100: https://en.wikipedia.org/wiki/Jacksonville_State_University | B100: Jacksonville State University | C100: Jax State | D100: Gamecocks | E100: Jacksonville | F100: AL | G100: Public | H100: FBS | I100: Conference USA | J100: {=XLOOKUP(B100, 'name-mapping-football'!C:C, 'name-mapping-football'!A:A, "")} -> https://www.sports-reference.com/cfb/schools/jacksonville-state/
...

Sheet name-mapping-football
A1: School url | B1: Website Name | C1: University | D1: Nickname
A2: https://www.sports-reference.com/cfb/schools/air-force/ | B2: Air Force | C2: United States Air Force Academy | D2: Falcons
A3: https://www.sports-reference.com/cfb/schools/akron/ | B3: Akron | C3: The University of Akron | D3: Zips
A4: https://www.sports-reference.com/cfb/schools/alabama/ | B4: Alabama | C4: The University of Alabama | D4: Crimson Tide
A5: https://www.sports-reference.com/cfb/schools/appalachian-state/ | B5: Appalachian State | C5: Appalachian State University | D5: Mountaineers
A6: https://www.sports-reference.com/cfb/schools/arizona/ | B6: Arizona | C6: University of Arizona | D6: Wildcats
A7: https://www.sports-reference.com/cfb/schools/arizona-state/ | B7: Arizona State | C7: Arizona State University | D7: Sun Devils
A8: https://www.sports-reference.com/cfb/schools/arkansas/ | B8: Arkansas | C8: University of Arkansas | D8: Razorbacks
A9: https://www.sports-reference.com/cfb/schools/arkansas-state/ | B9: Arkansas State | C9: Arkansas State University | D9: Red Wolves
A10: https://www.sports-reference.com/cfb/schools/army/ | B10: Army | C10: United States Military Academy | D10: Black Knights
A11: https://www.sports-reference.com/cfb/schools/auburn/ | B11: Auburn | C11: Auburn University | D11: Tigers
A12: https://www.sports-reference.com/cfb/schools/ball-state/ | B12: Ball State | C12: Ball State University | D12: Cardinals
... A137: https://www.sports-reference.com/cfb/schools/wyoming/ | B137: Wyoming | C137: University of Wyoming | D137: Cowboys

Sheet school_urls-football
A1: School url | B1: Common Name | C1: From | D1: To | E1: Yrs | F1: Overall G | G1: Overall W | H1: Overall L | I1: Overall T | J1: Overall Pct | K1: Bowls G | L1: Bowls W | M1: Bowls L | N1: Bowls T | O1: Bowls PCT | P1: SRS SRS | Q1: SRS SOS | R1: AP | S1: CC
A2: https://www.sports-reference.com/cfb/schools/air-force/ | B2: Air Force | C2: 1957 | D2: 2025 | E2: 69 | F2: 803 | G2: 436 | H2: 355 | I2: 12 | J2: 0.55 | K2: 30 | L2: 16 | M2: 13 | N2: 1 | O2: 0.55 | P2: 1.09 | Q2: -0.94 | R2: 7 | S2: 3
A3: https://www.sports-reference.com/cfb/schools/akron/ | B3: Akron | C3: 1975 | D3: 2025 | E3: 40 | F3: 461 | G3: 166 | H3: 292 | I3: 3 | J3: 0.363 | K3: 3 | L3: 1 | M3: 2 | N3: 0.333 | O3: -12.06 | P3: -6.58 | Q3: 1 | R3: 0 | S3: 0
A4: https://www.sports-reference.com/cfb/schools/alabama/ | B4: Alabama | C4: 1902 | D4: 2025 | E4: 122 | F4: 1360 | G4: 999 | H4: 319 | I4: 42 | J4: 0.75 | K4: 80 | L4: 47 | M4: 30 | N4: 3 | O4: 0.606 | P4: 13.86 | Q4: 4.33 | R4: 63 | S4: 30
A5: https://www.sports-reference.com/cfb/schools/alameda-coast-guard/ | B5: Alameda Coast Guard | C5: 1943 | D5: 1944 | E5: 2 | F5: 15 | G5: 8 | H5: 4 | I5: 3 | J5: 0.633 | K5: -0.16 | L5: -5.13 | M5: 0 | N5: 0 | O5: 0 | P5: 0 | R5: 0 | S5: 0
A6: https://www.sports-reference.com/cfb/schools/alcorn-state/ | B6: Alcorn State | C6: 1977 | D6: 1977 | E6: 1 | F6: 11 | G6: 3 | H6: 8 | I6: 0.273 | J6: -17.1 | K6: -9.19 | L6: 0 | M6: 0 | N6: 0 | O6: 0 | P6: 0 | R6: 0 | S6: 0
A7: https://www.sports-reference.com/cfb/schools/amarillo-field/ | B7: Amarillo Field | C7: 1944 | D7: 1944 | E7: 1 | F7: 8 | G7: 5 | H7: 3 | I7: 0.625 | J7: 5.1 | K7: -1.78 | L7: 0 | M7: 0 | N7: 0 | O7: 0 | P7: 0 | R7: 0 | S7: 0
A8: https://www.sports-reference.com/cfb/schools/amherst/ | B8: Amherst | C8: 1877 | D8: 1906 | E8: 25 | F8: 239 | G8: 108 | H8: 109 | I8: 22 | J8: 0.498 | K8: -1.08 | L8: 0 | M8: 0 | N8: 0 | O8: 0 | P8: -0.09 | R8: 0 | S8: 0
A9: https://www.sports-reference.com/cfb/schools/appalachian-state/ | B9: Appalachian State | C9: 1972 | D9: 2025 | E9: 22 | F9: 264 | G9: 154 | H9: 105 | I9: 5 | J9: 0.593 | K9: 9 | L9: 7 | M9: 2 | N9: 0 | O9: 0.778 | P9: -1.45 | Q9: -5.93 | R9: 1 | S9: 4
A10: https://www.sports-reference.com/cfb/schools/arizona/ | B10: Arizona | C10: 1931 | D10: 2025 | E10: 92 | F10: 1010 | G10: 519 | H10: 468 | I10: 23 | J10: 0.525 | K10: 22 | L10: 10 | M10: 11 | N10: 1 | O10: 0.477 | P10: 1.45 | Q10: 0.71 | R10: 8 | S10: 6
A11: https://www.sports-reference.com/cfb/schools/arizona-state/ | B11: Arizona State | C11: 1931 | D11: 2025 | E11: 92 | F11: 1018 | G11: 611 | H11: 389 | I11: 18 | J11: 0.609 | K11: 35 | L11: 15 | M11: 19 | N11: 1 | O11: 0.443 | P11: 3.53 | Q11: -1.08 | R11: 18 | S11: 18
A12: https://www.sports-reference.com/cfb/schools/arkansas/ | B12: Arkansas | C12: 1906 | D12: 2025 | E12: 120 | F12: 1284 | G12: 715 | H12: 532 | I12: 37 | J12: 0.571 | K12: 45 | L12: 18 | M12: 24 | N12: 3 | O12: 0.433 | P12: 6.39 | Q12: 3.13 | R12: 29 | S12: 14
A13: https://www.sports-reference.com/cfb/schools/arkansas-state/ | B13: Arkansas State | C13: 1974 | D13: 2025 | E13: 44 | F13: 518 | G13: 231 | H13: 285 | I13: 2 | J13: 0.448 | K13: 13 | L13: 6 | M13: 7 | N13: 0 | O13: 0.462 | P13: -8.88 | Q13: -6.48 | R13: 0 | S13: 7
A14: https://www.sports-reference.com/cfb/schools/army/ | B14: Army | C14: 1891 | D14: 2025 | E14: 132 | F14: 1329 | G14: 732 | H14: 546 | I14: 51 | J14: 0.57 | K14: 12 | L14: 9 | M14: 3 | N14: 0 | O14: 0.75 | P14: 3.29 | Q14: -0.36 | R14: 16 | S14: 1
A15: https://www.sports-reference.com/cfb/schools/auburn/ | B15: Auburn | C15: 1902 | D15: 2025 | E15: 123 | F15: 1301 | G15: 783 | H15: 475 | I15: 43 | J15: 0.618 | K15: 47 | L15: 24 | M15: 21 | N15: 2 | O15: 0.532 | P15: 8.79 | Q15: 4.57 | R15: 40 | S15: 8
A16: https://www.sports-reference.com/cfb/schools/ball-state/ | B16: Ball State | C16: 1975 | D16: 2025 | E16: 51 | F16: 588 | G16: 280 | H16: 304 | I16: 4 | J16: 0.48 | K16: 9 | L16: 1 | M16: 8 | N16: 0 | O16: 0.111 | P16: -8.13 | Q16: -6.97 | R16: 1 | S16: 6
A17: https://www.sports-reference.com/cfb/schools/bates/ | B17: Bates | C17: 1901 | D17: 1905 | E17: 3 | F17: 21 | G17: 10 | H17: 8 | I17: 3 | J17: 0.548 | K17: -0.94 | L17: 0 | M17: 0 | N17: 0 | O17: 0 | P17: -1.28 | R17: 0 | S17: 0
A18: https://www.sports-reference.com/cfb/schools/baylor/ | B18: Baylor | C18: 1903 | D18: 2025 | E18: 120 | F18: 1277 | G18: 631 | H18: 605 | I18: 41 | J18: 0.51 | K18: 28 | L18: 14 | M18: 14 | N18: 0 | O18: 0.5 | P18: 2.82 | Q18: 2.71 | R18: 16 | S18: 9
A19: https://www.sports-reference.com/cfb/schools/beloit/ | B19: Beloit | C19: 1894 | D19: 1905 | E19: 9 | F19: 85 | G19: 39 | H19: 36 | I19: 10 | J19: 0.518 | K19: -1.3 | L19: 0 | M19: 0 | N19: 0 | O19: 0 | P19: -1.39 | R19: 0 | S19: 0
A20: https://www.sports-reference.com/cfb/schools/birmingham-southern/ | B20: Birmingham-Southern | C20: 1920 | D20: 1924 | E20: 4 | F20: 36 | G20: 16 | H20: 17 | I20: 3 | J20: 0.486 | K20: -5.29 | L20: 0 | M20: 0 | N20: 0 | O20: 0 | P20: -4.68 | R20: 0 | S20: 0
A21: https://www.sports-reference.com/cfb/schools/boise-state/ | B21: Boise State | C21: 1996 | D21: 2025 | E21: 30 | F21: 384 | G21: 292 | H21: 92 | I21: 0.76 | J21: 23 | K21: 13 | L21: 0 | M21: 10 | N21: 0 | O21: 0.565 | P21: 6.04 | Q21: -3.86 | R21: 14 | S21: 17
A22: https://www.sports-reference.com/cfb/schools/boston-college/ | B22: Boston College | C22: 1901 | D22: 2025 | E22: 91 | F22: 990 | G22: 537 | H22: 439 | I22: 14 | J22: 0.549 | K22: 29 | L22: 15 | M22: 14 | N22: 0 | O22: 0.517 | P22: 1.74 | Q22: 0.07 | R22: 14 | S22: 1
A23: https://www.sports-reference.com/cfb/schools/boston-university/ | B23: Boston University | C23: 1923 | D23: 1964 | E23: 20 | F23: 170 | G23: 73 | H23: 90 | I23: 7 | J23: 0.45 | K23: -6.91 | L23: 0 | M23: 0 | N23: 0 | O23: 0 | P23: -4.99 | Q23: 1 | R23: 0
A24: https://www.sports-reference.com/cfb/schools/bowdoin/ | B24: Bowdoin | C24: 1896 | D24: 1905 | E24: 7 | F24: 66 | G24: 33 | H24: 30 | I24: 3 | J24: 0.523 | K24: -2.71 | L24: 0 | M24: 0 | N24: 0 | O24: 0 | P24: -2.47 | R24: 0 | S24: 0
A25: https://www.sports-reference.com/cfb/schools/bowling-green-state/ | B25: Bowling Green | C25: 1962 | D25: 2025 | E25: 64 | F25: 722 | G25: 383 | H25: 328 | I25: 11 | J25: 0.538 | K25: 15 | L25: 5 | M25: 10 | N25: 0 | O25: 0.333 | P25: -5.41 | Q25: -6.39 | R25: 1 | S25: 9
A26: https://www.sports-reference.com/cfb/schools/bradley/ | B26: Bradley | C26: 1949 | D26: 1951 | E26: 3 | F26: 29 | G26: 14 | H26: 15 | I26: 0.483 | J26: -12.91 | K26: -12.75 | L26: 0 | M26: 0 | N26: 0 | O26: 0 | P26: 0 | R26: 0 | S26: 0
A27: https://www.sports-reference.com/cfb/schools/brown/ | B27: Brown | C27: 1878 | D27: 1981 | E27: 93 | F27: 858 | G27: 431 | H27: 392 | I27: 35 | J27: 0.523 | K27: 1 | L27: 0 | M27: 1 | N27: 0 | O27: 0 | P27: -2.89 | Q27: -3.54 | R27: 0 | S27: 1
A28: https://www.sports-reference.com/cfb/schools/bucknell/ | B28: Bucknell | C28: 1888 | D28: 1946 | E28: 40 | F28: 357 | G28: 168 | H28: 157 | I28: 32 | J28: 0.515 | K28: 1 | L28: 1 | M28: 0 | N28: 0 | O28: 1 | P28: -2.93 | Q28: -2.85 | R28: 0 | S28: 0
A29: https://www.sports-reference.com/cfb/schools/buffalo/ | B29: Buffalo | C29: 1962 | D29: 2025 | E29: 36 | F29: 409 | G29: 163 | H29: 241 | I29: 4 | J29: 0.404 | K29: 7 | L29: 4 | M29: 3 | N29: 0 | O29: 0.571 | P29: -9.8 | Q29: -7.11 | R29: 1 | S29: 1
A30: https://www.sports-reference.com/cfb/schools/butler/ | B30: Butler | C30: 1932 | D30: 1933 | E30: 2 | F30: 15 | G30: 4 | H30: 10 | I30: 1 | J30: 0.3 | K30: -16.48 | L30: 0 | M30: 0 | N30: 0 | O30: 0 | P30: -10.26 | R30: 0 | S30: 0
A31: https://www.sports-reference.com/cfb/schools/brigham-young/ | B31: BYU | C31: 1922 | D31: 2025 | E31: 101 | F31: 1112 | G31: 639 | H31: 447 | I31: 26 | J31: 0.586 | K31: 42 | L31: 19 | M31: 22 | N31: 1 | O31: 0.464 | P31: -0.43 | Q31: -2.91 | R31: 21 | S31: 23
A32: https://www.sports-reference.com/cfb/schools/cal-state-fullerton/ | B32: Cal State Fullerton | C32: 1975 | D32: 1992 | E32: 18 | F32: 205 | G32: 76 | H32: 127 | I32: 2 | J32: 0.376 | K32: 1 | L32: 0 | M32: 1 | N32: 0 | O32: 0 | P32: -12.72 | Q32: -7.22 | R32: 0 | S32: 2
A33: https://www.sports-reference.com/cfb/schools/cal-state-los-angeles/ | B33: Cal State Los Angeles | C33: 1969 | D33: 1971 | E33: 3 | F33: 29 | G33: 3 | H33: 26 | I33: 0.103 | J33: -27.59 | K33: -9.75 | L33: 0 | M33: 0 | N33: 0 | O33: 0 | P33: 0 | R33: 0 | S33: 0
A34: https://www.sports-reference.com/cfb/schools/california/ | B34: California | C34: 1916 | D34: 2025 | E34: 110 | F34: 1195 | G34: 608 | H34: 556 | I34: 31 | J34: 0.522 | K34: 27 | L34: 12 | M34: 14 | N34: 1 | O34: 0.463 | P34: 5.11 | Q34: 3.94 | R34: 14 | S34: 13
A35: https://www.sports-reference.com/cfb/schools/california-santa-barbara/ | B35: California-Santa Barbara | C35: 1969 | D35: 1971 | E35: 3 | F35: 32 | G35: 11 | H35: 21 | I35: 0.344 | J35: -13.35 | K35: -7.22 | L35: 0 | M35: 0 | N35: 0 | O35: 0 | P35: 0 | R35: 0 | S35: 0
A36: https://www.sports-reference.com/cfb/schools/camp-grant/ | B36: Camp Grant | C36: 1943 | D36: 1943 | E36: 1 | F36: 10 | G36: 2 | H36: 6 | I36: 2 | J36: 0.3 | K36: 8.98 | L36: 0 | M36: 0 | N36: 0 | O36: 0 | P36: 14.38 | R36: 0 | S36: 0
A37: https://www.sports-reference.com/cfb/schools/carlisle/ | B37: Carlisle | C37: 1896 | D37: 1917 | E37: 21 | F37: 252 | G37: 165 | H37: 77 | I37: 10 | J37: 0.675 | K37: 8.26 | L37: 0 | M37: 0 | N37: 0 | O37: 0 | P37: 0.94 | R37: 0 | S37: 0
A38: https://www.sports-reference.com/cfb/schools/carnegie-mellon/ | B38: Carnegie Mellon | C38: 1910 | D38: 1940 | E38: 20 | F38: 172 | G38: 84 | H38: 75 | I38: 13 | J38: 0.526 | K38: 1 | L38: 0 | M38: 1 | N38: 0 | O38: 0 | P38: 4.03 | Q38: 1.5 | R38: 1 | S38: 0
A39: https://www.sports-reference.com/cfb/schools/centenary-la/ | B39: Centenary (LA) | C39: 1930 | D39: 1941 | E39: 12 | F39: 131 | G39: 69 | H39: 48 | I39: 14 | J39: 0.58 | K39: 1 | L39: 0 | M39: 0 | N39: 1 | O39: 0.5 | P39: 0.22 | Q39: -1.79 | R39: 0 | S39: 0
A40: https://www.sports-reference.com/cfb/schools/central-michigan/ | B40: Central Michigan | C40: 1975 | D40: 2025 | E40: 51 | F40: 593 | G40: 313 | H40: 269 | I40: 11 | J40: 0.537 | K40: 14 | L40: 4 | M40: 10 | N40: 0 | O40: 0.286 | P40: -6.67 | Q40: -7.62 | R40: 1 | S40: 7
A41: https://www.sports-reference.com/cfb/schools/centre/ | B41: Centre | C41: 1919 | D41: 1935 | E41: 8 | F41: 74 | G41: 51 | H41: 20 | I41: 3 | J41: 0.709 | K41: 3 | L41: 2 | M41: 1 | N41: 0 | O41: 0.667 | P41: 9.14 | Q41: -0.02 | R41: 0 | S41: 0
A42: https://www.sports-reference.com/cfb/schools/charlotte/ | B42: Charlotte | C42: 2015 | D42: 2025 | E42: 11 | F42: 127 | G42: 38 | H42: 89 | I42: 0.299 | J42: 1 | K42: 1 | L42: 0 | M42: 0 | N42: 0 | O42: 0 | P42: -13.49 | Q42: -4.86 | R42: 0 | S42: 0
A43: https://www.sports-reference.com/cfb/schools/chattanooga/ | B43: Chattanooga | C43: 1909 | D43: 1981 | E43: 22 | F43: 218 | G43: 105 | H43: 100 | I43: 13 | J43: 0.511 | K43: -5.92 | L43: 0 | M43: 0 | N43: 0 | O43: 0 | P43: -6.18 | Q43: 3 | R43: 0
A44: https://www.sports-reference.com/cfb/schools/chicago/ | B44: Chicago | C44: 1892 | D44: 1939 | E44: 48 | F44: 466 | G44: 287 | H44: 147 | I44: 32 | J44: 0.65 | K44: 7.28 | L44: 0 | M44: 0 | N44: 0 | O44: 0 | P44: 2.92 | Q44: 7 | R44: 0
A45: https://www.sports-reference.com/cfb/schools/cincinnati/ | B45: Cincinnati | C45: 1954 | D45: 2025 | E45: 72 | F45: 816 | G45: 409 | H45: 395 | I45: 12 | J45: 0.509 | K45: 20 | L45: 8 | M45: 12 | N45: 0 | O45: 0.4 | P45: -2.09 | Q45: -2.14 | R45: 8 | S45: 10
A46: https://www.sports-reference.com/cfb/schools/clemson/ | B46: Clemson | C46: 1902 | D46: 2025 | E46: 124 | F46: 1314 | G46: 795 | H46: 475 | I46: 44 | J46: 0.622 | K46: 52 | L46: 27 | M46: 25 | N46: 0 | O46: 0.519 | P46: 5.86 | Q46: 1.78 | R46: 38 | S46: 24
A47: https://www.sports-reference.com/cfb/schools/coast-guard/ | B47: Coast Guard | C47: 1944 | D47: 1945 | E47: 2 | F47: 17 | G47: 6 | H47: 10 | I47: 1 | J47: 0.382 | K47: -4.68 | L47: 0 | M47: 0 | N47: 0 | O47: 0 | P47: -1.1 | R47: 0 | S47: 0
A48: https://www.sports-reference.com/cfb/schools/coastal-carolina/ | B48: Coastal Carolina | C48: 2017 | D48: 2025 | E48: 9 | F48: 113 | G48: 64 | H48: 49 | I48: 0.566 | J48: 6 | K48: 2 | L48: 0 | M48: 4 | N48: 0 | O48: 0.333 | P48: -3.79 | Q48: -4.61 | R48: 1 | S48: 1
A49: https://www.sports-reference.com/cfb/schools/coe/ | B49: Coe | C49: 1905 | D49: 1905 | E49: 1 | F49: 9 | G49: 1 | H49: 7 | I49: 1 | J49: 0.167 | K49: -18.57 | L49: 0 | M49: 0 | N49: 0 | O49: 0 | P49: -4.35 | R49: 0 | S49: 0
A50: https://www.sports-reference.com/cfb/schools/colby/ | B50: Colby | C50: 1904 | D50: 1904 | E50: 1 | F50: 7 | G50: 2 | H50: 4 | I50: 1 | J50: 0.357 | K50: -5.3 | L50: 0 | M50: 0 | N50: 0 | O50: 0 | P50: 1.55 | R50: 0 | S50: 0
A51: https://www.sports-reference.com/cfb/schools/colgate/ | B51: Colgate | C51: 1905 | D51: 1981 | E51: 76 | F51: 670 | G51: 363 | H51: 266 | I51: 41 | J51: 0.572 | K51: -0.87 | L51: 0 | M51: 0 | N51: 0 | O51: 0 | P51: -4.01 | R51: 0 | S51: 0
A52: https://www.sports-reference.com/cfb/schools/colorado/ | B52: Colorado | C52: 1902 | D52: 2025 | E52: 124 | F52: 1248 | G52: 682 | H52: 530 | I52: 35 | J52: 0.561 | K52: 31 | L52: 12 | M52: 19 | N52: 0 | O52: 0.387 | P52: 3.85 | Q52: 1.48 | R52: 20 | S52: 19
A53: https://www.sports-reference.com/cfb/schools/colorado-college/ | B53: Colorado College | C53: 1902 | D53: 1945 | E53: 39 | F53: 296 | G53: 169 | H53: 109 | I53: 18 | J53: 0.601 | K53: -1.27 | L53: 0 | M53: 0 | N53: 0 | O53: 0 | P53: -4.88 | Q53: 1 | R53: 2
A54: https://www.sports-reference.com/cfb/schools/colorado-mines/ | B54: Colorado Mines | C54: 1902 | D54: 1937 | E54: 36 | F54: 239 | G54: 98 | H54: 128 | I54: 13 | J54: 0.437 | K54: -6.56 | L54: 0 | M54: 0 | N54: 0 | O54: 0 | P54: -4.56 | Q54: 3 | R54: 0
A55: https://www.sports-reference.com/cfb/schools/colorado-state/ | B55: Colorado State | C55: 1902 | D55: 2025 | E55: 118 | F55: 1179 | G55: 541 | H55: 607 | I55: 31 | J55: 0.472 | K55: 18 | L55: 6 | M55: 12 | N55: 0 | O55: 0.333 | P55: -4.11 | Q55: -2.97 | R55: 3 | S55: 15
A56: https://www.sports-reference.com/cfb/schools/columbia/ | B56: Columbia | C56: 1870 | D56: 1981 | E56: 84 | F56: 699 | G56: 282 | H56: 382 | I56: 35 | J56: 0.428 | K56: 1 | L56: 1 | M56: 0 | N56: 0 | O56: 1 | P56: -4.55 | Q56: -1.67 | R56: 2 | S56: 1
A57: https://www.sports-reference.com/cfb/schools/connecticut/ | B57: Connecticut | C57: 1979 | D57: 2025 | E57: 27 | F57: 316 | G57: 131 | H57: 183 | I57: 2 | J57: 0.418 | K57: 9 | L57: 4 | M57: 5 | N57: 0 | O57: 0.444 | P57: -6.18 | Q57: -2.89 | R57: 0 | S57: 2
A58: https://www.sports-reference.com/cfb/schools/cornell/ | B58: Cornell | C58: 1888 | D58: 1981 | E58: 93 | F58: 837 | G58: 488 | H58: 317 | I58: 32 | J58: 0.602 | K58: 2.2 | L58: 0 | M58: 0 | N58: 0 | O58: 0 | P58: -2.18 | Q58: 5 | R58: 1
A59: https://www.sports-reference.com/cfb/schools/cornell-college/ | B59: Cornell College | C59: 1903 | D59: 1903 | E59: 1 | F59: 9 | G59: 1 | H59: 8 | I59: 0.111 | J59: -14.48 | K59: -2.14 | L59: 0 | M59: 0 | N59: 0 | O59: 0 | P59: 0 | R59: 0 | S59: 0
A60: https://www.sports-reference.com/cfb/schools/creighton/ | B60: Creighton | C60: 1927 | D60: 1942 | E60: 16 | F60: 139 | G60: 61 | H60: 70 | I60: 8 | J60: 0.468 | K60: -6.26 | L60: 0 | M60: 0 | N60: 0 | O60: 0 | P60: -5.08 | Q60: 1 | R60: 0
A61: https://www.sports-reference.com/cfb/schools/cumberland/ | B61: Cumberland | C61: 1903 | D61: 1905 | E61: 2 | F61: 13 | G61: 7 | H61: 5 | I61: 1 | J61: 0.577 | K61: 5.07 | L61: 0 | M61: 0 | N61: 0 | O61: 0 | P61: -0.79 | R61: 0 | S61: 0
A62: https://www.sports-reference.com/cfb/schools/dartmouth/ | B62: Dartmouth | C62: 1881 | D62: 1981 | E62: 93 | F62: 795 | G62: 502 | H62: 258 | I62: 35 | J62: 0.653 | K62: 3.5 | L62: 0 | M62: 0 | N62: 0 | O62: 0 | P62: -2.81 | Q62: 5 | R62: 12
A63: https://www.sports-reference.com/cfb/schools/davidson/ | B63: Davidson | C63: 1902 | D63: 1973 | E63: 66 | F63: 600 | G63: 248 | H63: 312 | I63: 40 | J63: 0.447 | K63: 1 | L63: 0 | M63: 1 | N63: 0 | O63: 0 | P63: -7.33 | Q63: -5.96 | R63: 0 | S63: 1
A64: https://www.sports-reference.com/cfb/schools/dayton/ | B64: Dayton | C64: 1956 | D64: 1976 | E64: 21 | F64: 216 | G64: 78 | H64: 130 | I64: 8 | J64: 0.38 | K64: -13.09 | L64: 0 | M64: 0 | N64: 0 | O64: 0 | P64: -8.45 | R64: 0 | S64: 0
A65: https://www.sports-reference.com/cfb/schools/del-monte-pre-flight/ | B65: Del Monte Pre-Flight | C65: 1943 | D65: 1943 | E65: 1 | F65: 8 | G65: 7 | H65: 1 | I65: 0.875 | J65: 12.87 | K65: -6.25 | L65: 0 | M65: 0 | N65: 0 | O65: 0 | P65: 0 | Q65: 1 | R65: 0
A66: https://www.sports-reference.com/cfb/schools/delaware/ | B66: Delaware | C66: 2025 | D66: 2025 | E66: 1 | F66: 13 | G66: 7 | H66: 6 | I66: 0.538 | J66: 1 | K66: 1 | L66: 0 | M66: 0 | N66: 1 | O66: -8.16 | P66: -7.63 | R66: 0 | S66: 0
A67: https://www.sports-reference.com/cfb/schools/denver/ | B67: Denver | C67: 1902 | D67: 1960 | E67: 59 | F67: 520 | G67: 259 | H67: 228 | I67: 33 | J67: 0.53 | K67: 2 | L67: 0 | M67: 2 | N67: 0 | O67: 0 | P67: -4.08 | Q67: -4.86 | R67: 0 | S67: 6
A68: https://www.sports-reference.com/cfb/schools/detroit-mercy/ | B68: Detroit Mercy | C68: 1927 | D68: 1964 | E68: 36 | F68: 338 | G68: 196 | H68: 132 | I68: 10 | J68: 0.595 | K68: 0.21 | L68: 0 | M68: 0 | N68: 0 | O68: 0 | P68: -4.25 | Q68: 3 | R68: 0
A69: https://www.sports-reference.com/cfb/schools/dickinson/ | B69: Dickinson | C69: 1889 | D69: 1910 | E69: 18 | F69: 173 | G69: 84 | H69: 79 | I69: 10 | J69: 0.514 | K69: -3.19 | L69: 0 | M69: 0 | N69: 0 | O69: 0 | P69: -3.54 | R69: 0 | S69: 0
A70: https://www.sports-reference.com/cfb/schools/drake/ | B70: Drake | C70: 1900 | D70: 1985 | E70: 73 | F70: 666 | G70: 316 | H70: 326 | I70: 24 | J70: 0.492 | K70: 3 | L70: 2 | M70: 1 | N70: 0 | O70: 0.667 | P70: -5.6 | Q70: -5.7 | R70: 0 | S70: 7
A71: https://www.sports-reference.com/cfb/schools/drury/ | B71: Drury | C71: 1907 | D71: 1907 | E71: 1 | F71: 5 | G71: 1 | H71: 4 | I71: 0.2 | J71: -13.17 | K71: -3.97 | L71: 0 | M71: 0 | N71: 0 | O71: 0 | P71: 0 | R71: 0 | S71: 0
A72: https://www.sports-reference.com/cfb/schools/duke/ | B72: Duke | C72: 1922 | D72: 2025 | E72: 104 | F72: 1120 | G72: 535 | H72: 557 | I72: 28 | J72: 0.49 | K72: 18 | L72: 9 | M72: 9 | N72: 0 | O72: 0.5 | P72: 2.68 | Q72: 2.68 | R72: 16 | S72: 18
A73: https://www.sports-reference.com/cfb/schools/duquesne/ | B73: Duquesne | C73: 1933 | D73: 1950 | E73: 14 | F73: 132 | G73: 80 | H73: 49 | I73: 3 | J73: 0.617 | K73: 1 | L73: 1 | M73: 0 | N73: 0 | O73: 1 | P73: 1.04 | Q73: -2.38 | R73: 3 | S73: 0
A74: https://www.sports-reference.com/cfb/schools/east-carolina/ | B74: East Carolina | C74: 1965 | D74: 2025 | E74: 61 | F74: 703 | G74: 361 | H74: 339 | I74: 3 | J74: 0.516 | K74: 19 | L74: 10 | M74: 9 | N74: 0 | O74: 0.526 | P74: -2.56 | Q74: -2.74 | R74: 2 | S74: 6
A75: https://www.sports-reference.com/cfb/schools/east-tennessee-state/ | B75: East Tennessee State | C75: 1979 | D75: 1981 | E75: 3 | F75: 33 | G75: 15 | H75: 18 | I75: 0.455 | J75: -9.46 | K75: -8.43 | L75: 0 | M75: 0 | N75: 0 | O75: 0 | P75: 0 | R75: 0 | S75: 0
A76: https://www.sports-reference.com/cfb/schools/eastern-michigan/ | B76: Eastern Michigan | C76: 1975 | D76: 2025 | E76: 51 | F76: 580 | G76: 192 | H76: 381 | I76: 7 | J76: 0.337 | K76: 7 | L76: 2 | M76: 5 | N76: 0 | O76: 0.286 | P76: -13.92 | Q76: -7.28 | R76: 0 | S76: 1
A77: https://www.sports-reference.com/cfb/schools/erskine/ | B77: Erskine | C77: 1919 | D77: 1936 | E77: 5 | F77: 39 | G77: 12 | H77: 27 | I77: 0.308 | J77: -13.04 | K77: -5.98 | L77: 0 | M77: 0 | N77: 0 | O77: 0 | P77: 0 | R77: 0 | S77: 0
A78: https://www.sports-reference.com/cfb/schools/florida/ | B78: Florida | C78: 1911 | D78: 2025 | E78: 113 | F78: 1231 | G78: 745 | H78: 449 | I78: 37 | J78: 0.62 | K78: 49 | L78: 25 | M78: 24 | N78: 0 | O78: 0.51 | P78: 8.87 | Q78: 4.36 | R78: 34 | S78: 9
A79: https://www.sports-reference.com/cfb/schools/florida-am/ | B79: Florida A&M | C79: 2004 | D79: 2004 | E79: 1 | F79: 11 | G79: 3 | H79: 8 | I79: 0.273 | J79: -21.65 | K79: -12.38 | L79: 0 | M79: 0 | N79: 0 | O79: 0 | P79: 0 | R79: 0 | S79: 0
A80: https://www.sports-reference.com/cfb/schools/florida-atlantic/ | B80: Florida Atlantic | C80: 2004 | D80: 2025 | E80: 22 | F80: 264 | G80: 112 | H80: 154 | I80: 0.421 | J80: 5 | K80: 4 | L80: 0 | M80: 1 | N80: 0 | O80: 0.8 | P80: -7.84 | Q80: -4.92 | R80: 0 | S80: 3
A81: https://www.sports-reference.com/cfb/schools/florida-international/ | B81: Florida International | C81: 2004 | D81: 2025 | E81: 22 | F81: 260 | G81: 92 | H81: 168 | I81: 0.354 | J81: 6 | K81: 2 | L81: 0 | M81: 4 | N81: 0 | O81: 0.333 | P81: -12.26 | Q81: -6.59 | R81: 0 | S81: 1
A82: https://www.sports-reference.com/cfb/schools/florida-state/ | B82: Florida State | C82: 1954 | D82: 2025 | E82: 72 | F82: 856 | G82: 563 | H82: 277 | I82: 16 | J82: 0.667 | K82: 49 | L82: 29 | M82: 18 | N82: 2 | O82: 0.612 | P82: 10.58 | Q82: 3.9 | R82: 35 | S82: 16
A83: https://www.sports-reference.com/cfb/schools/fordham/ | B83: Fordham | C83: 1909 | D83: 1954 | E83: 25 | F83: 213 | G83: 126 | H83: 70 | I83: 17 | J83: 0.631 | K83: 2 | L83: 1 | M83: 1 | N83: 0 | O83: 0.5 | P83: 3.6 | Q83: -1.08 | R83: 6 | S83: 0
A84: https://www.sports-reference.com/cfb/schools/fort-benning/ | B84: Fort Benning | C84: 1922 | D84: 1922 | E84: 1 | F84: 10 | G84: 5 | H84: 5 | I84: 0.5 | J84: -6.13 | K84: -4.03 | L84: 0 | M84: 0 | N84: 0 | O84: 0 | P84: 0 | R84: 0 | S84: 0
A85: https://www.sports-reference.com/cfb/schools/fort-riley/ | B85: Fort Riley | C85: 1943 | D85: 1943 | E85: 1 | F85: 9 | G85: 6 | H85: 2 | I85: 1 | J85: 0.722 | K85: 10.37 | L85: 0 | M85: 0 | N85: 0 | O85: 0 | P85: 1.81 | R85: 0 | S85: 0
A86: https://www.sports-reference.com/cfb/schools/fort-warren/ | B86: Fort Warren | C86: 1944 | D86: 1944 | E86: 1 | F86: 10 | G86: 5 | H86: 4 | I86: 1 | J86: 0.55 | K86: -4.13 | L86: 0 | M86: 0 | N86: 0 | O86: 0 | P86: -3.83 | R86: 0 | S86: 0
A87: https://www.sports-reference.com/cfb/schools/franklin-marshall/ | B87: Franklin & Marshall | C87: 1889 | D87: 1904 | E87: 7 | F87: 62 | G87: 24 | H87: 31 | I87: 7 | J87: 0.444 | K87: -6.27 | L87: 0 | M87: 0 | N87: 0 | O87: 0 | P87: -3.24 | R87: 0 | S87: 0
A88: https://www.sports-reference.com/cfb/schools/fresno-state/ | B88: Fresno State | C88: 1969 | D88: 2025 | E88: 57 | F88: 689 | G88: 401 | H88: 284 | I88: 4 | J88: 0.585 | K88: 28 | L88: 15 | M88: 13 | N88: 0 | O88: 0.536 | P88: -1.72 | Q88: -5.34 | R88: 4 | S88: 13
A89: https://www.sports-reference.com/cfb/schools/furman/ | B89: Furman | C89: 1902 | D89: 1981 | E89: 61 | F89: 605 | G89: 297 | H89: 280 | I89: 28 | J89: 0.514 | K89: -6.16 | L89: 0 | M89: 0 | N89: 0 | O89: 0 | P89: -6.16 | Q89: 3 | R89: 0
A90: https://www.sports-reference.com/cfb/schools/george-washington/ | B90: George Washington | C90: 1908 | D90: 1966 | E90: 33 | F90: 299 | G90: 138 | H90: 147 | I90: 14 | J90: 0.485 | K90: 1 | L90: 1 | M90: 0 | N90: 0 | O90: 1 | P90: -4.59 | Q90: -4.24 | R90: 1 | S90: 0
A91: https://www.sports-reference.com/cfb/schools/georgetown/ | B91: Georgetown | C91: 1902 | D91: 1950 | E91: 36 | F91: 313 | G91: 184 | H91: 110 | I91: 19 | J91: 0.618 | K91: 2 | L91: 0 | M91: 2 | N91: 0 | O91: 0 | P91: 2.82 | Q91: -2.36 | R91: 1 | S91: 0
A92: https://www.sports-reference.com/cfb/schools/georgia/ | B92: Georgia | C92: 1902 | D92: 2025 | E92: 122 | F92: 1339 | G92: 878 | H92: 411 | I92: 50 | J92: 0.674 | K92: 64 | L92: 38 | M92: 23 | N92: 3 | O92: 0.617 | P92: 10.74 | Q92: 4.86 | R92: 44 | S92: 16
A93: https://www.sports-reference.com/cfb/schools/georgia-pre-flight/ | B93: Georgia Pre-Flight | C93: 1942 | D93: 1943 | E93: 2 | F93: 15 | G93: 12 | H93: 2 | I93: 1 | J93: 0.833 | K93: 11.14 | L93: 0 | M93: 0 | N93: 0 | O93: 0 | P93: 2.27 | R93: 0 | S93: 0
A94: https://www.sports-reference.com/cfb/schools/georgia-southern/ | B94: Georgia Southern | C94: 2014 | D94: 2025 | E94: 12 | F94: 152 | G94: 80 | H94: 72 | I94: 0.526 | J94: 8 | K94: 4 | L94: 0 | M94: 4 | N94: 0 | O94: 0.5 | P94: -3.24 | Q94: -4.1 | R94: 0 | S94: 1
A95: https://www.sports-reference.com/cfb/schools/georgia-state/ | B95: Georgia State | C95: 2013 | D95: 2025 | E95: 13 | F95: 158 | G95: 55 | H95: 103 | I95: 0.348 | J95: 6 | K95: 4 | L95: 0 | M95: 2 | N95: 0 | O95: 0.667 | P95: -9.35 | Q95: -3.68 | R95: 0 | S95: 0
A96: https://www.sports-reference.com/cfb/schools/georgia-tech/ | B96: Georgia Tech | C96: 1902 | D96: 2025 | E96: 124 | F96: 1335 | G96: 766 | H96: 529 | I96: 40 | J96: 0.589 | K96: 48 | L96: 26 | M96: 22 | N96: 0 | O96: 0.542 | P96: 8.26 | Q96: 4.53 | R96: 24 | S96: 8
A97: https://www.sports-reference.com/cfb/schools/gonzaga/ | B97: Gonzaga | C97: 1922 | D97: 1941 | E97: 16 | F97: 141 | G97: 67 | H97: 63 | I97: 11 | J97: 0.514 | K97: 1 | L97: 0 | M97: 1 | N97: 0 | O97: 0 | P97: -2.55 | Q97: -4.15 | R97: 0 | S97: 0
A98: https://www.sports-reference.com/cfb/schools/grambling-state/ | B98: Grambling State | C98: 1977 | D98: 1977 | E98: 1 | F98: 11 | G98: 10 | H98: 1 | I98: 0.909 | J98: 6.73 | K98: -10 | L98: 0 | M98: 0 | N98: 0 | O98: 0 | P98: 0 | Q98: 1 | R98: 0
A99: https://www.sports-reference.com/cfb/schools/great-lakes-navy/ | B99: Great Lakes Navy | C99: 1918 | D99: 1945 | E99: 5 | F99: 55 | G99: 39 | H99: 11 | I99: 5 | J99: 0.755 | K99: 1 | L99: 1 | M99: 0 | N99: 0 | O99: 1 | P99: 16.37 | Q99: 6.95 | R99: 2 | S99: 0
A100: https://www.sports-reference.com/cfb/schools/grinnell/ | B100: Grinnell | C100: 1899 | D100: 1936 | E100: 26 | F100: 218 | G100: 90 | H100: 110 | I100: 18 | J100: 0.454 | K100: -6.86 | L100: 0 | M100: 0 | N100: 0 | O100: 0 | P100: -4.63 | R100: 0 | S100: 0
...

Sheet Sheet-1-all-teams
A1: University URL wiki | B1: Source URL | C1: University | D1: School name | E1: Nickname | F1: City | G1: State | H1: Type | I1: Division | J1: Conference | K1: Roster count 2026 | L1: Roster count 2025 | M1: Roster count 2024 | N1: Avg Roster Count Last 3 years | O1: Sport | P1: Num of seasons | Q1: Estimated Athlete pool | R1: Pro Players Count | S1: Draft Probability | T1: National Average | U1: Vs_National_Average
A2: https://en.wikipedia.org/wiki/Abilene_Christian_University | C2: Abilene Christian University | D2: Abilene Christian | E2: Wildcats | F2: Abilene | G2: TX | H2: Private | I2: FCS | J2: Western Athletic Conference | N2: 0 | O2: American Football | P2: 10 | Q2: =P2*N2 -> 0 | R2: {=IF(O2="American Football", XLOOKUP(C2, drafts_football!A:A, drafts_football!B:B, 0), "")} -> 0 | S2: =IF(Q2 = 0, 0, R2/Q2) -> 0 | T2: 0.013414865 | U2: =S2-T2 -> -0.013414865
A3: https://en.wikipedia.org/wiki/Alabama_A%26M_University | C3: Alabama Agricultural and Mechanical University | D3: Alabama A&M | E3: Bulldogs | F3: Normal | G3: AL | H3: Public | I3: FCS | J3: Southwestern Athletic Conference | N3: 0 | O3: American Football | P3: 10 | Q3: =P3*N3 -> 0 | R3: {=IF(O3="American Football", XLOOKUP(C3, drafts_football!A:A, drafts_football!B:B, 0), "")} -> 1 | S3: =IF(Q3 = 0, 0, R3/Q3) -> 0 | T3: 0.013414865 | U3: =S3-T3 -> -0.013414865
A4: https://en.wikipedia.org/wiki/Alabama_State_University | C4: Alabama State University | D4: Alabama State | E4: Hornets | F4: Montgomery | G4: AL | H4: Public | I4: FCS | J4: Southwestern Athletic Conference | N4: 0 | O4: American Football | P4: 10 | Q4: =P4*N4 -> 0 | R4: {=IF(O4="American Football", XLOOKUP(C4, drafts_football!A:A, drafts_football!B:B, 0), "")} -> 2 | S4: =IF(Q4 = 0, 0, R4/Q4) -> 0 | T4: 0.013414865 | U4: =S4-T4 -> -0.013414865
A5: https://en.wikipedia.org/wiki/Alcorn_State_University | C5: Alcorn State University | D5: Alcorn State | E5: Braves | F5: Lorman | G5: MS | H5: Public | I5: FCS | J5: Southwestern Athletic Conference | N5: 0 | O5: American Football | P5: 10 | Q5: =P5*N5 -> 0 | R5: {=IF(O5="American Football", XLOOKUP(C5, drafts_football!A:A, drafts_football!B:B, 0), "")} -> 0 | S5: =IF(Q5 = 0, 0, R5/Q5) -> 0 | T5: 0.013414865 | U5: =S5-T5 -> -0.013414865
A6: https://en.wikipedia.org/wiki/American_University | C6: American University | D6: American | E6: Eagles | F6: Washington | G6: DC | H6: Private | I6: Non-football | J6: Patriot League | K6: 0 | L6: 0 | M6: 0 | N6: 0 | O6: American Football | P6: 10 | Q6: =P6*N6 -> 0 | R6: {=IF(O6="American Football", XLOOKUP(C6, drafts_football!A:A, drafts_football!B:B, 0), "")} -> 0 | S6: =IF(Q6 = 0, 0, R6/Q6) -> 0 | T6: 0.013414865 | U6: =S6-T6 -> -0.013414865
A7: https://en.wikipedia.org/wiki/Appalachian_State_University | B7: https://www.sports-reference.com/cfb/schools/appalachian-state/ | C7: Appalachian State University | D7: Appalachian State | E7: Mountaineers | F7: Boone | G7: NC | H7: Public | I7: FBS | J7: Sun Belt Conference | L7: 120 | M7: 114 | N7: 117 | O7: American Football | P7: 10 | Q7: =P7*N7 -> 1170 | R7: {=IF(O7="American Football", XLOOKUP(C7, drafts_football!A:A, drafts_football!B:B, 0), "")} -> 8 | S7: =IF(Q7 = 0, 0, R7/Q7) -> 0.0068376068 | T7: 0.013414865 | U7: =S7-T7 -> -0.0065772577
A8: https://en.wikipedia.org/wiki/Arizona_State_University | B8: https://www.sports-reference.com/cfb/schools/arizona-state/ | C8: Arizona State University | D8: Arizona State | E8: Sun Devils | F8: Tempe | G8: AZ | H8: Public | I8: FBS | J8: Big 12 Conference | K8: 107 | L8: 119 | M8: 116 | N8: 114 | O8: American Football | P8: 10 | Q8: =P8*N8 -> 1140 | R8: {=IF(O8="American Football", XLOOKUP(C8, drafts_football!A:A, drafts_football!B:B, 0), "")} -> 17 | S8: =IF(Q8 = 0, 0, R8/Q8) -> 0.014912281 | T8: 0.013414865 | U8: =S8-T8 -> 0.0014974161
A9: https://en.wikipedia.org/wiki/Arkansas_State_University | B9: https://www.sports-reference.com/cfb/schools/arkansas-state/ | C9: Arkansas State University | D9: Arkansas State | E9: Red Wolves | F9: Jonesboro | G9: AR | H9: Public | I9: FBS | J9: Sun Belt Conference | K9: 122 | L9: 130 | M9: 121 | N9: 124.3 | O9: American Football | P9: 10 | Q9: =P9*N9 -> 1243 | R9: {=IF(O9="American Football", XLOOKUP(C9, drafts_football!A:A, drafts_football!B:B, 0), "")} -> 0 | S9: =IF(Q9 = 0, 0, R9/Q9) -> 0 | T9: 0.013414865 | U9: =S9-T9 -> -0.013414865
A10: https://en.wikipedia.org/wiki/Auburn_University | B10: https://www.sports-reference.com/cfb/schools/auburn/ | C10: Auburn University | D10: Auburn | E10: Tigers | F10: Auburn | G10: AL | H10: Public | I10: FBS | J10: Southeastern Conference | K10: 114 | L10: 121 | M10: 119 | N10: 118 | O10: American Football | P10: 10 | Q10: =P10*N10 -> 1180 | R10: {=IF(O10="American Football", XLOOKUP(C10, drafts_football!A:A, drafts_football!B:B, 0), "")} -> 41 | S10: =IF(Q10 = 0, 0, R10/Q10) -> 0.034745763 | T10: 0.013414865 | U10: =S10-T10 -> 0.021330898
A11: https://en.wikipedia.org/wiki/Austin_Peay_State_University | C11: Austin Peay State University | D11: Austin Peay | E11: Governors | F11: Clarksville | G11: TN | H11: Public | I11: FCS | J11: Atlantic Sun Conference | N11: 0 | O11: American Football | P11: 10 | Q11: =P11*N11 -> 0 | R11: {=IF(O11="American Football", XLOOKUP(C11, drafts_football!A:A, drafts_football!B:B, 0), "")} -> 0 | S11: =IF(Q11 = 0, 0, R11/Q11) -> 0 | T11: 0.013414865 | U11: =S11-T11 -> -0.013414865
A12: https://en.wikipedia.org/wiki/Ball_State_University | B12: https://www.sports-reference.com/cfb/schools/ball-state/ | C12: Ball State University | D12: Ball State | E12: Cardinals | F12: Muncie | G12: IN | H12: Public | I12: FBS | J12: Mid-American Conference | K12: 106 | L12: 119 | M12: 118 | N12: 114.3 | O12: American Football | P12: 10 | Q12: =P12*N12 -> 1143 | R12: {=IF(O12="American Football", XLOOKUP(C12, drafts_football!A:A, drafts_football!B:B, 0), "")} -> 2 | S12: =IF(Q12 = 0, 0, R12/Q12) -> 0.0017497813 | T12: 0.013414865 | U12: =S12-T12 -> -0.011665083
A13: https://en.wikipedia.org/wiki/Baylor_University | B13: https://www.sports-reference.com/cfb/schools/baylor/ | C13: Baylor University | D13: Baylor | E13: Bears | F13: Waco | G13: TX | H13: Private | I13: FBS | J13: Big 12 Conference | K13: 115 | L13: 113 | M13: 109 | N13: 112.3 | O13: American Football | P13: 10 | Q13: =P13*N13 -> 1123 | R13: {=IF(O13="American Football", XLOOKUP(C13, drafts_football!A:A, drafts_football!B:B, 0), "")} -> 19 | S13: =IF(Q13 = 0, 0, R13/Q13) -> 0.016918967 | T13: 0.013414865 | U13: =S13-T13 -> 0.0035041025
A14: https://en.wikipedia.org/wiki/Bellarmine_University | C14: Bellarmine University | D14: Bellarmine | E14: Knights | F14: Louisville | G14: KY | H14: Private | I14: Non-football | J14: Atlantic Sun Conference | K14: 0 | L14: 0 | M14: 0 | N14: 0 | O14: American Football | P14: 10 | Q14: =P14*N14 -> 0 | R14: {=IF(O14="American Football", XLOOKUP(C14, drafts_football!A:A, drafts_football!B:B, 0), "")} -> 0 | S14: =IF(Q14 = 0, 0, R14/Q14) -> 0 | T14: 0.013414865 | U14: =S14-T14 -> -0.013414865
A15: https://en.wikipedia.org/wiki/Belmont_University | C15: Belmont University | D15: Belmont | E15: Bruins | F15: Nashville | G15: TN | H15: Private | I15: Non-football | J15: Missouri Valley Conference | K15: 0 | L15: 0 | M15: 0 | N15: 0 | O15: American Football | P15: 10 | Q15: =P15*N15 -> 0 | R15: {=IF(O15="American Football", XLOOKUP(C15, drafts_football!A:A, drafts_football!B:B, 0), "")} -> 0 | S15: =IF(Q15 = 0, 0, R15/Q15) -> 0 | T15: 0.013414865 | U15: =S15-T15 -> -0.013414865
A16: https://en.wikipedia.org/wiki/Bethune%E2%80%93Cookman_University | C16: Bethune–Cookman University | D16: Bethune–Cookman | E16: Wildcats | F16: Daytona Beach | G16: FL | H16: Private | I16: FCS | J16: Southwestern Athletic Conference | N16: 0 | O16: American Football | P16: 10 | Q16: =P16*N16 -> 0 | R16: {=IF(O16="American Football", XLOOKUP(C16, drafts_football!A:A, drafts_football!B:B, 0), "")} -> 0 | S16: =IF(Q16 = 0, 0, R16/Q16) -> 0 | T16: 0.013414865 | U16: =S16-T16 -> -0.013414865
A17: https://en.wikipedia.org/wiki/Boise_State_University | B17: https://www.sports-reference.com/cfb/schools/boise-state/ | C17: Boise State University | D17: Boise State | E17: Broncos | F17: Boise | G17: ID | H17: Public | I17: FBS | J17: Mountain West Conference | K17: 108 | L17: 115 | M17: 113 | N17: 112 | O17: American Football | P17: 10 | Q17: =P17*N17 -> 1120 | R17: {=IF(O17="American Football", XLOOKUP(C17, drafts_football!A:A, drafts_football!B:B, 0), "")} -> 17 | S17: =IF(Q17 = 0, 0, R17/Q17) -> 0.015178571 | T17: 0.013414865 | U17: =S17-T17 -> 0.0017637069
A18: https://en.wikipedia.org/wiki/Boston_College | B18: https://www.sports-reference.com/cfb/schools/boston-college/ | C18: Boston College | D18: Boston College | E18: Eagles | F18: Chestnut Hill | G18: MA | H18: Private | I18: FBS | J18: Atlantic Coast Conference | K18: 127 | L18: 117 | M18: 117 | N18: 120.3 | O18: American Football | P18: 10 | Q18: =P18*N18 -> 1203 | R18: {=IF(O18="American Football", XLOOKUP(C18, drafts_football!A:A, drafts_football!B:B, 0), "")} -> 21 | S18: =IF(Q18 = 0, 0, R18/Q18) -> 0.017456359 | T18: 0.013414865 | U18: =S18-T18 -> 0.0040414945
A19: https://en.wikipedia.org/wiki/Boston_University | C19: Boston University | D19: Boston University | E19: Terriers | F19: Boston | G19: MA | H19: Private | I19: Non-football | J19: Patriot League | K19: 0 | L19: 0 | M19: 0 | N19: 0 | O19: American Football | P19: 10 | Q19: =P19*N19 -> 0 | R19: {=IF(O19="American Football", XLOOKUP(C19, drafts_football!A:A, drafts_football!B:B, 0), "")} -> 0 | S19: =IF(Q19 = 0, 0, R19/Q19) -> 0 | T19: 0.013414865 | U19: =S19-T19 -> -0.013414865
A20: https://en.wikipedia.org/wiki/Bowling_Green_State_University | B20: https://www.sports-reference.com/cfb/schools/bowling-green-state/ | C20: Bowling Green State University | D20: Bowling Green | E20: Falcons | F20: Bowling Green | G20: OH | H20: Public | I20: FBS | J20: Mid-American Conference | K20: 107 | L20: 109 | M20: 107 | N20: 107.7 | O20: American Football | P20: 10 | Q20: =P20*N20 -> 1077 | R20: {=IF(O20="American Football", XLOOKUP(C20, drafts_football!A:A, drafts_football!B:B, 0), "")} -> 3 | S20: =IF(Q20 = 0, 0, R20/Q20) -> 0.0027855153 | T20: 0.013414865 | U20: =S20-T20 -> -0.010629349
A21: https://en.wikipedia.org/wiki/Bradley_University | C21: Bradley University | D21: Bradley | E21: Braves | F21: Peoria | G21: IL | H21: Private | I21: Non-football | J21: Missouri Valley Conference | K21: 0 | L21: 0 | M21: 0 | N21: 0 | O21: American Football | P21: 10 | Q21: =P21*N21 -> 0 | R21: {=IF(O21="American Football", XLOOKUP(C21, drafts_football!A:A, drafts_football!B:B, 0), "")} -> 0 | S21: =IF(Q21 = 0, 0, R21/Q21) -> 0 | T21: 0.013414865 | U21: =S21-T21 -> -0.013414865
A22: https://en.wikipedia.org/wiki/Brigham_Young_University | B22: https://www.sports-reference.com/cfb/schools/brigham-young/ | C22: Brigham Young University | D22: BYU | E22: Cougars | F22: Provo | G22: UT | H22: Private | I22: FBS | J22: Big 12 Conference | K22: 115 | L22: 121 | M22: 119 | N22: 118.3 | O22: American Football | P22: 10 | Q22: =P22*N22 -> 1183 | R22: {=IF(O22="American Football", XLOOKUP(C22, drafts_football!A:A, drafts_football!B:B, 0), "")} -> 14 | S22: =IF(Q22 = 0, 0, R22/Q22) -> 0.01183432 | T22: 0.013414865 | U22: =S22-T22 -> -0.001580545
A23: https://en.wikipedia.org/wiki/Brown_University | C23: Brown University | D23: Brown | E23: Bears | F23: Providence | G23: RI | H23: Private | I23: FCS | J23: Ivy League | N23: 0 | O23: American Football | P23: 10 | Q23: =P23*N23 -> 0 | R23: {=IF(O23="American Football", XLOOKUP(C23, drafts_football!A:A, drafts_football!B:B, 0), "")} -> 0 | S23: =IF(Q23 = 0, 0, R23/Q23) -> 0 | T23: 0.013414865 | U23: =S23-T23 -> -0.013414865
A24: https://en.wikipedia.org/wiki/Bryant_University | C24: Bryant University | D24: Bryant | E24: Bulldogs | F24: Smithfield | G24: RI | H24: Private | I24: FCS | J24: America East Conference | N24: 0 | O24: American Football | P24: 10 | Q24: =P24*N24 -> 0 | R24: {=IF(O24="American Football", XLOOKUP(C24, drafts_football!A:A, drafts_football!B:B, 0), "")} -> 0 | S24: =IF(Q24 = 0, 0, R24/Q24) -> 0 | T24: 0.013414865 | U24: =S24-T24 -> -0.013414865
A25: https://en.wikipedia.org/wiki/Bucknell_University | C25: Bucknell University | D25: Bucknell | E25: Bison | F25: Lewisburg | G25: PA | H25: Private | I25: FCS | J25: Patriot League | N25: 0 | O25: American Football | P25: 10 | Q25: =P25*N25 -> 0 | R25: {=IF(O25="American Football", XLOOKUP(C25, drafts_football!A:A, drafts_football!B:B, 0), "")} -> 1 | S25: =IF(Q25 = 0, 0, R25/Q25) -> 0 | T25: 0.013414865 | U25: =S25-T25 -> -0.013414865
A26: https://en.wikipedia.org/wiki/Butler_University | C26: Butler University | D26: Butler | E26: Bulldogs | F26: Indianapolis | G26: IN | H26: Private | I26: FCS | J26: Big East Conference | N26: 0 | O26: American Football | P26: 10 | Q26: =P26*N26 -> 0 | R26: {=IF(O26="American Football", XLOOKUP(C26, drafts_football!A:A, drafts_football!B:B, 0), "")} -> 0 | S26: =IF(Q26 = 0, 0, R26/Q26) -> 0 | T26: 0.013414865 | U26: =S26-T26 -> -0.013414865
A27: https://en.wikipedia.org/wiki/California_Baptist_University | C27: California Baptist University | D27: Cal Baptist | E27: Lancers | F27: Riverside | G27: CA | H27: Private | I27: Non-football | J27: Western Athletic Conference | K27: 0 | L27: 0 | M27: 0 | N27: 0 | O27: American Football | P27: 10 | Q27: =P27*N27 -> 0 | R27: {=IF(O27="American Football", XLOOKUP(C27, drafts_football!A:A, drafts_football!B:B, 0), "")} -> 0 | S27: =IF(Q27 = 0, 0, R27/Q27) -> 0 | T27: 0.013414865 | U27: =S27-T27 -> -0.013414865
A28: https://en.wikipedia.org/wiki/California_Polytechnic_State_University,_San_Luis_Obispo | C28: California Polytechnic State University | D28: Cal Poly | E28: Mustangs | F28: San Luis Obispo | G28: CA | H28: Public | I28: FCS | J28: Big West Conference | N28: 0 | O28: American Football | P28: 10 | Q28: =P28*N28 -> 0 | R28: {=IF(O28="American Football", XLOOKUP(C28, drafts_football!A:A, drafts_football!B:B, 0), "")} -> 0 | S28: =IF(Q28 = 0, 0, R28/Q28) -> 0 | T28: 0.013414865 | U28: =S28-T28 -> -0.013414865
A29: https://en.wikipedia.org/wiki/California_State_University,_Bakersfield | C29: California State University, Bakersfield | D29: Bakersfield | E29: Roadrunners | F29: Bakersfield | G29: CA | H29: Public | I29: Non-football | J29: Big West Conference | K29: 0 | L29: 0 | M29: 0 | N29: 0 | O29: American Football | P29: 10 | Q29: =P29*N29 -> 0 | R29: {=IF(O29="American Football", XLOOKUP(C29, drafts_football!A:A, drafts_football!B:B, 0), "")} -> 0 | S29: =IF(Q29 = 0, 0, R29/Q29) -> 0 | T29: 0.013414865 | U29: =S29-T29 -> -0.013414865
A30: https://en.wikipedia.org/wiki/California_State_University,_Fresno | B30: https://www.sports-reference.com/cfb/schools/fresno-state/ | C30: California State University, Fresno | D30: Fresno State | E30: Bulldogs | F30: Fresno | G30: CA | H30: Public | I30: FBS | J30: Mountain West Conference | K30: 113 | L30: 115 | M30: 112 | N30: 113.3 | O30: American Football | P30: 10 | Q30: =P30*N30 -> 1133 | R30: {=IF(O30="American Football", XLOOKUP(C30, drafts_football!A:A, drafts_football!B:B, 0), "")} -> 5 | S30: =IF(Q30 = 0, 0, R30/Q30) -> 0.0044130627 | T30: 0.013414865 | U30: =S30-T30 -> -0.0090018019
A31: https://en.wikipedia.org/wiki/California_State_University,_Fullerton | C31: California State University, Fullerton | D31: Cal State Fullerton | E31: Titans | F31: Fullerton | G31: CA | H31: Public | I31: Non-football | J31: Big West Conference | K31: 0 | L31: 0 | M31: 0 | N31: 0 | O31: American Football | P31: 10 | Q31: =P31*N31 -> 0 | R31: {=IF(O31="American Football", XLOOKUP(C31, drafts_football!A:A, drafts_football!B:B, 0), "")} -> 0 | S31: =IF(Q31 = 0, 0, R31/Q31) -> 0 | T31: 0.013414865 | U31: =S31-T31 -> -0.013414865
A32: https://en.wikipedia.org/wiki/California_State_University,_Long_Beach | C32: California State University, Long Beach | D32: Long Beach State | E32: Beach | F32: Long Beach | G32: CA | H32: Public | I32: Non-football | J32: Big West Conference | K32: 0 | L32: 0 | M32: 0 | N32: 0 | O32: American Football | P32: 10 | Q32: =P32*N32 -> 0 | R32: {=IF(O32="American Football", XLOOKUP(C32, drafts_football!A:A, drafts_football!B:B, 0), "")} -> 0 | S32: =IF(Q32 = 0, 0, R32/Q32) -> 0 | T32: 0.013414865 | U32: =S32-T32 -> -0.013414865
A33: https://en.wikipedia.org/wiki/California_State_University,_Northridge | C33: California State University, Northridge | D33: Cal State Northridge / CSUN | E33: Matadors | F33: Northridge | G33: CA | H33: Public | I33: Non-football | J33: Big West Conference | K33: 0 | L33: 0 | M33: 0 | N33: 0 | O33: American Football | P33: 10 | Q33: =P33*N33 -> 0 | R33: {=IF(O33="American Football", XLOOKUP(C33, drafts_football!A:A, drafts_football!B:B, 0), "")} -> 0 | S33: =IF(Q33 = 0, 0, R33/Q33) -> 0 | T33: 0.013414865 | U33: =S33-T33 -> -0.013414865
A34: https://en.wikipedia.org/wiki/California_State_University,_Sacramento | C34: California State University, Sacramento | D34: Sacramento State | E34: Hornets | F34: Sacramento | G34: CA | H34: Public | I34: FCS | J34: Big Sky Conference | N34: 0 | O34: American Football | P34: 10 | Q34: =P34*N34 -> 0 | R34: {=IF(O34="American Football", XLOOKUP(C34, drafts_football!A:A, drafts_football!B:B, 0), "")} -> 2 | S34: =IF(Q34 = 0, 0, R34/Q34) -> 0 | T34: 0.013414865 | U34: =S34-T34 -> -0.013414865
A35: https://en.wikipedia.org/wiki/Campbell_University | C35: Campbell University | D35: Campbell | E35: Fighting Camels | F35: Buies Creek | G35: NC | H35: Private | I35: FCS | J35: Coastal Athletic Association | N35: 0 | O35: American Football | P35: 10 | Q35: =P35*N35 -> 0 | R35: {=IF(O35="American Football", XLOOKUP(C35, drafts_football!A:A, drafts_football!B:B, 0), "")} -> 0 | S35: =IF(Q35 = 0, 0, R35/Q35) -> 0 | T35: 0.013414865 | U35: =S35-T35 -> -0.013414865
A36: https://en.wikipedia.org/wiki/Canisius_University | C36: Canisius University | D36: Canisius | E36: Golden Griffins | F36: Buffalo | G36: NY | H36: Private | I36: Non-football | J36: Metro Atlantic Athletic Conference | K36: 0 | L36: 0 | M36: 0 | N36: 0 | O36: American Football | P36: 10 | Q36: =P36*N36 -> 0 | R36: {=IF(O36="American Football", XLOOKUP(C36, drafts_football!A:A, drafts_football!B:B, 0), "")} -> 0 | S36: =IF(Q36 = 0, 0, R36/Q36) -> 0 | T36: 0.013414865 | U36: =S36-T36 -> -0.013414865
A37: https://en.wikipedia.org/wiki/Central_Connecticut_State_University | C37: Central Connecticut State University | D37: Central Connecticut | E37: Blue Devils | F37: New Britain | G37: CT | H37: Public | I37: FCS | J37: NEC | N37: 0 | O37: American Football | P37: 10 | Q37: =P37*N37 -> 0 | R37: {=IF(O37="American Football", XLOOKUP(C37, drafts_football!A:A, drafts_football!B:B, 0), "")} -> 0 | S37: =IF(Q37 = 0, 0, R37/Q37) -> 0 | T37: 0.013414865 | U37: =S37-T37 -> -0.013414865
A38: https://en.wikipedia.org/wiki/Central_Michigan_University | B38: https://www.sports-reference.com/cfb/schools/central-michigan/ | C38: Central Michigan University | D38: Central Michigan | E38: Chippewas | F38: Mount Pleasant | G38: MI | H38: Public | I38: FBS | J38: Mid-American Conference | K38: 104 | L38: 120 | M38: 115 | N38: 113 | O38: American Football | P38: 10 | Q38: =P38*N38 -> 1130 | R38: {=IF(O38="American Football", XLOOKUP(C38, drafts_football!A:A, drafts_football!B:B, 0), "")} -> 8 | S38: =IF(Q38 = 0, 0, R38/Q38) -> 0.007079646 | T38: 0.013414865 | U38: =S38-T38 -> -0.0063352185
A39: https://en.wikipedia.org/wiki/Charleston_Southern_University | C39: Charleston Southern University | D39: Charleston Southern | E39: Buccaneers | F39: North Charleston | G39: SC | H39: Private | I39: FCS | J39: Big South Conference | N39: 0 | O39: American Football | P39: 10 | Q39: =P39*N39 -> 0 | R39: {=IF(O39="American Football", XLOOKUP(C39, drafts_football!A:A, drafts_football!B:B, 0), "")} -> 0 | S39: =IF(Q39 = 0, 0, R39/Q39) -> 0 | T39: 0.013414865 | U39: =S39-T39 -> -0.013414865
A40: https://en.wikipedia.org/wiki/Chicago_State_University | C40: Chicago State University | D40: Chicago State | E40: Cougars | F40: Chicago | G40: IL | H40: Public | I40: Non-football | J40: NEC | K40: 0 | L40: 0 | M40: 0 | N40: 0 | O40: American Football | P40: 10 | Q40: =P40*N40 -> 0 | R40: {=IF(O40="American Football", XLOOKUP(C40, drafts_football!A:A, drafts_football!B:B, 0), "")} -> 0 | S40: =IF(Q40 = 0, 0, R40/Q40) -> 0 | T40: 0.013414865 | U40: =S40-T40 -> -0.013414865
A41: https://en.wikipedia.org/wiki/Clemson_University | B41: https://www.sports-reference.com/cfb/schools/clemson/ | C41: Clemson University | D41: Clemson | E41: Tigers | F41: Clemson | G41: SC | H41: Public | I41: FBS | J41: Atlantic Coast Conference | K41: 126 | L41: 136 | M41: 136 | N41: 132.7 | O41: American Football | P41: 10 | Q41: =P41*N41 -> 1327 | R41: {=IF(O41="American Football", XLOOKUP(C41, drafts_football!A:A, drafts_football!B:B, 0), "")} -> 52 | S41: =IF(Q41 = 0, 0, R41/Q41) -> 0.039186134 | T41: 0.013414865 | U41: =S41-T41 -> 0.02577127
A42: https://en.wikipedia.org/wiki/Cleveland_State_University | C42: Cleveland State University | D42: Cleveland State | E42: Vikings | F42: Cleveland | G42: OH | H42: Public | I42: Non-football | J42: Horizon League | K42: 0 | L42: 0 | M42: 0 | N42: 0 | O42: American Football | P42: 10 | Q42: =P42*N42 -> 0 | R42: {=IF(O42="American Football", XLOOKUP(C42, drafts_football!A:A, drafts_football!B:B, 0), "")} -> 0 | S42: =IF(Q42 = 0, 0, R42/Q42) -> 0 | T42: 0.013414865 | U42: =S42-T42 -> -0.013414865
A43: https://en.wikipedia.org/wiki/Coastal_Carolina_University | B43: https://www.sports-reference.com/cfb/schools/coastal-carolina/ | C43: Coastal Carolina University | D43: Coastal Carolina | E43: Chanticleers | F43: Conway | G43: SC | H43: Public | I43: FBS | J43: Sun Belt Conference | K43: 106 | L43: 119 | M43: 116 | N43: 113.7 | O43: American Football | P43: 10 | Q43: =P43*N43 -> 1137 | R43: {=IF(O43="American Football", XLOOKUP(C43, drafts_football!A:A, drafts_football!B:B, 0), "")} -> 4 | S43: =IF(Q43 = 0, 0, R43/Q43) -> 0.0035180299 | T43: 0.013414865 | U43: =S43-T43 -> -0.0098968347
A44: https://en.wikipedia.org/wiki/Colgate_University | C44: Colgate University | D44: Colgate | E44: Raiders | F44: Hamilton | G44: NY | H44: Private | I44: FCS | J44: Patriot League | N44: 0 | O44: American Football | P44: 10 | Q44: =P44*N44 -> 0 | R44: {=IF(O44="American Football", XLOOKUP(C44, drafts_football!A:A, drafts_football!B:B, 0), "")} -> 0 | S44: =IF(Q44 = 0, 0, R44/Q44) -> 0 | T44: 0.013414865 | U44: =S44-T44 -> -0.013414865
A45: https://en.wikipedia.org/wiki/College_of_Charleston | C45: College of Charleston | D45: Charleston | E45: Cougars | F45: Charleston | G45: SC | H45: Public | I45: Non-football | J45: Coastal Athletic Association | K45: 0 | L45: 0 | M45: 0 | N45: 0 | O45: American Football | P45: 10 | Q45: =P45*N45 -> 0 | R45: {=IF(O45="American Football", XLOOKUP(C45, drafts_football!A:A, drafts_football!B:B, 0), "")} -> 0 | S45: =IF(Q45 = 0, 0, R45/Q45) -> 0 | T45: 0.013414865 | U45: =S45-T45 -> -0.013414865
A46: https://en.wikipedia.org/wiki/College_of_the_Holy_Cross | C46: College of the Holy Cross | D46: Holy Cross | E46: Crusaders | F46: Worcester | G46: MA | H46: Private | I46: FCS | J46: Patriot League | N46: 0 | O46: American Football | P46: 10 | Q46: =P46*N46 -> 0 | R46: {=IF(O46="American Football", XLOOKUP(C46, drafts_football!A:A, drafts_football!B:B, 0), "")} -> 1 | S46: =IF(Q46 = 0, 0, R46/Q46) -> 0 | T46: 0.013414865 | U46: =S46-T46 -> -0.013414865
A47: https://en.wikipedia.org/wiki/Colorado_State_University | B47: https://www.sports-reference.com/cfb/schools/colorado-state/ | C47: Colorado State University | D47: Colorado State | E47: Rams | F47: Fort Collins | G47: CO | H47: Public | I47: FBS | J47: Mountain West Conference | K47: 108 | L47: 112 | M47: 113 | N47: 111 | O47: American Football | P47: 10 | Q47: =P47*N47 -> 1110 | R47: {=IF(O47="American Football", XLOOKUP(C47, drafts_football!A:A, drafts_football!B:B, 0), "")} -> 7 | S47: =IF(Q47 = 0, 0, R47/Q47) -> 0.0063063063 | T47: 0.013414865 | U47: =S47-T47 -> -0.0071085582
A48: https://en.wikipedia.org/wiki/Columbia_University | C48: Columbia University in the City of New York | D48: Columbia | E48: Lions | F48: New York | G48: NY | H48: Private | I48: FCS | J48: Ivy League | N48: 0 | O48: American Football | P48: 10 | Q48: =P48*N48 -> 0 | R48: {=IF(O48="American Football", XLOOKUP(C48, drafts_football!A:A, drafts_football!B:B, 0), "")} -> 0 | S48: =IF(Q48 = 0, 0, R48/Q48) -> 0 | T48: 0.013414865 | U48: =S48-T48 -> -0.013414865
A49: https://en.wikipedia.org/wiki/Coppin_State_University | C49: Coppin State University | D49: Coppin State | E49: Eagles | F49: Baltimore | G49: MD | H49: Public | I49: Non-football | J49: Mid-Eastern Athletic Conference | K49: 0 | L49: 0 | M49: 0 | N49: 0 | O49: American Football | P49: 10 | Q49: =P49*N49 -> 0 | R49: {=IF(O49="American Football", XLOOKUP(C49, drafts_football!A:A, drafts_football!B:B, 0), "")} -> 0 | S49: =IF(Q49 = 0, 0, R49/Q49) -> 0 | T49: 0.013414865 | U49: =S49-T49 -> -0.013414865
A50: https://en.wikipedia.org/wiki/Cornell_University | C50: Cornell University | D50: Cornell | E50: Big Red | F50: Ithaca | G50: NY | H50: Private | I50: FCS | J50: Ivy League | N50: 0 | O50: American Football | P50: 10 | Q50: =P50*N50 -> 0 | R50: {=IF(O50="American Football", XLOOKUP(C50, drafts_football!A:A, drafts_football!B:B, 0), "")} -> 0 | S50: =IF(Q50 = 0, 0, R50/Q50) -> 0 | T50: 0.013414865 | U50: =S50-T50 -> -0.013414865
A51: https://en.wikipedia.org/wiki/Creighton_University | C51: Creighton University | D51: Creighton | E51: Bluejays | F51: Omaha | G51: NE | H51: Private | I51: Non-football | J51: Big East Conference | K51: 0 | L51: 0 | M51: 0 | N51: 0 | O51: American Football | P51: 10 | Q51: =P51*N51 -> 0 | R51: {=IF(O51="American Football", XLOOKUP(C51, drafts_football!A:A, drafts_football!B:B, 0), "")} -> 0 | S51: =IF(Q51 = 0, 0, R51/Q51) -> 0 | T51: 0.013414865 | U51: =S51-T51 -> -0.013414865
A52: https://en.wikipedia.org/wiki/Dartmouth_College | C52: Dartmouth College | D52: Dartmouth | E52: Big Green | F52: Hanover | G52: NH | H52: Private | I52: FCS | J52: Ivy League | N52: 0 | O52: American Football | P52: 10 | Q52: =P52*N52 -> 0 | R52: {=IF(O52="American Football", XLOOKUP(C52, drafts_football!A:A, drafts_football!B:B, 0), "")} -> 0 | S52: =IF(Q52 = 0, 0, R52/Q52) -> 0 | T52: 0.013414865 | U52: =S52-T52 -> -0.013414865
A53: https://en.wikipedia.org/wiki/Davidson_College | C53: Davidson College | D53: Davidson | E53: Wildcats | F53: Davidson | G53: NC | H53: Private | I53: FCS | J53: Atlantic 10 Conference | N53: 0 | O53: American Football | P53: 10 | Q53: =P53*N53 -> 0 | R53: {=IF(O53="American Football", XLOOKUP(C53, drafts_football!A:A, drafts_football!B:B, 0), "")} -> 0 | S53: =IF(Q53 = 0, 0, R53/Q53) -> 0 | T53: 0.013414865 | U53: =S53-T53 -> -0.013414865
A54: https://en.wikipedia.org/wiki/Delaware_State_University | C54: Delaware State University | D54: Delaware State | E54: Hornets | F54: Dover | G54: DE | H54: Public | I54: FCS | J54: Mid-Eastern Athletic Conference | N54: 0 | O54: American Football | P54: 10 | Q54: =P54*N54 -> 0 | R54: {=IF(O54="American Football", XLOOKUP(C54, drafts_football!A:A, drafts_football!B:B, 0), "")} -> 0 | S54: =IF(Q54 = 0, 0, R54/Q54) -> 0 | T54: 0.013414865 | U54: =S54-T54 -> -0.013414865
A55: https://en.wikipedia.org/wiki/DePaul_University | C55: DePaul University | D55: DePaul | E55: Blue Demons | F55: Chicago | G55: IL | H55: Private | I55: Non-football | J55: Big East Conference | K55: 0 | L55: 0 | M55: 0 | N55: 0 | O55: American Football | P55: 10 | Q55: =P55*N55 -> 0 | R55: {=IF(O55="American Football", XLOOKUP(C55, drafts_football!A:A, drafts_football!B:B, 0), "")} -> 0 | S55: =IF(Q55 = 0, 0, R55/Q55) -> 0 | T55: 0.013414865 | U55: =S55-T55 -> -0.013414865
A56: https://en.wikipedia.org/wiki/Drake_University | C56: Drake University | D56: Drake | E56: Bulldogs | F56: Des Moines | G56: IA | H56: Private | I56: FCS | J56: Missouri Valley Conference | N56: 0 | O56: American Football | P56: 10 | Q56: =P56*N56 -> 0 | R56: {=IF(O56="American Football", XLOOKUP(C56, drafts_football!A:A, drafts_football!B:B, 0), "")} -> 1 | S56: =IF(Q56 = 0, 0, R56/Q56) -> 0 | T56: 0.013414865 | U56: =S56-T56 -> -0.013414865
A57: https://en.wikipedia.org/wiki/Drexel_University | C57: Drexel University | D57: Drexel | E57: Dragons | F57: Philadelphia | G57: PA | H57: Private | I57: Non-football | J57: Coastal Athletic Association | K57: 0 | L57: 0 | M57: 0 | N57: 0 | O57: American Football | P57: 10 | Q57: =P57*N57 -> 0 | R57: {=IF(O57="American Football", XLOOKUP(C57, drafts_football!A:A, drafts_football!B:B, 0), "")} -> 0 | S57: =IF(Q57 = 0, 0, R57/Q57) -> 0 | T57: 0.013414865 | U57: =S57-T57 -> -0.013414865
A58: https://en.wikipedia.org/wiki/Duke_University | B58: https://www.sports-reference.com/cfb/schools/duke/ | C58: Duke University | D58: Duke | E58: Blue Devils | F58: Durham | G58: NC | H58: Private | I58: FBS | J58: Atlantic Coast Conference | K58: 104 | L58: 118 | M58: 111 | N58: 111 | O58: American Football | P58: 10 | Q58: =P58*N58 -> 1110 | R58: {=IF(O58="American Football", XLOOKUP(C58, drafts_football!A:A, drafts_football!B:B, 0), "")} -> 8 | S58: =IF(Q58 = 0, 0, R58/Q58) -> 0.0072072072 | T58: 0.013414865 | U58: =S58-T58 -> -0.0062076573
A59: https://en.wikipedia.org/wiki/Duquesne_University | C59: Duquesne University of the Holy Spirit | D59: Duquesne | E59: Dukes | F59: Pittsburgh | G59: PA | H59: Private | I59: FCS | J59: Atlantic 10 Conference | N59: 0 | O59: American Football | P59: 10 | Q59: =P59*N59 -> 0 | R59: {=IF(O59="American Football", XLOOKUP(C59, drafts_football!A:A, drafts_football!B:B, 0), "")} -> 0 | S59: =IF(Q59 = 0, 0, R59/Q59) -> 0 | T59: 0.013414865 | U59: =S59-T59 -> -0.013414865
A60: https://en.wikipedia.org/wiki/East_Carolina_University | B60: https://www.sports-reference.com/cfb/schools/east-carolina/ | C60: East Carolina University | D60: East Carolina | E60: Pirates | F60: Greenville | G60: NC | H60: Public | I60: FBS | J60: American Conference | K60: 122 | L60: 134 | M60: 123 | N60: 126.3 | O60: American Football | P60: 10 | Q60: =P60*N60 -> 1263 | R60: {=IF(O60="American Football", XLOOKUP(C60, drafts_football!A:A, drafts_football!B:B, 0), "")} -> 3 | S60: =IF(Q60 = 0, 0, R60/Q60) -> 0.0023752969 | T60: 0.013414865 | U60: =S60-T60 -> -0.011039568
A61: https://en.wikipedia.org/wiki/Eastern_Illinois_University | C61: Eastern Illinois University | D61: Eastern Illinois | E61: Panthers | F61: Charleston | G61: IL | H61: Public | I61: FCS | J61: Ohio Valley Conference | N61: 0 | O61: American Football | P61: 10 | Q61: =P61*N61 -> 0 | R61: {=IF(O61="American Football", XLOOKUP(C61, drafts_football!A:A, drafts_football!B:B, 0), "")} -> 1 | S61: =IF(Q61 = 0, 0, R61/Q61) -> 0 | T61: 0.013414865 | U61: =S61-T61 -> -0.013414865
A62: https://en.wikipedia.org/wiki/Eastern_Kentucky_University | C62: Eastern Kentucky University | D62: Eastern Kentucky | E62: Colonels | F62: Richmond | G62: KY | H62: Public | I62: FCS | J62: Atlantic Sun Conference | N62: 0 | O62: American Football | P62: 10 | Q62: =P62*N62 -> 0 | R62: {=IF(O62="American Football", XLOOKUP(C62, drafts_football!A:A, drafts_football!B:B, 0), "")} -> 2 | S62: =IF(Q62 = 0, 0, R62/Q62) -> 0 | T62: 0.013414865 | U62: =S62-T62 -> -0.013414865
A63: https://en.wikipedia.org/wiki/Eastern_Michigan_University | B63: https://www.sports-reference.com/cfb/schools/eastern-michigan/ | C63: Eastern Michigan University | D63: Eastern Michigan | E63: Eagles | F63: Ypsilanti | G63: MI | H63: Public | I63: FBS | J63: Mid-American Conference | K63: 112 | L63: 119 | M63: 112 | N63: 114.3 | O63: American Football | P63: 10 | Q63: =P63*N63 -> 1143 | R63: {=IF(O63="American Football", XLOOKUP(C63, drafts_football!A:A, drafts_football!B:B, 0), "")} -> 5 | S63: =IF(Q63 = 0, 0, R63/Q63) -> 0.0043744532 | T63: 0.013414865 | U63: =S63-T63 -> -0.0090404114
A64: https://en.wikipedia.org/wiki/Eastern_Washington_University | C64: Eastern Washington University | D64: Eastern Washington | E64: Eagles | F64: Cheney | G64: WA | H64: Public | I64: FCS | J64: Big Sky Conference | N64: 0 | O64: American Football | P64: 10 | Q64: =P64*N64 -> 0 | R64: {=IF(O64="American Football", XLOOKUP(C64, drafts_football!A:A, drafts_football!B:B, 0), "")} -> 2 | S64: =IF(Q64 = 0, 0, R64/Q64) -> 0 | T64: 0.013414865 | U64: =S64-T64 -> -0.013414865
A65: https://en.wikipedia.org/wiki/East_Tennessee_State_University | C65: East Tennessee State University | D65: East Tennessee State | E65: Buccaneers | F65: Johnson City | G65: TN | H65: Public | I65: FCS | J65: Southern Conference | N65: 0 | O65: American Football | P65: 10 | Q65: =P65*N65 -> 0 | R65: {=IF(O65="American Football", XLOOKUP(C65, drafts_football!A:A, drafts_football!B:B, 0), "")} -> 0 | S65: =IF(Q65 = 0, 0, R65/Q65) -> 0 | T65: 0.013414865 | U65: =S65-T65 -> -0.013414865
A66: https://en.wikipedia.org/wiki/East_Texas_A%26M_University | C66: East Texas A&M University | D66: East Texas A&M | E66: Lions | F66: Commerce | G66: TX | H66: Public | I66: FCS | J66: Southland Conference | N66: 0 | O66: American Football | P66: 10 | Q66: =P66*N66 -> 0 | R66: {=IF(O66="American Football", XLOOKUP(C66, drafts_football!A:A, drafts_football!B:B, 0), "")} -> 1 | S66: =IF(Q66 = 0, 0, R66/Q66) -> 0 | T66: 0.013414865 | U66: =S66-T66 -> -0.013414865
A67: https://en.wikipedia.org/wiki/Elon_University | C67: Elon University | D67: Elon | E67: Phoenix | F67: Elon | G67: NC | H67: Private | I67: FCS | J67: Coastal Athletic Association | N67: 0 | O67: American Football | P67: 10 | Q67: =P67*N67 -> 0 | R67: {=IF(O67="American Football", XLOOKUP(C67, drafts_football!A:A, drafts_football!B:B, 0), "")} -> 1 | S67: =IF(Q67 = 0, 0, R67/Q67) -> 0 | T67: 0.013414865 | U67: =S67-T67 -> -0.013414865
A68: https://en.wikipedia.org/wiki/Fairfield_University | C68: Fairfield University | D68: Fairfield | E68: Stags | F68: Fairfield | G68: CT | H68: Private | I68: Non-football | J68: Metro Atlantic Athletic Conference | K68: 0 | L68: 0 | M68: 0 | N68: 0 | O68: American Football | P68: 10 | Q68: =P68*N68 -> 0 | R68: {=IF(O68="American Football", XLOOKUP(C68, drafts_football!A:A, drafts_football!B:B, 0), "")} -> 0 | S68: =IF(Q68 = 0, 0, R68/Q68) -> 0 | T68: 0.013414865 | U68: =S68-T68 -> -0.013414865
A69: https://en.wikipedia.org/wiki/Fairleigh_Dickinson_University | C69: Fairleigh Dickinson University | D69: Fairleigh Dickinson | E69: Knights | F69: Hackensack | G69: NJ | H69: Private | I69: Non-football | J69: NEC | K69: 0 | L69: 0 | M69: 0 | N69: 0 | O69: American Football | P69: 10 | Q69: =P69*N69 -> 0 | R69: {=IF(O69="American Football", XLOOKUP(C69, drafts_football!A:A, drafts_football!B:B, 0), "")} -> 0 | S69: =IF(Q69 = 0, 0, R69/Q69) -> 0 | T69: 0.013414865 | U69: =S69-T69 -> -0.013414865
A70: https://en.wikipedia.org/wiki/Florida_A%26M_University | C70: Florida Agricultural and Mechanical University | D70: Florida A&M | E70: Rattlers | F70: Tallahassee | G70: FL | H70: Public | I70: FCS | J70: Southwestern Athletic Conference | N70: 0 | O70: American Football | P70: 10 | Q70: =P70*N70 -> 0 | R70: {=IF(O70="American Football", XLOOKUP(C70, drafts_football!A:A, drafts_football!B:B, 0), "")} -> 0 | S70: =IF(Q70 = 0, 0, R70/Q70) -> 0 | T70: 0.013414865 | U70: =S70-T70 -> -0.013414865
A71: https://en.wikipedia.org/wiki/Florida_Atlantic_University | B71: https://www.sports-reference.com/cfb/schools/florida-atlantic/ | C71: Florida Atlantic University | D71: Florida Atlantic | E71: Owls | F71: Boca Raton | G71: FL | H71: Public | I71: FBS | J71: American Conference | K71: 108 | L71: 115 | M71: 114 | N71: 112.3 | O71: American Football | P71: 10 | Q71: =P71*N71 -> 1123 | R71: {=IF(O71="American Football", XLOOKUP(C71, drafts_football!A:A, drafts_football!B:B, 0), "")} -> 4 | S71: =IF(Q71 = 0, 0, R71/Q71) -> 0.0035618878 | T71: 0.013414865 | U71: =S71-T71 -> -0.0098529768
A72: https://en.wikipedia.org/wiki/Florida_Gulf_Coast_University | C72: Florida Gulf Coast University | D72: FGCU | E72: Eagles | F72: Fort Myers | G72: FL | H72: Public | I72: Non-football | J72: Atlantic Sun Conference | K72: 0 | L72: 0 | M72: 0 | N72: 0 | O72: American Football | P72: 10 | Q72: =P72*N72 -> 0 | R72: {=IF(O72="American Football", XLOOKUP(C72, drafts_football!A:A, drafts_football!B:B, 0), "")} -> 0 | S72: =IF(Q72 = 0, 0, R72/Q72) -> 0 | T72: 0.013414865 | U72: =S72-T72 -> -0.013414865
A73: https://en.wikipedia.org/wiki/Florida_International_University | B73: https://www.sports-reference.com/cfb/schools/florida-international/ | C73: Florida International University | D73: FIU | E73: Panthers | F73: Miami | G73: FL | H73: Public | I73: FBS | J73: Conference USA | K73: 107 | L73: 115 | M73: 114 | N73: 112 | O73: American Football | P73: 10 | Q73: =P73*N73 -> 1120 | R73: {=IF(O73="American Football", XLOOKUP(C73, drafts_football!A:A, drafts_football!B:B, 0), "")} -> 4 | S73: =IF(Q73 = 0, 0, R73/Q73) -> 0.0035714286 | T73: 0.013414865 | U73: =S73-T73 -> -0.009843436
A74: https://en.wikipedia.org/wiki/Florida_State_University | B74: https://www.sports-reference.com/cfb/schools/florida-state/ | C74: Florida State University | D74: Florida State | E74: Seminoles | F74: Tallahassee | G74: FL | H74: Public | I74: FBS | J74: Atlantic Coast Conference | K74: 106 | L74: 124 | M74: 124 | N74: 118 | O74: American Football | P74: 10 | Q74: =P74*N74 -> 1180 | R74: {=IF(O74="American Football", XLOOKUP(C74, drafts_football!A:A, drafts_football!B:B, 0), "")} -> 33 | S74: =IF(Q74 = 0, 0, R74/Q74) -> 0.027966102 | T74: 0.013414865 | U74: =S74-T74 -> 0.014551237
A75: https://en.wikipedia.org/wiki/Fordham_University | C75: Fordham University | D75: Fordham | E75: Rams | F75: Bronx | G75: NY | H75: Private | I75: FCS | J75: Atlantic 10 Conference | N75: 0 | O75: American Football | P75: 10 | Q75: =P75*N75 -> 0 | R75: {=IF(O75="American Football", XLOOKUP(C75, drafts_football!A:A, drafts_football!B:B, 0), "")} -> 2 | S75: =IF(Q75 = 0, 0, R75/Q75) -> 0 | T75: 0.013414865 | U75: =S75-T75 -> -0.013414865
A76: https://en.wikipedia.org/wiki/Furman_University | C76: Furman University | D76: Furman | E76: Paladins | F76: Greenville | G76: SC | H76: Private | I76: FCS | J76: Southern Conference | N76: 0 | O76: American Football | P76: 10 | Q76: =P76*N76 -> 0 | R76: {=IF(O76="American Football", XLOOKUP(C76, drafts_football!A:A, drafts_football!B:B, 0), "")} -> 0 | S76: =IF(Q76 = 0, 0, R76/Q76) -> 0 | T76: 0.013414865 | U76: =S76-T76 -> -0.013414865
A77: https://en.wikipedia.org/wiki/Gardner%E2%80%93Webb_University | C77: Gardner–Webb University | D77: Gardner–Webb | E77: Runnin' Bulldogs | F77: Boiling Springs | G77: NC | H77: Private | I77: FCS | J77: Big South Conference | N77: 0 | O77: American Football | P77: 10 | Q77: =P77*N77 -> 0 | R77: {=IF(O77="American Football", XLOOKUP(C77, drafts_football!A:A, drafts_football!B:B, 0), "")} -> 0 | S77: =IF(Q77 = 0, 0, R77/Q77) -> 0 | T77: 0.013414865 | U77: =S77-T77 -> -0.013414865
A78: https://en.wikipedia.org/wiki/George_Mason_University | C78: George Mason University | D78: George Mason | E78: Patriots | F78: Fairfax | G78: VA | H78: Public | I78: Non-football | J78: Atlantic 10 Conference | K78: 0 | L78: 0 | M78: 0 | N78: 0 | O78: American Football | P78: 10 | Q78: =P78*N78 -> 0 | R78: {=IF(O78="American Football", XLOOKUP(C78, drafts_football!A:A, drafts_football!B:B, 0), "")} -> 0 | S78: =IF(Q78 = 0, 0, R78/Q78) -> 0 | T78: 0.013414865 | U78: =S78-T78 -> -0.013414865
A79: https://en.wikipedia.org/wiki/Georgetown_University | C79: Georgetown University | D79: Georgetown | E79: Hoyas | F79: Washington | G79: DC | H79: Private | I79: FCS | J79: Big East Conference | N79: 0 | O79: American Football | P79: 10 | Q79: =P79*N79 -> 0 | R79: {=IF(O79="American Football", XLOOKUP(C79, drafts_football!A:A, drafts_football!B:B, 0), "")} -> 0 | S79: =IF(Q79 = 0, 0, R79/Q79) -> 0 | T79: 0.013414865 | U79: =S79-T79 -> -0.013414865
A80: https://en.wikipedia.org/wiki/Georgia_Tech | B80: https://www.sports-reference.com/cfb/schools/georgia-tech/ | C80: Georgia Institute of Technology | D80: Georgia Tech | E80: Yellow Jackets | F80: Atlanta | G80: GA | H80: Public | I80: FBS | J80: Atlantic Coast Conference | K80: 105 | L80: 121 | M80: 114 | N80: 113.3 | O80: American Football | P80: 10 | Q80: =P80*N80 -> 1133 | R80: {=IF(O80="American Football", XLOOKUP(C80, drafts_football!A:A, drafts_football!B:B, 0), "")} -> 10 | S80: =IF(Q80 = 0, 0, R80/Q80) -> 0.0088261253 | T80: 0.013414865 | U80: =S80-T80 -> -0.0045887392
A81: https://en.wikipedia.org/wiki/Georgia_Southern_University | B81: https://www.sports-reference.com/cfb/schools/georgia-southern/ | C81: Georgia Southern University | D81: Georgia Southern | E81: Eagles | F81: Statesboro | G81: GA | H81: Public | I81: FBS | J81: Sun Belt Conference | K81: 116 | L81: 125 | M81: 129 | N81: 123.3 | O81: American Football | P81: 10 | Q81: =P81*N81 -> 1233 | R81: {=IF(O81="American Football", XLOOKUP(C81, drafts_football!A:A, drafts_football!B:B, 0), "")} -> 4 | S81: =IF(Q81 = 0, 0, R81/Q81) -> 0.00324412 | T81: 0.013414865 | U81: =S81-T81 -> -0.010170745
A82: https://en.wikipedia.org/wiki/Georgia_State_University | B82: https://www.sports-reference.com/cfb/schools/georgia-state/ | C82: Georgia State University | D82: Georgia State | E82: Panthers | F82: Atlanta | G82: GA | H82: Public | I82: FBS | J82: Sun Belt Conference | K82: 121 | L82: 119 | M82: 108 | N82: 116 | O82: American Football | P82: 10 | Q82: =P82*N82 -> 1160 | R82: {=IF(O82="American Football", XLOOKUP(C82, drafts_football!A:A, drafts_football!B:B, 0), "")} -> 2 | S82: =IF(Q82 = 0, 0, R82/Q82) -> 0.0017241379 | T82: 0.013414865 | U82: =S82-T82 -> -0.011690727
A83: https://en.wikipedia.org/wiki/Gonzaga_University | C83: Gonzaga University | D83: Gonzaga | E83: Bulldogs | F83: Spokane | G83: WA | H83: Private | I83: Non-football | J83: West Coast Conference | K83: 0 | L83: 0 | M83: 0 | N83: 0 | O83: American Football | P83: 10 | Q83: =P83*N83 -> 0 | R83: {=IF(O83="American Football", XLOOKUP(C83, drafts_football!A:A, drafts_football!B:B, 0), "")} -> 0 | S83: =IF(Q83 = 0, 0, R83/Q83) -> 0 | T83: 0.013414865 | U83: =S83-T83 -> -0.013414865
A84: https://en.wikipedia.org/wiki/Grambling_State_University | C84: Grambling State University | D84: Grambling State | E84: Tigers | F84: Grambling | G84: LA | H84: Public | I84: FCS | J84: Southwestern Athletic Conference | N84: 0 | O84: American Football | P84: 10 | Q84: =P84*N84 -> 0 | R84: {=IF(O84="American Football", XLOOKUP(C84, drafts_football!A:A, drafts_football!B:B, 0), "")} -> 1 | S84: =IF(Q84 = 0, 0, R84/Q84) -> 0 | T84: 0.013414865 | U84: =S84-T84 -> -0.013414865
A85: https://en.wikipedia.org/wiki/Grand_Canyon_University | C85: Grand Canyon University | D85: Grand Canyon | E85: Antelopes | F85: Phoenix | G85: AZ | H85: Private | I85: Non-football | J85: Mountain West Conference | K85: 0 | L85: 0 | M85: 0 | N85: 0 | O85: American Football | P85: 10 | Q85: =P85*N85 -> 0 | R85: {=IF(O85="American Football", XLOOKUP(C85, drafts_football!A:A, drafts_football!B:B, 0), "")} -> 0 | S85: =IF(Q85 = 0, 0, R85/Q85) -> 0 | T85: 0.013414865 | U85: =S85-T85 -> -0.013414865
A86: https://en.wikipedia.org/wiki/Hampton_University | C86: Hampton University | D86: Hampton | E86: Pirates | F86: Hampton | G86: VA | H86: Private | I86: FCS | J86: Coastal Athletic Association | N86: 0 | O86: American Football | P86: 10 | Q86: =P86*N86 -> 0 | R86: {=IF(O86="American Football", XLOOKUP(C86, drafts_football!A:A, drafts_football!B:B, 0), "")} -> 0 | S86: =IF(Q86 = 0, 0, R86/Q86) -> 0 | T86: 0.013414865 | U86: =S86-T86 -> -0.013414865
A87: https://en.wikipedia.org/wiki/Harvard_University | C87: Harvard University | D87: Harvard | E87: Crimson | F87: Cambridge | G87: MA | H87: Private | I87: FCS | J87: Ivy League | N87: 0 | O87: American Football | P87: 10 | Q87: =P87*N87 -> 0 | R87: {=IF(O87="American Football", XLOOKUP(C87, drafts_football!A:A, drafts_football!B:B, 0), "")} -> 1 | S87: =IF(Q87 = 0, 0, R87/Q87) -> 0 | T87: 0.013414865 | U87: =S87-T87 -> -0.013414865
A88: https://en.wikipedia.org/wiki/High_Point_University | C88: High Point University | D88: High Point | E88: Panthers | F88: High Point | G88: NC | H88: Private | I88: Non-football | J88: Big South Conference | K88: 0 | L88: 0 | M88: 0 | N88: 0 | O88: American Football | P88: 10 | Q88: =P88*N88 -> 0 | R88: {=IF(O88="American Football", XLOOKUP(C88, drafts_football!A:A, drafts_football!B:B, 0), "")} -> 0 | S88: =IF(Q88 = 0, 0, R88/Q88) -> 0 | T88: 0.013414865 | U88: =S88-T88 -> -0.013414865
A89: https://en.wikipedia.org/wiki/Hofstra_University | C89: Hofstra University | D89: Hofstra | E89: Pride | F89: Hempstead | G89: NY | H89: Private | I89: Non-football | J89: Coastal Athletic Association | K89: 0 | L89: 0 | M89: 0 | N89: 0 | O89: American Football | P89: 10 | Q89: =P89*N89 -> 0 | R89: {=IF(O89="American Football", XLOOKUP(C89, drafts_football!A:A, drafts_football!B:B, 0), "")} -> 0 | S89: =IF(Q89 = 0, 0, R89/Q89) -> 0 | T89: 0.013414865 | U89: =S89-T89 -> -0.013414865
A90: https://en.wikipedia.org/wiki/Houston_Christian_University | C90: Houston Christian University | D90: Houston Christian | E90: Huskies | F90: Houston | G90: TX | H90: Private | I90: FCS | J90: Southland Conference | N90: 0 | O90: American Football | P90: 10 | Q90: =P90*N90 -> 0 | R90: {=IF(O90="American Football", XLOOKUP(C90, drafts_football!A:A, drafts_football!B:B, 0), "")} -> 1 | S90: =IF(Q90 = 0, 0, R90/Q90) -> 0 | T90: 0.013414865 | U90: =S90-T90 -> -0.013414865
A91: https://en.wikipedia.org/wiki/Howard_University | C91: Howard University | D91: Howard | E91: Bison | F91: Washington | G91: DC | H91: Private | I91: FCS | J91: Mid-Eastern Athletic Conference | N91: 0 | O91: American Football | P91: 10 | Q91: =P91*N91 -> 0 | R91: {=IF(O91="American Football", XLOOKUP(C91, drafts_football!A:A, drafts_football!B:B, 0), "")} -> 0 | S91: =IF(Q91 = 0, 0, R91/Q91) -> 0 | T91: 0.013414865 | U91: =S91-T91 -> -0.013414865
A92: https://en.wikipedia.org/wiki/Idaho_State_University | C92: Idaho State University | D92: Idaho State | E92: Bengals | F92: Pocatello | G92: ID | H92: Public | I92: FCS | J92: Big Sky Conference | N92: 0 | O92: American Football | P92: 10 | Q92: =P92*N92 -> 0 | R92: {=IF(O92="American Football", XLOOKUP(C92, drafts_football!A:A, drafts_football!B:B, 0), "")} -> 0 | S92: =IF(Q92 = 0, 0, R92/Q92) -> 0 | T92: 0.013414865 | U92: =S92-T92 -> -0.013414865
A93: https://en.wikipedia.org/wiki/Illinois_State_University | C93: Illinois State University | D93: Illinois State | E93: Redbirds | F93: Normal | G93: IL | H93: Public | I93: FCS | J93: Missouri Valley Conference | N93: 0 | O93: American Football | P93: 10 | Q93: =P93*N93 -> 0 | R93: {=IF(O93="American Football", XLOOKUP(C93, drafts_football!A:A, drafts_football!B:B, 0), "")} -> 1 | S93: =IF(Q93 = 0, 0, R93/Q93) -> 0 | T93: 0.013414865 | U93: =S93-T93 -> -0.013414865
A94: https://en.wikipedia.org/wiki/Indiana_State_University | C94: Indiana State University | D94: Indiana State | E94: Sycamores | F94: Terre Haute | G94: IN | H94: Public | I94: FCS | J94: Missouri Valley Conference | N94: 0 | O94: American Football | P94: 10 | Q94: =P94*N94 -> 0 | R94: {=IF(O94="American Football", XLOOKUP(C94, drafts_football!A:A, drafts_football!B:B, 0), "")} -> 0 | S94: =IF(Q94 = 0, 0, R94/Q94) -> 0 | T94: 0.013414865 | U94: =S94-T94 -> -0.013414865
A95: https://en.wikipedia.org/wiki/Indiana_University_Bloomington | B95: https://www.sports-reference.com/cfb/schools/indiana/ | C95: Indiana University Bloomington | D95: Indiana | E95: Hoosiers | F95: Bloomington | G95: IN | H95: Public | I95: FBS | J95: Big Ten Conference | K95: 106 | L95: 113 | M95: 121 | N95: 113.3 | O95: American Football | P95: 10 | Q95: =P95*N95 -> 1133 | R95: {=IF(O95="American Football", XLOOKUP(C95, drafts_football!A:A, drafts_football!B:B, 0), "")} -> 12 | S95: =IF(Q95 = 0, 0, R95/Q95) -> 0.01059135 | T95: 0.013414865 | U95: =S95-T95 -> -0.0028235142
A96: https://en.wikipedia.org/wiki/Indiana_University_Indianapolis | C96: Indiana University Indianapolis | D96: IU Indy | E96: Jaguars | F96: Indianapolis | G96: IN | H96: Public | I96: Non-football | J96: Horizon League | K96: 0 | L96: 0 | M96: 0 | N96: 0 | O96: American Football | P96: 10 | Q96: =P96*N96 -> 0 | R96: {=IF(O96="American Football", XLOOKUP(C96, drafts_football!A:A, drafts_football!B:B, 0), "")} -> 0 | S96: =IF(Q96 = 0, 0, R96/Q96) -> 0 | T96: 0.013414865 | U96: =S96-T96 -> -0.013414865
A97: https://en.wikipedia.org/wiki/Iona_University | C97: Iona University | D97: Iona | E97: Gaels | F97: New Rochelle | G97: NY | H97: Private | I97: Non-football | J97: Metro Atlantic Athletic Conference | K97: 0 | L97: 0 | M97: 0 | N97: 0 | O97: American Football | P97: 10 | Q97: =P97*N97 -> 0 | R97: {=IF(O97="American Football", XLOOKUP(C97, drafts_football!A:A, drafts_football!B:B, 0), "")} -> 0 | S97: =IF(Q97 = 0, 0, R97/Q97) -> 0 | T97: 0.013414865 | U97: =S97-T97 -> -0.013414865
A98: https://en.wikipedia.org/wiki/Iowa_State_University | B98: https://www.sports-reference.com/cfb/schools/iowa-state/ | C98: Iowa State University of Science and Technology | D98: Iowa State | E98: Cyclones | F98: Ames | G98: IA | H98: Public | I98: FBS | J98: Big 12 Conference | K98: 121 | L98: 133 | M98: 132 | N98: 128.7 | O98: American Football | P98: 10 | Q98: =P98*N98 -> 1287 | R98: {=IF(O98="American Football", XLOOKUP(C98, drafts_football!A:A, drafts_football!B:B, 0), "")} -> 15 | S98: =IF(Q98 = 0, 0, R98/Q98) -> 0.011655012 | T98: 0.013414865 | U98: =S98-T98 -> -0.0017598529
A99: https://en.wikipedia.org/wiki/Jackson_State_University | C99: Jackson State University | D99: Jackson State | E99: Tigers | F99: Jackson | G99: MS | H99: Public | I99: FCS | J99: Southwestern Athletic Conference | N99: 0 | O99: American Football | P99: 10 | Q99: =P99*N99 -> 0 | R99: {=IF(O99="American Football", XLOOKUP(C99, drafts_football!A:A, drafts_football!B:B, 0), "")} -> 2 | S99: =IF(Q99 = 0, 0, R99/Q99) -> 0 | T99: 0.013414865 | U99: =S99-T99 -> -0.013414865
A100: https://en.wikipedia.org/wiki/Jacksonville_State_University | B100: https://www.sports-reference.com/cfb/schools/jacksonville-state/ | C100: Jacksonville State University | D100: Jax State | E100: Gamecocks | F100: Jacksonville | G100: AL | H100: Public | I100: FBS | J100: Conference USA | K100: 117 | L100: 126 | M100: 128 | N100: 123.7 | O100: American Football | P100: 10 | Q100: =P100*N100 -> 1237 | R100: {=IF(O100="American Football", XLOOKUP(C100, drafts_football!A:A, drafts_football!B:B, 0), "")} -> 1 | S100: =IF(Q100 = 0, 0, R100/Q100) -> 0.00080840744 | T100: 0.013414865 | U100: =S100-T100 -> -0.012606457
...

Sheet Top_Football
A1: School name | B1: State | C1: Conference | D1: Estimated Athlete pool | E1: Pro Players Count | F1: Draft Probability | G1: National Average | H1: Vs_National_Average
A2: Ohio State | B2: OH | C2: Big Ten Conference | D2: 1213 | E2: 84 | F2: 0.069249794 | G2: 0.013414865 | H2: 0.055834929
A3: Alabama | B3: AL | C3: Southeastern Conference | D3: 1327 | E3: 90 | F3: 0.067822155 | G3: 0.013414865 | H3: 0.054407291
A4: Georgia | B4: GA | C4: Southeastern Conference | D4: 1293 | E4: 80 | F4: 0.061871616 | G4: 0.013414865 | H4: 0.048456752
A5: Michigan | B5: MI | C5: Big Ten Conference | D5: 1333 | E5: 73 | F5: 0.054763691 | G5: 0.013414865 | H5: 0.041348826
A6: Florida | B6: FL | C6: Southeastern Conference | D6: 1233 | E6: 57 | F6: 0.04622871 | G6: 0.013414865 | H6: 0.032813846
A7: Notre Dame | B7: IN | C7: Atlantic Coast Conference | D7: 1170 | E7: 52 | F7: 0.044444444 | G7: 0.013414865 | H7: 0.03102958
A8: Penn State | B8: PA | C8: Big Ten Conference | D8: 1280 | E8: 56 | F8: 0.04375 | G8: 0.013414865 | H8: 0.030335135
A9: Clemson | B9: SC | C9: Atlantic Coast Conference | D9: 1327 | E9: 52 | F9: 0.039186134 | G9: 0.013414865 | H9: 0.02577127
A10: Miami (Florida) | B10: FL | C10: Atlantic Coast Conference | D10: 1150 | E10: 45 | F10: 0.039130435 | G10: 0.013414865 | H10: 0.02571557
A11: Texas | B11: TX | C11: Southeastern Conference | D11: 1163 | E11: 45 | F11: 0.038693035 | G11: 0.013414865 | H11: 0.025278171
A12: Oklahoma | B12: OK | C12: Southeastern Conference | D12: 1210 | E12: 46 | F12: 0.038016529 | G12: 0.013414865 | H12: 0.024601664
A13: Washington | B13: WA | C13: Big Ten Conference | D13: 1113 | E13: 41 | F13: 0.036837376 | G13: 0.013414865 | H13: 0.023422512
... A129: Texas State | B129: TX | C129: Sun Belt Conference | D129: 1170 | E129: 0 | F129: 0 | G129: 0.013414865 | H129: -0.013414865

Sheet MLB-athlete-per-school-count
A1: Drafted Out of | B1: City | C1: State | D1: Pro Players Count | E1: Num of Seasons | F1: Roster count 2026 | G1: Roster count 2025 | H1: Roster count 2024 | I1: Avg Roster Count Last 3 years | J1: Estimated Athlete Pool | K1: Draft Probability | L1: National Average | M1: Vs_National_Average
A2: University of Arkansas | B2: Fayetteville | C2: AR | D2: 76 | E2: 10 | F2: 34 | G2: 40 | H2: 40 | I2: 35 | J2: =I2*E2 -> 350 | K2: =D2/J2 -> 0.21714286 | L2: 0.026573227 | M2: =K2-L2 -> 0.19056963
A3: Vanderbilt University | B3: Nashville | C3: TN | D3: 72 | E3: 10 | F3: 34 | G3: 40 | H3: 40 | I3: 35 | J3: =I3*E3 -> 350 | K3: =D3/J3 -> 0.20571429 | L3: 0.026573227 | M3: =K3-L3 -> 0.17914106
A4: Louisiana State University | B4: Baton Rouge | C4: LA | D4: 68 | E4: 10 | F4: 34 | G4: 40 | H4: 40 | I4: 35 | J4: =I4*E4 -> 350 | K4: =D4/J4 -> 0.19428571 | L4: 0.026573227 | M4: =K4-L4 -> 0.16771249
A5: Mississippi State University | B5: Mississippi State | C5: MS | D5: 67 | E5: 10 | F5: 34 | G5: 40 | H5: 40 | I5: 35 | J5: =I5*E5 -> 350 | K5: =D5/J5 -> 0.19142857 | L5: 0.026573227 | M5: =K5-L5 -> 0.16485534
A6: Oklahoma State University | B6: Stillwater | C6: OK | D6: 62 | E6: 10 | F6: 34 | G6: 40 | H6: 40 | I6: 35 | J6: =I6*E6 -> 350 | K6: =D6/J6 -> 0.17714286 | L6: 0.026573227 | M6: =K6-L6 -> 0.15056963
A7: University of Tennessee | B7: Knoxville | C7: TN | D7: 62 | E7: 10 | F7: 34 | G7: 40 | H7: 40 | I7: 35 | J7: =I7*E7 -> 350 | K7: =D7/J7 -> 0.17714286 | L7: 0.026573227 | M7: =K7-L7 -> 0.15056963
A8: Texas A&M University | B8: College Station | C8: TX | D8: 60 | E8: 10 | F8: 34 | G8: 40 | H8: 40 | I8: 35 | J8: =I8*E8 -> 350 | K8: =D8/J8 -> 0.17142857 | L8: 0.026573227 | M8: =K8-L8 -> 0.14485534
A9: Texas Tech University | B9: Lubbock | C9: TX | D9: 59 | E9: 10 | F9: 34 | G9: 40 | H9: 40 | I9: 35 | J9: =I9*E9 -> 350 | K9: =D9/J9 -> 0.16857143 | L9: 0.026573227 | M9: =K9-L9 -> 0.1419982
A10: University of Mississippi | B10: Oxford | C10: MS | D10: 59 | E10: 10 | F10: 34 | G10: 40 | H10: 40 | I10: 35 | J10: =I10*E10 -> 350 | K10: =D10/J10 -> 0.16857143 | L10: 0.026573227 | M10: =K10-L10 -> 0.1419982
A11: University of Louisville | B11: Louisville | C11: KY | D11: 59 | E11: 10 | F11: 34 | G11: 40 | H11: 40 | I11: 35 | J11: =I11*E11 -> 350 | K11: =D11/J11 -> 0.16857143 | L11: 0.026573227 | M11: =K11-L11 -> 0.1419982
A12: University of Oklahoma | B12: Norman | C12: OK | D12: 57 | E12: 10 | F12: 34 | G12: 40 | H12: 40 | I12: 35 | J12: =I12*E12 -> 350 | K12: =D12/J12 -> 0.16285714 | L12: 0.026573227 | M12: =K12-L12 -> 0.13628392
A13: University of Florida | B13: Gainesville | C13: FL | D13: 56 | E13: 10 | F13: 34 | G13: 40 | H13: 40 | I13: 35 | J13: =I13*E13 -> 350 | K13: =D13/J13 -> 0.16 | L13: 0.026573227 | M13: =K13-L13 -> 0.13342677
... A553: Northern Oklahoma College-Tonkawa | B553: Tonkawa | C553: OK | D553: 1 | E553: 10 | F553: 34 | G553: 40 | H553: 40 | I553: 35 | J553: =I553*E553 -> 350 | K553: =D553/J553 -> 0.0028571429 | L553: 0.026573227 | M553: =K553-L553 -> -0.023716084
K554: =AVERAGE(K2:K553) -> 0.028850932

Sheet MLB-athlete-all-data-drafts
A1: Year | B1: Rnd | C1: OvPck | D1: RdPck | E1: Tm | F1: Signed | G1: Bonus | H1: Name | I1: Pos | J1: WAR | K1: G | L1: AB | M1: HR | N1: BA | O1: OPS | P1: G.1 | Q1: W | R1: L | S1: ERA | T1: WHIP | U1: SV | V1: Type | W1: Drafted Out of
A2: 2016 | B2: 1 | C2: 2 | D2: 2 | E2: Reds | F2: Y | G2: $6,200,000 | H2: Nick Senzel (minors) | I2: 3B | J2: -3.1 | K2: 451 | L2: 1466 | M2: 40 | N2: 0.232 | O2: 0.662 | V2: 4Yr | W2: University of Tennessee (Knoxville, TN)
A3: 2016 | B3: 1 | C3: 5 | D3: 5 | E3: Brewers | F3: Y | G3: $4,800,000 | H3: Corey Ray (minors) | I3: OF | J3: 0 | K3: 1 | L3: 2 | M3: 0 | N3: 0 | O3: 0.333 | V3: 4Yr | W3: University of Louisville (Louisville, KY)
A4: 2016 | B4: 1 | C4: 6 | D4: 6 | E4: Athletics | F4: Y | G4: $4,125,000 | H4: A.J. Puk (minors) | I4: LHP | J4: 3.4 | K4: 3 | L4: 0 | M4: 0 | P4: 212 | Q4: 17 | R4: 20 | S4: 3.53 | T4: 1.19 | U4: 26 | V4: 4Yr | W4: University of Florida (Gainesville, FL)
A5: 2016 | B5: 1 | C5: 8 | D5: 8 | E5: Padres | F5: Y | G5: $4,145,900 | H5: Cal Quantrill (minors) | I5: RHP | J5: 7.8 | K5: 24 | L5: 27 | M5: 0 | N5: 0.111 | O5: 0.254 | P5: 187 | Q5: 47 | R5: 46 | S5: 4.35 | T5: 1.33 | U5: 1 | V5: 4Yr | W5: Stanford University (Palo Alto, CA)
A6: 2016 | B6: 1 | C6: 10 | D6: 10 | E6: White Sox | F6: Y | G6: $3,380,600 | H6: Zack Collins (minors) | I6: C | J6: -1.1 | K6: 152 | L6: 398 | M6: 11 | N6: 0.188 | O6: 0.629 | V6: 4Yr | W6: University of Miami (Coral Gables, FL)
A7: 2016 | B7: 1 | C7: 11 | D7: 11 | E7: Mariners | F7: Y | G7: $3,286,700 | H7: Kyle Lewis (minors) | I7: OF | J7: 1.8 | K7: 146 | L7: 514 | M7: 26 | N7: 0.235 | O7: 0.732 | V7: 4Yr | W7: Mercer University (Macon, GA)
A8: 2016 | B8: 1 | C8: 16 | D8: 16 | E8: Angels | F8: Y | G8: $2,150,000 | H8: Matt Thaiss (minors) | I8: C | J8: 1.9 | K8: 305 | L8: 819 | M8: 23 | N8: 0.21 | O8: 0.652 | V8: 4Yr | W8: University of Virginia (Charlottesville, VA)
A9: 2016 | B9: 1 | C9: 19 | D9: 19 | E9: Mets | F9: Y | G9: $2,378,800 | H9: Justin Dunn (minors) | I9: RHP | J9: 1.5 | K9: 3 | L9: 4 | M9: 0 | N9: 0.25 | O9: 0.75 | P9: 32 | Q9: 6 | R9: 7 | S9: 4.44 | T9: 1.41 | U9: 0 | V9: 4Yr | W9: Boston College (Chestnut Hill, MA)
A10: 2016 | B10: 1 | C10: 21 | D10: 21 | E10: Blue Jays | F10: Y | G10: $2,175,000 | H10: T.J. Zeuch (minors) | I10: RHP | J10: -0.6 | K10: 1 | L10: 1 | M10: 0 | N10: 0 | O10: 0 | P10: 16 | Q10: 2 | R10: 7 | S10: 6.49 | T10: 1.79 | U10: 0 | V10: 4Yr | W10: University of Pittsburgh (Pittsburgh, PA)
A11: 2016 | B11: 1 | C11: 22 | D11: 22 | E11: Pirates | F11: Y | G11: $2,253,700 | H11: Will Craig (minors) | I11: 3B | J11: -0.7 | K11: 20 | L11: 64 | M11: 1 | N11: 0.203 | O11: 0.542 | V11: 4Yr | W11: Wake Forest University (Winston-Salem, NC)
A12: 2016 | B12: 1 | C12: 25 | D12: 25 | E12: Padres | F12: Y | G12: $2,000,000 | H12: Eric Lauer (minors) | I12: LHP | J12: 5.8 | K12: 76 | L12: 96 | M12: 1 | N12: 0.104 | O12: 0.321 | P12: 150 | Q12: 46 | R12: 40 | S12: 4.14 | T12: 1.33 | U12: 0 | V12: 4Yr | W12: Kent State University (Kent, OH)
A13: 2016 | B13: 1 | C13: 26 | D13: 26 | E13: White Sox | F13: Y | G13: $2,128,500 | H13: Zack Burdi (minors) | I13: RHP | J13: -0.8 | K13: 0 | L13: 0 | M13: 0 | P13: 18 | Q13: 0 | R13: 1 | S13: 8.44 | T13: 1.88 | U13: 0 | V13: 4Yr | W13: University of Louisville (Louisville, KY)
A14: 2016 | B14: 1 | C14: 27 | D14: 27 | E14: Orioles | F14: Y | G14: $2,097,200 | H14: Cody Sedlock (minors) | I14: RHP | J14: -0.1 | K14: 0 | L14: 0 | M14: 0 | P14: 1 | Q14: 0 | R14: 0 | S14: 15 | T14: 2.33 | U14: 0 | V14: 4Yr | W14: University of Illinois at Urbana-Champaign (Champaign, IL)
A15: 2016 | B15: 1 | C15: 29 | D15: 29 | E15: Nationals | F15: Y | G15: $2,000,000 | H15: Dane Dunning (minors) | I15: RHP | J15: 3.5 | K15: 2 | L15: 3 | M15: 0 | N15: 0.333 | O15: 0.667 | P15: 136 | Q15: 28 | R15: 32 | S15: 4.44 | T15: 1.37 | U15: 2 | V15: 4Yr | W15: University of Florida (Gainesville, FL)
A16: 2016 | B16: 1 | C16: 31 | D16: 31 | E16: Mets | F16: Y | G16: $1,100,000 | H16: Anthony Kay (minors) | I16: LHP | J16: 0.1 | K16: 4 | L16: 0 | M16: 0 | P16: 46 | Q16: 4 | R16: 2 | S16: 5.44 | T16: 1.58 | U16: 0 | V16: 4Yr | W16: University of Connecticut (Storrs, CT)
A17: 2016 | B17: 1 | C17: 32 | D17: 32 | E17: Dodgers | F17: Y | G17: $1,772,500 | H17: Will Smith (minors) | I17: C | J17: 23 | K17: 732 | L17: 2542 | M17: 130 | N17: 0.263 | O17: 0.832 | V17: 4Yr | W17: University of Louisville (Louisville, KY)
A18: 2016 | B18: 1 | C18: 34 | D18: 34 | E18: Cardinals | F18: Y | G18: $2,000,000 | H18: Dakota Hudson (minors) | I18: RHP | J18: 3.5 | K18: 56 | L18: 55 | M18: 0 | N18: 0.091 | O18: 0.214 | P18: 132 | Q18: 40 | R18: 32 | S18: 4.21 | T18: 1.43 | U18: 1 | V18: 4Yr | W18: Mississippi State University (Mississippi State, MS)
A19: 2016 | B19: 1 | C19: 36 | D19: 36 | E19: Dodgers | F19: Y | G19: $1,847,500 | H19: Jordan Sheffield (minors) | I19: RHP | J19: 0.7 | K19: 30 | L19: 0 | M19: 0 | P19: 32 | Q19: 0 | R19: 0 | S19: 3.16 | T19: 1.15 | U19: 0 | V19: 4Yr | W19: Vanderbilt University (Nashville, TN)
A20: 2016 | B20: 1 | C20: 37 | D20: 37 | E20: Athletics | F20: Y | G20: $1,600,000 | H20: Daulton Jefferies (minors) | I20: RHP | J20: -1 | K20: 0 | L20: 0 | M20: 0 | P20: 20 | Q20: 2 | R20: 10 | S20: 6.59 | T20: 1.46 | U20: 0 | V20: 4Yr | W20: University of California, Berkeley (Berkeley, CA)
A21: 2016 | B21: 1 | C21: 38 | D21: 38 | E21: Rockies | F21: Y | G21: $1,701,600 | H21: Robert Tyler (minors) | I21: RHP | V21: 4Yr | W21: University of Georgia (Athens, GA)
A22: 2016 | B22: 1 | C22: 39 | D22: 39 | E22: Diamondbacks | F22: Y | G22: $1,500,000 | H22: Anfernee Grier (minors) | I22: OF | V22: 4Yr | W22: Auburn University (Auburn, AL)
A23: 2016 | B23: 2 | C23: 43 | D23: 2 | E23: Reds | F23: Y | G23: $2,000,000 | H23: Chris Okey (minors) | I23: C | J23: -0.3 | K23: 9 | L23: 14 | M23: 0 | N23: 0.143 | O23: 0.343 | V23: 4Yr | W23: Clemson University (Clemson, SC)
A24: 2016 | B24: 2 | C24: 45 | D24: 4 | E24: Rockies | F24: Y | G24: $1,600,000 | H24: Ben Bowden (minors) | I24: LHP | J24: -0.6 | K24: 36 | L24: 0 | M24: 0 | P24: 50 | Q24: 3 | R24: 2 | S24: 6.02 | T24: 1.71 | U24: 0 | V24: 4Yr | W24: Vanderbilt University (Nashville, TN)
A25: 2016 | B25: 2 | C25: 46 | D25: 5 | E25: Brewers | F25: Y | G25: $1,150,000 | H25: Lucas Erceg (minors) | I25: 3B | J25: 2.8 | K25: 2 | L25: 0 | M25: 0 | P25: 177 | Q25: 14 | R25: 14 | S25: 3.55 | T25: 1.26 | U25: 19 | V25: 4Yr | W25: Menlo College (Atherton, CA)
A26: 2016 | B26: 2 | C26: 47 | D26: 6 | E26: Athletics | F26: Y | G26: $1,500,000 | H26: Logan Shore (minors) | I26: RHP | V26: 4Yr | W26: University of Florida (Gainesville, FL)
A27: 2016 | B27: 2 | C27: 48 | D27: 7 | E27: Padres | F27: Y | G27: $1,075,000 | H27: Michael Reed (minors) | I27: OF | V27: 4Yr | W27: University of Florida (Gainesville, FL)
A28: 2016 | B28: 2 | C28: 49 | D28: 8 | E28: White Sox | F28: Y | G28: $1,200,000 | H28: Alec Hansen (minors) | I28: RHP | V28: 4Yr | W28: University of Oklahoma (Norman, OK)
A29: 2016 | B29: 2 | C29: 51 | D29: 10 | E29: Red Sox | F29: Y | G29: $1,100,000 | H29: C.J. Chatham (minors) | I29: SS | V29: 4Yr | W29: Florida Atlantic University (Boca Raton, FL)
A30: 2016 | B30: 2 | C30: 53 | D30: 12 | E30: Rays | F30: Y | G30: $997,500 | H30: Ryan Boldt (minors) | I30: OF | V30: 4Yr | W30: University of Nebraska-Lincoln (Lincoln, NE)
A31: 2016 | B31: 2 | C31: 54 | D31: 13 | E31: Orioles | F31: Y | G31: $1,177,200 | H31: Keegan Akin (minors) | I31: LHP | J31: 1.9 | K31: 4 | L31: 2 | M31: 0 | N31: 0 | O31: 0 | P31: 231 | Q31: 16 | R31: 22 | S31: 4.48 | T31: 1.3 | U31: 11 | V31: 4Yr | W31: Western Michigan University (Kalamazoo, MI)
A32: 2016 | B32: 2 | C32: 57 | D32: 16 | E32: Blue Jays | F32: Y | G32: $975,000 | H32: J.B. Woodman (minors) | I32: OF | V32: 4Yr | W32: University of Mississippi (Oxford, MS)
A33: 2016 | B33: 2 | C33: 58 | D33: 17 | E33: Nationals | F33: Y | G33: $900,000 | H33: Sheldon Neuse (minors) | I33: 3B | J33: -0.8 | K33: 147 | L33: 392 | M33: 7 | N33: 0.212 | O33: 0.558 | P33: 3 | Q33: 0 | R33: 0 | S33: 0 | T33: 0.27 | U33: 0 | V33: 4Yr | W33: University of Oklahoma (Norman, OK)
A34: 2016 | B34: 2 | C34: 59 | D34: 18 | E34: Giants | F34: Y | G34: $1,350,000 | H34: Bryan Reynolds (minors) | I34: OF | J34: 21.3 | K34: 959 | L34: 3603 | M34: 140 | N34: 0.271 | O34: 0.804 | V34: 4Yr | W34: Vanderbilt University (Nashville, TN)
A35: 2016 | B35: 2 | C35: 61 | D35: 20 | E35: Astros | F35: Y | G35: $1,056,800 | H35: Ronnie Dawson (minors) | I35: OF | J35: -0.2 | K35: 4 | L35: 8 | M35: 0 | N35: 0.125 | O35: 0.347 | V35: 4Yr | W35: The Ohio State University (Columbus, OH)
A36: 2016 | B36: 2 | C36: 62 | D36: 21 | E36: Yankees | F36: Y | G36: $950,000 | H36: Nick Solak (minors) | I36: 2B | J36: 0 | K36: 259 | L36: 876 | M36: 21 | N36: 0.25 | O36: 0.694 | V36: 4Yr | W36: University of Louisville (Louisville, KY)
A37: 2016 | B37: 2 | C37: 64 | D37: 23 | E37: Mets | F37: Y | G37: $909,200 | H37: Pete Alonso (minors) | I37: 1B | J37: 23.3 | K37: 1019 | L37: 3806 | M37: 265 | N37: 0.252 | O37: 0.853 | V37: 4Yr | W37: University of Florida (Gainesville, FL)
A38: 2016 | B38: 2 | C38: 65 | D38: 24 | E38: Dodgers | F38: Y | G38: $588,300 | H38: Mitch White (minors) | I38: RHP | J38: -2 | K38: 21 | L38: 15 | M38: 0 | N38: 0 | O38: 0.063 | P38: 71 | Q38: 4 | R38: 12 | S38: 5.25 | T38: 1.42 | U38: 0 | V38: 4Yr | W38: Santa Clara University (Santa Clara, CA)
A39: 2016 | B39: 2 | C39: 67 | D39: 26 | E39: Royals | F39: Y | G39: $1,200,000 | H39: A.J. Puckett (minors) | I39: RHP | V39: 4Yr | W39: Pepperdine University (Malibu, CA)
A40: 2016 | B40: 2 | C40: 70 | D40: 29 | E40: Cardinals | F40: Y | G40: $1,100,000 | H40: Connor Jones (minors) | I40: RHP | V40: 4Yr | W40: University of Virginia (Charlottesville, VA)
A41: 2016 | B41: 2 | C41: 72 | D41: 31 | E41: Indians | F41: Y | G41: $850,000 | H41: Logan Ice (minors) | I41: C | V41: 4Yr | W41: Oregon State University (Corvallis, OR)
A42: 2016 | B42: 2 | C42: 76 | D42: 35 | E42: Braves | F42: Y | G42: $1,500,000 | H42: Brett Cumberland (minors) | I42: C | V42: 4Yr | W42: University of California, Berkeley (Berkeley, CA)
A43: 2016 | B43: 2 | C43: 77 | D43: 36 | E43: Rays | F43: Y | G43: $797,500 | H43: Jake Fraley (minors) | I43: OF | J43: 2.6 | K43: 477 | L43: 1398 | M43: 47 | N43: 0.247 | O43: 0.732 | V43: 4Yr | W43: Louisiana State University (Baton Rouge, LA)
A44: 2016 | B44: 3 | C44: 80 | D44: 3 | E44: Braves | F44: Y | G44: $900,000 | H44: Drew Harrington (minors) | I44: LHP | V44: 4Yr | W44: University of Louisville (Louisville, KY)
A45: 2016 | B45: 3 | C45: 81 | D45: 4 | E45: Rockies | F45: Y | G45: $750,000 | H45: Garrett Hampson (minors) | I45: SS | J45: 1.5 | K45: 692 | L45: 1669 | M45: 29 | N45: 0.235 | O45: 0.651 | P45: 2 | Q45: 0 | R45: 0 | S45: 0 | T45: 0 | U45: 0 | V45: 4Yr | W45: California State University, Long Beach (Long Beach, CA)
A46: 2016 | B46: 3 | C46: 82 | D46: 5 | E46: Brewers | F46: Y | G46: $700,000 | H46: Braden Webb (minors) | I46: RHP | V46: 4Yr | W46: University of South Carolina (Columbia, SC)
A47: 2016 | B47: 3 | C47: 83 | D47: 6 | E47: Athletics | F47: Y | G47: $753,100 | H47: Sean Murphy (minors) | I47: C | J47: 15.8 | K47: 604 | L47: 1993 | M47: 93 | N47: 0.228 | O47: 0.751 | V47: 4Yr | W47: Wright State University (Dayton, OH)
A48: 2016 | B48: 3 | C48: 86 | D48: 9 | E48: White Sox | F48: Y | G48: $719,100 | H48: Alex Call (minors) | I48: OF | J48: 4.7 | K48: 319 | L48: 867 | M48: 21 | N48: 0.245 | O48: 0.718 | V48: 4Yr | W48: Ball State University (Muncie, IN)
A49: 2016 | B49: 3 | C49: 87 | D49: 10 | E49: Mariners | F49: Y | G49: $700,000 | H49: Bryson Brigman (minors) | I49: SS | V49: 4Yr | W49: University of San Diego (San Diego, CA)
A50: 2016 | B50: 3 | C50: 88 | D50: 11 | E50: Red Sox | F50: Y | G50: $700,000 | H50: Shaun Anderson (minors) | I50: RHP | J50: -2.2 | K50: 29 | L50: 25 | M50: 0 | N50: 0.08 | O50: 0.235 | P50: 79 | Q50: 5 | R50: 7 | S50: 6.3 | T50: 1.7 | U50: 2 | V50: 4Yr | W50: University of Florida (Gainesville, FL)
A51: 2016 | B51: 3 | C51: 89 | D51: 12 | E51: Diamondbacks | F51: Y | G51: $686,600 | H51: Jon Duplantier (minors) | I51: RHP | J51: -0.5 | K51: 18 | L51: 10 | M51: 0 | N51: 0.1 | O51: 0.282 | P51: 19 | Q51: 1 | R51: 4 | S51: 6.7 | T51: 1.69 | U51: 1 | V51: 4Yr | W51: Rice University (Houston, TX)
A52: 2016 | B52: 3 | C52: 91 | D52: 14 | E52: Orioles | F52: Y | G52: $665,800 | H52: Austin Hays (minors) | I52: RF | J52: 10.2 | K52: 691 | L52: 2440 | M52: 84 | N52: 0.261 | O52: 0.746 | V52: 4Yr | W52: Jacksonville University (Jacksonville, FL)
A53: 2016 | B53: 3 | C53: 92 | D53: 15 | E53: Indians | F53: Y | G53: $625,000 | H53: Aaron Civale (minors) | I53: RHP | J53: 7.2 | K53: 2 | L53: 3 | M53: 0 | N53: 0 | O53: 0.25 | P53: 142 | Q53: 44 | R53: 44 | S53: 4.13 | T53: 1.21 | U53: 1 | V53: 4Yr | W53: Northeastern University (Boston, MA)
A54: 2016 | B54: 3 | C54: 93 | D54: 16 | E54: Twins | F54: Y | G54: $645,600 | H54: Griffin Jax (minors) | I54: RHP | J54: 3 | K54: 3 | L54: 3 | M54: 0 | N54: 0 | O54: 0 | P54: 304 | Q54: 23 | R54: 33 | S54: 4.12 | T54: 1.17 | U54: 15 | V54: 4Yr | W54: United States Air Force Academy (Colorado Springs, CO)
A55: 2016 | B55: 3 | C55: 95 | D55: 18 | E55: Giants | F55: Y | G55: $625,900 | H55: Heath Quinn (minors) | I55: OF | V55: 4Yr | W55: Samford University (Homewood, AL)
A56: 2016 | B56: 3 | C56: 97 | D56: 20 | E56: Astros | F56: Y | G56: $614,000 | H56: Jake Rogers (minors) | I56: C | J56: 2.4 | K56: 331 | L56: 999 | M56: 44 | N56: 0.199 | O56: 0.653 | P56: 5 | Q56: 0 | R56: 0 | S56: 5.79 | T56: 1.71 | U56: 0 | V56: 4Yr | W56: Tulane University (New Orleans, LA)
A57: 2016 | B57: 3 | C57: 100 | D57: 23 | E57: Mets | F57: Y | G57: $500,000 | H57: Blake Tiberi (minors) | I57: 3B | V57: 4Yr | W57: University of Louisville (Louisville, KY)
A58: 2016 | B58: 3 | C58: 102 | D58: 25 | E58: Blue Jays | F58: Y | G58: $275,000 | H58: Zach Jackson (minors) | I58: RHP | J58: 1.6 | K58: 0 | L58: 0 | M58: 0 | P58: 73 | Q58: 4 | R58: 4 | S58: 2.86 | T58: 1.35 | U58: 4 | V58: 4Yr | W58: University of Arkansas (Fayetteville, AR)
A59: 2016 | B59: 3 | C59: 104 | D59: 27 | E59: Cubs | F59: Y | G59: $573,900 | H59: Thomas Hatch (minors) | I59: RHP | J59: 0.1 | K59: 0 | L59: 0 | M59: 0 | P59: 51 | Q59: 6 | R59: 5 | S59: 5.24 | T59: 1.59 | U59: 0 | V59: 4Yr | W59: Oklahoma State University (Stillwater, OK)
A60: 2016 | B60: 3 | C60: 105 | D60: 28 | E60: Pirates | F60: Y | G60: $500,000 | H60: Stephen Alemais (minors) | I60: SS | V60: 4Yr | W60: Tulane University (New Orleans, LA)
A61: 2016 | B61: 3 | C61: 106 | D61: 29 | E61: Cardinals | F61: Y | G61: $563,100 | H61: Zac Gallen (minors) | I61: RHP | J61: 20.9 | K61: 36 | L61: 51 | M61: 0 | N61: 0.157 | O61: 0.369 | P61: 179 | Q61: 67 | R61: 53 | S61: 3.57 | T61: 1.16 | U61: 0 | V61: 4Yr | W61: University of North Carolina at Chapel Hill (Chapel Hill, NC)
A62: 2016 | B62: 4 | C62: 108 | D62: 2 | E62: Reds | F62: Y | G62: $577,400 | H62: Scott Moss (minors) | I62: LHP | V62: 4Yr | W62: University of Florida (Gainesville, FL)
A63: 2016 | B63: 4 | C63: 111 | D63: 5 | E63: Brewers | F63: Y | G63: $536,400 | H63: Corbin Burnes (minors) | I63: RHP | J63: 19.6 | K63: 86 | L63: 59 | M63: 0 | N63: 0.169 | O63: 0.379 | P63: 210 | Q63: 63 | R63: 38 | S63: 3.15 | T63: 1.07 | U63: 2 | V63: 4Yr | W63: Saint Mary's College of California (Moraga, CA)
A64: 2016 | B64: 4 | C64: 114 | D64: 8 | E64: Padres | F64: Y | G64: $100,000 | H64: Joey Lucchesi (minors) | I64: LHP | J64: 4.2 | K64: 62 | L64: 92 | M64: 0 | N64: 0.054 | O64: 0.165 | P64: 122 | Q64: 23 | R64: 27 | S64: 4.09 | T64: 1.29 | U64: 0 | V64: 4Yr | W64: Southeast Missouri State University (Cape Girardeau, MO)
A65: 2016 | B65: 4 | C65: 115 | D65: 9 | E65: Tigers | F65: Y | G65: $750,000 | H65: Kyle Funkhouser (minors) | I65: RHP | J65: 0.7 | K65: 4 | L65: 0 | M65: 0 | P65: 70 | Q65: 8 | R65: 5 | S65: 4.2 | T65: 1.51 | U65: 1 | V65: 4Yr | W65: University of Louisville (Louisville, KY)
A66: 2016 | B66: 4 | C66: 116 | D66: 10 | E66: White Sox | F66: Y | G66: $485,000 | H66: Jameson Fisher (minors) | I66: OF | V66: 4Yr | W66: Southeastern Louisiana University (Hammond, LA)
A67: 2016 | B67: 4 | C67: 117 | D67: 11 | E67: Mariners | F67: Y | G67: $450,000 | H67: Thomas Burrows (minors) | I67: LHP | V67: 4Yr | W67: University of Alabama (Tuscaloosa, AL)
A68: 2016 | B68: 4 | C68: 118 | D68: 12 | E68: Red Sox | F68: Y | G68: $650,000 | H68: Bobby Dalbec (minors) | I68: 3B | J68: -0.7 | K68: 338 | L68: 964 | M68: 47 | N68: 0.222 | O68: 0.713 | V68: 4Yr | W68: University of Arizona (Tucson, AZ)
A69: 2016 | B69: 4 | C69: 119 | D69: 13 | E69: Diamondbacks | F69: Y | G69: $496,700 | H69: Curtis Taylor (minors) | I69: RHP | V69: 4Yr | W69: University of British Columbia (Vancouver, BC)
A70: 2016 | B70: 4 | C70: 122 | D70: 16 | E70: Indians | F70: Y | G70: $420,000 | H70: Shane Bieber (minors) | I70: RHP | J70: 18.5 | K70: 6 | L70: 15 | M70: 0 | N70: 0.067 | O70: 0.258 | P70: 143 | Q70: 66 | R70: 34 | S70: 3.24 | T70: 1.11 | U70: 0 | V70: 4Yr | W70: University of California, Santa Barbara (Santa Barbara, CA)
A71: 2016 | B71: 4 | C71: 123 | D71: 17 | E71: Twins | F71: Y | G71: $225,000 | H71: Tom Hackimer (minors) | I71: RHP | V71: 4Yr | W71: St. John's University (Queens, NY)
A72: 2016 | B72: 4 | C72: 124 | D72: 18 | E72: Nationals | F72: Y | G72: $500,000 | H72: Nick Banks (minors) | I72: OF | V72: 4Yr | W72: Texas A&M University (College Station, TX)
A73: 2016 | B73: 4 | C73: 125 | D73: 19 | E73: Giants | F73: Y | G73: $500,000 | H73: Matt Krook (minors) | I73: LHP | J73: -0.5 | K73: 0 | L73: 0 | M73: 0 | P73: 8 | Q73: 0 | R73: 0 | S73: 16.2 | T73: 2.64 | U73: 0 | V73: 4Yr | W73: University of Oregon (Eugene, OR)
A74: 2016 | B74: 4 | C74: 127 | D74: 21 | E74: Astros | F74: Y | G74: $430,000 | H74: Brett Adcock (minors) | I74: LHP | V74: 4Yr | W74: University of Michigan (Ann Arbor, MI)
A75: 2016 | B75: 4 | C75: 129 | D75: 23 | E75: Rangers | F75: Y | G75: $415,000 | H75: Charles Leblanc (minors) | I75: SS | J75: 0.8 | K75: 59 | L75: 177 | M75: 6 | N75: 0.254 | O75: 0.742 | V75: 4Yr | W75: University of Pittsburgh (Pittsburgh, PA)
A76: 2016 | B76: 4 | C76: 130 | D76: 24 | E76: Mets | F76: Y | G76: $446,500 | H76: Michael Paez (minors) | I76: SS | V76: 4Yr | W76: Coastal Carolina University (Conway, SC)
A77: 2016 | B77: 4 | C77: 132 | D77: 26 | E77: Blue Jays | F77: Y | G77: $438,100 | H77: Joshua Palacios (minors) | I77: CF | J77: -1.7 | K77: 207 | L77: 524 | M77: 15 | N77: 0.223 | O77: 0.637 | V77: 4Yr | W77: Auburn University (Auburn, AL)
A78: 2016 | B78: 4 | C78: 133 | D78: 27 | E78: Royals | F78: Y | G78: $375,000 | H78: Jace Vines (minors) | I78: RHP | V78: 4Yr | W78: Texas A&M University (College Station, TX)
A79: 2016 | B79: 4 | C79: 134 | D79: 28 | E79: Cubs | F79: Y | H79: Tyson Miller (minors) | I79: RHP | J79: 0.7 | K79: 0 | L79: 0 | M79: 0 | P79: 74 | Q79: 7 | R79: 3 | S79: 3.87 | T79: 1.05 | U79: 1 | V79: 4Yr | W79: California Baptist University (Riverside, CA)
A80: 2016 | B80: 4 | C80: 136 | D80: 30 | E80: Cardinals | F80: Y | G80: $600,000 | H80: Jeremy Martinez (minors) | I80: C | V80: 4Yr | W80: University of Southern California (Los Angeles, CA)
A81: 2016 | B81: 5 | C81: 137 | D81: 1 | E81: Phillies | F81: Y | G81: $800,000 | H81: Cole Irvin (minors) | I81: LHP | J81: 2.5 | K81: 16 | L81: 11 | M81: 0 | N81: 0.182 | O81: 0.49 | P81: 134 | Q81: 28 | R81: 40 | S81: 4.54 | T81: 1.31 | U81: 2 | V81: 4Yr | W81: University of Oregon (Eugene, OR)
A82: 2016 | B82: 5 | C82: 138 | D82: 2 | E82: Reds | F82: Y | G82: $410,000 | H82: Ryan Hendrix (minors) | I82: RHP | J82: -0.3 | K82: 34 | L82: 1 | M82: 0 | N82: 0 | O82: 0 | P82: 45 | Q82: 5 | R82: 1 | S82: 5.85 | T82: 1.6 | U82: 0 | V82: 4Yr | W82: Texas A&M University (College Station, TX)
A83: 2016 | B83: 5 | C83: 139 | D83: 3 | E83: Braves | F83: Y | G83: $275,000 | H83: Jeremy Walker (minors) | I83: RHP | J83: 0.2 | K83: 6 | L83: 1 | M83: 0 | N83: 0 | O83: 0 | P83: 6 | Q83: 0 | R83: 0 | S83: 1.93 | T83: 1.39 | U83: 0 | V83: 4Yr | W83: Gardner-Webb University (Boiling Springs, NC)
A84: 2016 | B84: 5 | C84: 140 | D84: 4 | E84: Rockies | F84: Y | G84: $400,000 | H84: Brian Serven (minors) | I84: C | J84: -0.3 | K84: 101 | L84: 273 | M84: 6 | N84: 0.187 | O84: 0.54 | P84: 1 | Q84: 0 | R84: 0 | S84: 0 | T84: 1 | U84: 0 | V84: 4Yr | W84: Arizona State University (Tempe, AZ)
A85: 2016 | B85: 5 | C85: 141 | D85: 5 | E85: Brewers | F85: Y | G85: $401,700 | H85: Zack Brown (minors) | I85: RHP | V85: 4Yr | W85: University of Kentucky (Lexington, KY)
A86: 2016 | B86: 5 | C86: 142 | D86: 6 | E86: Athletics | F86: Y | G86: $275,000 | H86: JaVon Shelby (minors) | I86: 3B | V86: 4Yr | W86: University of Kentucky (Lexington, KY)
A87: 2016 | B87: 5 | C87: 143 | D87: 7 | E87: Marlins | F87: Y | G87: $20,000 | H87: Sam Perez (minors) | I87: RHP | V87: 4Yr | W87: Missouri State University (Springfield, MO)
A88: 2016 | B88: 5 | C88: 144 | D88: 8 | E88: Padres | F88: Y | G88: $350,000 | H88: Lake Bachar (minors) | I88: RHP | J88: 0.7 | K88: 0 | L88: 0 | M88: 0 | P88: 65 | Q88: 8 | R88: 3 | S88: 4.06 | T88: 1.25 | U88: 3 | V88: 4Yr | W88: University of Wisconsin-Whitewater (Whitewater, WI)
A89: 2016 | B89: 5 | C89: 145 | D89: 9 | E89: Tigers | F89: Y | G89: $386,500 | H89: Mark Ecker (minors) | I89: RHP | V89: 4Yr | W89: Texas A&M University (College Station, TX)
A90: 2016 | B90: 5 | C90: 146 | D90: 10 | E90: White Sox | F90: Y | G90: $325,000 | H90: Jimmy Lambert (minors) | I90: RHP | J90: 0.8 | K90: 1 | L90: 0 | M90: 0 | P90: 83 | Q90: 4 | R90: 6 | S90: 4.33 | T90: 1.49 | U90: 1 | V90: 4Yr | W90: California State University, Fresno (Fresno, CA)
A91: 2016 | B91: 5 | C91: 147 | D91: 11 | E91: Mariners | F91: Y | G91: $125,000 | H91: Donovan Walton (minors) | I91: SS | J91: -0.4 | K91: 72 | L91: 198 | M91: 4 | N91: 0.172 | O91: 0.521 | P91: 2 | Q91: 0 | R91: 0 | S91: 13.5 | T91: 3 | U91: 0 | V91: 4Yr | W91: Oklahoma State University (Stillwater, OK)
A92: 2016 | B92: 5 | C92: 148 | D92: 12 | E92: Red Sox | F92: Y | G92: $637,500 | H92: Mike Shawaryn (minors) | I92: RHP | J92: -0.6 | K92: 0 | L92: 0 | M92: 0 | P92: 14 | Q92: 0 | R92: 0 | S92: 9.74 | T92: 1.92 | U92: 0 | V92: 4Yr | W92: University of Maryland (College Park, MD)
A93: 2016 | B93: 5 | C93: 154 | D93: 18 | E93: Nationals | F93: Y | G93: $325,000 | H93: Daniel Johnson (minors) | I93: CF | J93: -0.2 | K93: 67 | L93: 143 | M93: 5 | N93: 0.196 | O93: 0.565 | V93: 4Yr | W93: New Mexico State University (Las Cruces, NM)
A94: 2016 | B94: 5 | C94: 155 | D94: 19 | E94: Giants | F94: Y | G94: $250,000 | H94: Ryan Howard (minors) | I94: SS | V94: 4Yr | W94: University of Missouri (Columbia, MO)
A95: 2016 | B95: 5 | C95: 156 | D95: 20 | E95: Angels | F95: Y | G95: $250,000 | H95: Connor Justus (minors) | I95: SS | V95: 4Yr | W95: Georgia Institute of Technology (Atlanta, GA)
A96: 2016 | B96: 5 | C96: 158 | D96: 22 | E96: Yankees | F96: Y | G96: $250,000 | H96: Dom Thompson-Williams (minors) | I96: CF | V96: 4Yr | W96: University of South Carolina (Columbia, SC)
A97: 2016 | B97: 5 | C97: 160 | D97: 24 | E97: Mets | F97: Y | G97: $334,500 | H97: Colby Woodmansee (minors) | I97: SS | V97: 4Yr | W97: Arizona State University (Tempe, AZ)
A98: 2016 | B98: 5 | C98: 162 | D98: 26 | E98: Blue Jays | F98: Y | G98: $300,000 | H98: Cavan Biggio (minors) | I98: 2B | J98: 6.8 | K98: 561 | L98: 1627 | M98: 52 | N98: 0.223 | O98: 0.712 | V98: 4Yr | W98: University of Notre Dame (South Bend, IN)
A99: 2016 | B99: 5 | C99: 163 | D99: 27 | E99: Royals | F99: Y | G99: $243,300 | H99: Nicky Lopez (minors) | I99: SS | J99: 5.5 | K99: 686 | L99: 2128 | M99: 7 | N99: 0.245 | O99: 0.621 | P99: 4 | Q99: 0 | R99: 0 | S99: 9.82 | T99: 2.73 | U99: 0 | V99: 4Yr | W99: Creighton University (Omaha, NE)
A100: 2016 | B100: 5 | C100: 164 | D100: 28 | E100: Cubs | F100: Y | G100: $450,000 | H100: Bailey Clark (minors) | I100: RHP | V100: 4Yr | W100: Duke University (Durham, NC)
...

Sheet Top_Basketball
A1: School name | B1: State | C1: Conference | D1: Estimated Athlete pool | E1: Pro Players Count | F1: Draft Probability | G1: National Average | H1: Vs_National_Average
A2: Duke | B2: NC | C2: Atlantic Coast Conference | D2: 140 | E2: 30 | F2: 0.21428571 | G2: 0.0086111259 | H2: 0.20567459
A3: Kentucky | B3: KY | C3: Southeastern Conference | D3: 157 | E3: 27 | F3: 0.17197452 | G3: 0.0086111259 | H3: 0.1633634
A4: Gonzaga | B4: WA | C4: West Coast Conference | D4: 140 | E4: 12 | F4: 0.085714286 | G4: 0.0086111259 | H4: 0.07710316
A5: UCLA | B5: CA | C5: Big Ten Conference | D5: 133 | E5: 11 | F5: 0.082706767 | G5: 0.0086111259 | H5: 0.074095641
A6: Kansas | B6: KS | C6: Big 12 Conference | D6: 153 | E6: 12 | F6: 0.078431373 | G6: 0.0086111259 | H6: 0.069820247
A7: Michigan | B7: MI | C7: Big Ten Conference | D7: 157 | E7: 12 | F7: 0.076433121 | G7: 0.0086111259 | H7: 0.067821995
A8: North Carolina | B8: NC | C8: Atlantic Coast Conference | D8: 147 | E8: 11 | F8: 0.074829932 | G8: 0.0086111259 | H8: 0.066218806
A9: UConn | B9: CT | C9: Big East Conference | D9: 137 | E9: 10 | F9: 0.072992701 | G9: 0.0086111259 | H9: 0.064381575
A10: Villanova | B10: PA | C10: Big East Conference | D10: 127 | E10: 9 | F10: 0.070866142 | G10: 0.0086111259 | H10: 0.062255016
A11: Baylor | B11: TX | C11: Big 12 Conference | D11: 133 | E11: 9 | F11: 0.067669173 | G11: 0.0086111259 | H11: 0.059058047
A12: Florida State | B12: FL | C12: Atlantic Coast Conference | D12: 167 | E12: 11 | F12: 0.065868263 | G12: 0.0086111259 | H12: 0.057257138
A13: Arizona | B13: AZ | C13: Big 12 Conference | D13: 167 | E13: 11 | F13: 0.065868263 | G13: 0.0086111259 | H13: 0.057257138
... A362: Youngstown State | B362: OH | C362: Horizon League | D362: 127 | E362: 0 | F362: 0 | G362: 0.0086111259 | H362: -0.0086111259

Sheet pro-probability-by-state
A1: State | B1: SUM of Estimated Athlete pool | C1: SUM of Pro Players Count | D1: Pro_Probability
A2: AL | B2: 6452 | C2: 163 | D2: =C2/B2 -> 0.025263484
A3: AR | B3: 3158 | C3: 37 | D3: =C3/B3 -> 0.011716276
A4: AZ | B4: 2847 | C4: 42 | D4: =C4/B4 -> 0.014752371
A5: CA | B5: 11603 | C5: 194 | D5: =C5/B5 -> 0.016719814
A6: CO | B6: 2936 | C6: 33 | D6: =C6/B6 -> 0.011239782
A7: CT | B7: 1984 | C7: 20 | D7: =C7/B7 -> 0.010080645
A8: DC | B8: 614 | C8: 2 | D8: =C8/B8 -> 0.003257329
A9: DE | B9: 1390 | C9: 2 | D9: =C9/B9 -> 0.0014388489
A10: FL | B10: 10084 | C10: 189 | D10: =C10/B10 -> 0.018742562
A11: GA | B11: 6804 | C11: 101 | D11: =C11/B11 -> 0.014844209
A12: HI | B12: 1300 | C12: 3 | D12: =C12/B12 -> 0.0023076923
A13: IA | B13: 3051 | C13: 62 | D13: =C13/B13 -> 0.020321206
... A51: WY | B51: 1303 | C51: 8 | D51: =C51/B51 -> 0.0061396777

Sheet pro-probability-by-state-per-sp
A1: State | B1: Sport | C1: Total Estimated Athlete pool | D1: Total Pro Players Count | E1: Pro probability
A2: AL | B2: American Football | C2: 4944 | D2: 149 | E2: =D2/C2 -> 0.03013754
A3: AL | B3: Basketball | C3: 1508 | D3: 14 | E3: =D3/C3 -> 0.0092838196
A4: AR | B4: American Football | C4: 2430 | D4: 29 | E4: =D4/C4 -> 0.011934156
A5: AR | B5: Basketball | C5: 728 | D5: 8 | E5: =D5/C5 -> 0.010989011
A6: AZ | B6: American Football | C6: 2253 | D6: 30 | E6: =D6/C6 -> 0.013315579
A7: AZ | B7: Basketball | C7: 594 | D7: 12 | E7: =D7/C7 -> 0.02020202
A8: CA | B8: American Football | C8: 7797 | D8: 158 | E8: =D8/C8 -> 0.020264204
A9: CA | B9: Basketball | C9: 3806 | D9: 36 | E9: =D9/C9 -> 0.0094587493
A10: CO | B10: American Football | C10: 2210 | D10: 24 | E10: =D10/C10 -> 0.010859729
A11: CO | B11: Basketball | C11: 726 | D11: 9 | E11: =D11/C11 -> 0.012396694
A12: CT | B12: American Football | C12: 1117 | D12: 9 | E12: =D12/C12 -> 0.0080572963
A13: CT | B13: Basketball | C13: 867 | D13: 11 | E13: =D13/C13 -> 0.012687428
A14: DC | B14: American Football | C14: 0 | D14: 0 | E14: 0
A15: DC | B15: Basketball | C15: 614 | D15: 2 | E15: =D15/C15 -> 0.003257329
A16: DE | B16: American Football | C16: 1100 | D16: 2 | E16: =D16/C16 -> 0.0018181818
A17: DE | B17: Basketball | C17: 290 | D17: 0 | E17: =D17/C17 -> 0
A18: FL | B18: American Football | C18: 8186 | D18: 165 | E18: =D18/C18 -> 0.020156365
A19: FL | B19: Basketball | C19: 1898 | D19: 24 | E19: =D19/C19 -> 0.012644889
A20: GA | B20: American Football | C20: 5924 | D20: 97 | E20: =D20/C20 -> 0.016374072
A21: GA | B21: Basketball | C21: 880 | D21: 4 | E21: =D21/C21 -> 0.0045454545
A22: HI | B22: American Football | C22: 1167 | D22: 3 | E22: =D22/C22 -> 0.0025706941
A23: HI | B23: Basketball | C23: 133 | D23: 0 | E23: =D23/C23 -> 0
A24: IA | B24: American Football | C24: 2504 | D24: 58 | E24: =D24/C24 -> 0.023162939
A25: IA | B25: Basketball | C25: 547 | D25: 4 | E25: =D25/C25 -> 0.0073126143
A26: ID | B26: American Football | C26: 1120 | D26: 18 | E26: =D26/C26 -> 0.016071429
... A41: MD | B41: Basketball | C41: 1391 | D41: 9 | E41: =D41/C41 -> 0.0064701653
A42: ME | B42: American Football | C42: 0 | D42: 2 | E42: 0
A43: ME | B43: Basketball | C43: 143 | D43: 0 | E43: =D43/C43 -> 0
A44: MI | B44: American Football | C44: 5836 | D44: 119 | E44: =D44/C44 -> 0.020390679
A45: MI | B45: Basketball | C45: 1007 | D45: 22 | E45: =D45/C45 -> 0.021847071
A46: MN | B46: American Football | C46: 1133 | D46: 22 | E46: =D46/C46 -> 0.019417476
A47: MN | B47: Basketball | C47: 287 | D47: 2 | E47: =D47/C47 -> 0.0069686411
A48: MO | B48: American Football | C48: 2167 | D48: 29 | E48: =D48/C48 -> 0.013382557
A49: MO | B49: Basketball | C49: 860 | D49: 1 | E49: =D49/C49 -> 0.0011627907
A50: MS | B50: American Football | C50: 3463 | D50: 78 | E50: =D50/C50 -> 0.022523823
A51: MS | B51: Basketball | C51: 916 | D51: 3 | E51: =D51/C51 -> 0.0032751092
A52: MT | B52: American Football | C52: 0 | D52: 6 | E52: 0
A53: MT | B53: Basketball | C53: 280 | D53: 0 | E53: =D53/C53 -> 0
A54: NC | B54: American Football | C54: 8347 | D54: 99 | E54: =D54/C54 -> 0.011860549
A55: NC | B55: Basketball | C55: 2793 | D55: 44 | E55: =D55/C55 -> 0.01575367
A56: ND | B56: American Football | C56: 0 | D56: 12 | E56: 0
A57: ND | B57: Basketball | C57: 264 | D57: 0 | E57: =D57/C57 -> 0
A58: NE | B58: American Football | C58: 1383 | D58: 17 | E58: =D58/C58 -> 0.012292119
A59: NE | B59: Basketball | C59: 416 | D59: 8 | E59: =D59/C59 -> 0.019230769
A60: NH | B60: American Football | C60: 0 | D60: 1 | E60: 0
A61: NH | B61: Basketball | C61: 277 | D61: 0 | E61: =D61/C61 -> 0
A62: NJ | B62: American Football | C62: 1327 | D62: 14 | E62: =D62/C62 -> 0.010550113
A63: NJ | B63: Basketball | C63: 1185 | D63: 4 | E63: =D63/C63 -> 0.0033755274
A64: NM | B64: American Football | C64: 2273 | D64: 4 | E64: =D64/C64 -> 0.0017597888
A65: NM | B65: Basketball | C65: 270 | D65: 1 | E65: =D65/C65 -> 0.0037037037
A66: NV | B66: American Football | C66: 2190 | D66: 5 | E66: =D66/C66 -> 0.002283105
A67: NV | B67: Basketball | C67: 270 | D67: 5 | E67: =D67/C67 -> 0.018518519
A68: NY | B68: American Football | C68: 2280 | D68: 19 | E68: =D68/C68 -> 0.0083333333
A69: NY | B69: Basketball | C69: 3116 | D69: 5 | E69: =D69/C69 -> 0.0016046213
A70: OH | B70: American Football | C70: 8984 | D70: 134 | E70: =D70/C70 -> 0.014915405
A71: OH | B71: Basketball | C71: 1836 | D71: 14 | E71: =D71/C71 -> 0.0076252723
A72: OK | B72: American Football | C72: 2483 | D72: 73 | E72: =D72/C72 -> 0.029399919
... A77: PA | B77: Basketball | C77: 2031 | D77: 16 | E77: =D77/C77 -> 0.0078778927
A78: RI | B78: American Football | C78: 0 | D78: 1 | E78: 0
A79: RI | B79: Basketball | C79: 597 | D79: 3 | E79: =D79/C79 -> 0.0050251256
A80: SC | B80: American Football | C80: 3624 | D80: 92 | E80: =D80/C80 -> 0.025386313
A81: SC | B81: Basketball | C81: 1711 | D81: 8 | E81: =D81/C81 -> 0.0046756283
A82: SD | B82: American Football | C82: 0 | D82: 8 | E82: 0
A83: SD | B83: Basketball | C83: 267 | D83: 0 | E83: =D83/C83 -> 0
A84: TN | B84: American Football | C84: 4714 | D84: 57 | E84: =D84/C84 -> 0.012091642
A85: TN | B85: Basketball | C85: 1748 | D85: 21 | E85: =D85/C85 -> 0.01201373
A86: TX | B86: American Football | C86: 15332 | D86: 206 | E86: =D86/C86 -> 0.013435951
A87: TX | B87: Basketball | C87: 3573 | D87: 29 | E87: =D87/C87 -> 0.0081164288
A88: UT | B88: American Football | C88: 3473 | D88: 56 | E88: =D88/C88 -> 0.016124388
A89: UT | B89: Basketball | C89: 1017 | D89: 7 | E89: =D89/C89 -> 0.0068829892
A90: VA | B90: American Football | C90: 5834 | D90: 51 | E90: =D90/C90 -> 0.0087418581
A91: VA | B91: Basketball | C91: 2024 | D91: 11 | E91: =D91/C91 -> 0.0054347826
A92: VT | B92: American Football | C92: 0 | D92: 0 | E92: 0
A93: VT | B93: Basketball | C93: 137 | D93: 0 | E93: =D93/C93 -> 0
A94: WA | B94: American Football | C94: 2336 | D94: 57 | E94: =D94/C94 -> 0.024400685
A95: WA | B95: Basketball | C95: 689 | D95: 23 | E95: =D95/C95 -> 0.033381713
A96: WI | B96: American Football | C96: 1180 | D96: 33 | E96: =D96/C96 -> 0.027966102
A97: WI | B97: Basketball | C97: 609 | D97: 8 | E97: =D97/C97 -> 0.013136289
A98: WV | B98: American Football | C98: 2374 | D98: 26 | E98: =D98/C98 -> 0.01095198
A99: WV | B99: Basketball | C99: 280 | D99: 3 | E99: =D99/C99 -> 0.010714286
A100: WY | B100: American Football | C100: 1163 | D100: 7 | E100: =D100/C100 -> 0.0060189166
A101: WY | B101: Basketball | C101: 140 | D101: 1 | E101: =D101/C101 -> 0.0071428571

Sheet national average football
A1: State | B1: Sport | C1: SUM of Estimated Athlete pool | D1: SUM of Pro Players Count | E1: Pro probability | F1: National average
A2: AL | B2: American Football | C2: 4944 | D2: 149 | E2: =D2/C2 -> 0.03013754 | F2: 0.013414865
A3: AR | B3: American Football | C3: 2430 | D3: 29 | E3: =D3/C3 -> 0.011934156 | F3: 0.013414865
A4: AZ | B4: American Football | C4: 2253 | D4: 30 | E4: =D4/C4 -> 0.013315579 | F4: 0.013414865
A5: CA | B5: American Football | C5: 7797 | D5: 158 | E5: =D5/C5 -> 0.020264204 | F5: 0.013414865
A6: CO | B6: American Football | C6: 2210 | D6: 24 | E6: =D6/C6 -> 0.010859729 | F6: 0.013414865
A7: CT | B7: American Football | C7: 1117 | D7: 9 | E7: =D7/C7 -> 0.0080572963 | F7: 0.013414865
A8: DC | B8: American Football | C8: 0 | D8: 0 | E8: 0 | F8: 0.013414865
A9: DE | B9: American Football | C9: 1100 | D9: 2 | E9: =D9/C9 -> 0.0018181818 | F9: 0.013414865
A10: FL | B10: American Football | C10: 8186 | D10: 165 | E10: =D10/C10 -> 0.020156365 | F10: 0.013414865
A11: GA | B11: American Football | C11: 5924 | D11: 97 | E11: =D11/C11 -> 0.016374072 | F11: 0.013414865
A12: HI | B12: American Football | C12: 1167 | D12: 3 | E12: =D12/C12 -> 0.0025706941 | F12: 0.013414865
A13: IA | B13: American Football | C13: 2504 | D13: 58 | E13: =D13/C13 -> 0.023162939 | F13: 0.013414865
A14: ID | B14: American Football | C14: 1120 | D14: 18 | E14: =D14/C14 -> 0.016071429 | F14: 0.013414865
A15: IL | B15: American Football | C15: 3421 | D15: 40 | E15: =D15/C15 -> 0.011692488 | F15: 0.013414865
A16: IN | B16: American Football | C16: 4633 | D16: 84 | E16: =D16/C16 -> 0.018130801 | F16: 0.013414865
A17: KS | B17: American Football | C17: 2367 | D17: 26 | E17: =D17/C17 -> 0.010984368 | F17: 0.013414865
A18: KY | B18: American Football | C18: 3387 | D18: 62 | E18: =D18/C18 -> 0.018305285 | F18: 0.013414865
A19: LA | B19: American Football | C19: 3513 | D19: 113 | E19: =D19/C19 -> 0.03216624 | F19: 0.013414865
A20: MA | B20: American Football | C20: 2290 | D20: 27 | E20: =D20/C20 -> 0.011790393 | F20: 0.013414865
A21: MD | B21: American Football | C21: 1137 | D21: 31 | E21: =D21/C21 -> 0.027264732 | F21: 0.013414865
A22: ME | B22: American Football | C22: 0 | D22: 2 | E22: 0 | F22: 0.013414865
A23: MI | B23: American Football | C23: 5836 | D23: 119 | E23: =D23/C23 -> 0.020390679 | F23: 0.013414865
A24: MN | B24: American Football | C24: 1133 | D24: 22 | E24: =D24/C24 -> 0.019417476 | F24: 0.013414865
A25: MO | B25: American Football | C25: 2167 | D25: 29 | E25: =D25/C25 -> 0.013382557 | F25: 0.013414865
A26: MS | B26: American Football | C26: 3463 | D26: 78 | E26: =D26/C26 -> 0.022523823 | F26: 0.013414865
A27: MT | B27: American Football | C27: 0 | D27: 6 | E27: 0 | F27: 0.013414865
A28: NC | B28: American Football | C28: 8347 | D28: 99 | E28: =D28/C28 -> 0.011860549 | F28: 0.013414865
A29: ND | B29: American Football | C29: 0 | D29: 12 | E29: 0 | F29: 0.013414865
A30: NE | B30: American Football | C30: 1383 | D30: 17 | E30: =D30/C30 -> 0.012292119 | F30: 0.013414865
A31: NH | B31: American Football | C31: 0 | D31: 1 | E31: 0 | F31: 0.013414865
A32: NJ | B32: American Football | C32: 1327 | D32: 14 | E32: =D32/C32 -> 0.010550113 | F32: 0.013414865
A33: NM | B33: American Football | C33: 2273 | D33: 4 | E33: =D33/C33 -> 0.0017597888 | F33: 0.013414865
A34: NV | B34: American Football | C34: 2190 | D34: 5 | E34: =D34/C34 -> 0.002283105 | F34: 0.013414865
A35: NY | B35: American Football | C35: 2280 | D35: 19 | E35: =D35/C35 -> 0.0083333333 | F35: 0.013414865
A36: OH | B36: American Football | C36: 8984 | D36: 134 | E36: =D36/C36 -> 0.014915405 | F36: 0.013414865
A37: OK | B37: American Football | C37: 2483 | D37: 73 | E37: =D37/C37 -> 0.029399919 | F37: 0.013414865
A38: OR | B38: American Football | C38: 2393 | D38: 56 | E38: =D38/C38 -> 0.023401588 | F38: 0.013414865
A39: PA | B39: American Football | C39: 3593 | D39: 108 | E39: =D39/C39 -> 0.030058447 | F39: 0.013414865
A40: RI | B40: American Football | C40: 0 | D40: 1 | E40: 0 | F40: 0.013414865
A41: SC | B41: American Football | C41: 3624 | D41: 92 | E41: =D41/C41 -> 0.025386313 | F41: 0.013414865
A42: SD | B42: American Football | C42: 0 | D42: 8 | E42: 0 | F42: 0.013414865
A43: TN | B43: American Football | C43: 4714 | D43: 57 | E43: =D43/C43 -> 0.012091642 | F43: 0.013414865
A44: TX | B44: American Football | C44: 15332 | D44: 206 | E44: =D44/C44 -> 0.013435951 | F44: 0.013414865
A45: UT | B45: American Football | C45: 3473 | D45: 56 | E45: =D45/C45 -> 0.016124388 | F45: 0.013414865
A46: VA | B46: American Football | C46: 5834 | D46: 51 | E46: =D46/C46 -> 0.0087418581 | F46: 0.013414865
A47: VT | B47: American Football | C47: 0 | D47: 0 | E47: 0 | F47: 0.013414865
A48: WA | B48: American Football | C48: 2336 | D48: 57 | E48: =D48/C48 -> 0.024400685 | F48: 0.013414865
A49: WI | B49: American Football | C49: 1180 | D49: 33 | E49: =D49/C49 -> 0.027966102 | F49: 0.013414865
A50: WV | B50: American Football | C50: 2374 | D50: 26 | E50: =D50/C50 -> 0.01095198 | F50: 0.013414865
A51: WY | B51: American Football | C51: 1163 | D51: 7 | E51: =D51/C51 -> 0.0060189166 | F51: 0.013414865

Sheet national average basketball
A1: State | B1: Sport | C1: SUM of Estimated Athlete pool | D1: SUM of Pro Players Count | E1: Pro probability | F1: National Average
A2: AL | B2: Basketball | C2: 1508 | D2: 14 | E2: 0.0092838196 | F2: 0.0086111259
A3: AR | B3: Basketball | C3: 728 | D3: 8 | E3: 0.010989011 | F3: 0.0086111259
A4: AZ | B4: Basketball | C4: 594 | D4: 12 | E4: 0.02020202 | F4: 0.0086111259
A5: CA | B5: Basketball | C5: 3806 | D5: 36 | E5: 0.0094587493 | F5: 0.0086111259
A6: CO | B6: Basketball | C6: 726 | D6: 9 | E6: 0.012396694 | F6: 0.0086111259
A7: CT | B7: Basketball | C7: 867 | D7: 11 | E7: 0.012687428 | F7: 0.0086111259
A8: DC | B8: Basketball | C8: 614 | D8: 2 | E8: 0.003257329 | F8: 0.0086111259
A9: DE | B9: Basketball | C9: 290 | D9: 0 | E9: 0 | F9: 0.0086111259
A10: FL | B10: Basketball | C10: 1898 | D10: 24 | E10: 0.012644889 | F10: 0.0086111259
A11: GA | B11: Basketball | C11: 880 | D11: 4 | E11: 0.0045454545 | F11: 0.0086111259
A12: HI | B12: Basketball | C12: 133 | D12: 0 | E12: 0 | F12: 0.0086111259
A13: IA | B13: Basketball | C13: 547 | D13: 4 | E13: 0.0073126143 | F13: 0.0086111259
... A51: WY | B51: Basketball | C51: 140 | D51: 1 | E51: 0.0071428571 | F51: 0.0086111259

Sheet basketball_rosters
A1: Source URL | B1: University | C1: School name | D1: Nickname | E1: City | F1: State | G1: Type | H1: Division | I1: Conference | J1: Roster count 2026 | K1: Roster count 2025 | L1: Roster count 2024 | M1: Avg Roster Count Last 3 years | N1: Sport
A2: https://www.sports-reference.com/cbb/schools/abilene-christian/men/ | B2: Abilene Christian University | C2: Abilene Christian | D2: Wildcats | E2: Abilene | F2: TX | G2: Private | H2: FCS | I2: Western Athletic Conference | J2: 13 | K2: 14 | L2: 14 | M2: 13.7 | N2: Basketball
A3: https://www.sports-reference.com/cbb/schools/alabama-am/men/ | B3: Alabama Agricultural and Mechanical University | C3: Alabama A&M | D3: Bulldogs | E3: Normal | F3: AL | G3: Public | H3: FCS | I3: Southwestern Athletic Conference | J3: 16 | K3: 20 | L3: 17 | M3: 17.7 | N3: Basketball
A4: https://www.sports-reference.com/cbb/schools/alabama-state/men/ | B4: Alabama State University | C4: Alabama State | D4: Hornets | E4: Montgomery | F4: AL | G4: Public | H4: FCS | I4: Southwestern Athletic Conference | J4: 16 | K4: 13 | L4: 15 | M4: 14.7 | N4: Basketball
A5: https://www.sports-reference.com/cbb/schools/alcorn-state/men/ | B5: Alcorn State University | C5: Alcorn State | D5: Braves | E5: Lorman | F5: MS | G5: Public | H5: FCS | I5: Southwestern Athletic Conference | J5: 12 | K5: 17 | L5: 16 | M5: 15 | N5: Basketball
A6: https://www.sports-reference.com/cbb/schools/american/men/ | B6: American University | C6: American | D6: Eagles | E6: Washington | F6: DC | G6: Private | H6: Non-football | I6: Patriot League | J6: 19 | K6: 15 | L6: 16 | M6: 16.7 | N6: Basketball
A7: https://www.sports-reference.com/cbb/schools/appalachian-state/men/ | B7: Appalachian State University | C7: Appalachian State | D7: Mountaineers | E7: Boone | F7: NC | G7: Public | H7: FBS | I7: Sun Belt Conference | J7: 16 | K7: 16 | L7: 13 | M7: 15 | N7: Basketball
A8: https://www.sports-reference.com/cbb/schools/arizona-state/men/ | B8: Arizona State University | C8: Arizona State | D8: Sun Devils | E8: Tempe | F8: AZ | G8: Public | H8: FBS | I8: Big 12 Conference | J8: 16 | K8: 15 | L8: 16 | M8: 15.7 | N8: Basketball
A9: https://www.sports-reference.com/cbb/schools/arkansas-state/men/ | B9: Arkansas State University | C9: Arkansas State | D9: Red Wolves | E9: Jonesboro | F9: AR | G9: Public | H9: FBS | I9: Sun Belt Conference | J9: 16 | K9: 15 | L9: 13 | M9: 14.7 | N9: Basketball
A10: https://www.sports-reference.com/cbb/schools/auburn/men/ | B10: Auburn University | C10: Auburn | D10: Tigers | E10: Auburn | F10: AL | G10: Public | H10: FBS | I10: Southeastern Conference | J10: 18 | K10: 15 | L10: 17 | M10: 16.7 | N10: Basketball
A11: https://www.sports-reference.com/cbb/schools/austin-peay/men/ | B11: Austin Peay State University | C11: Austin Peay | D11: Governors | E11: Clarksville | F11: TN | G11: Public | H11: FCS | I11: Atlantic Sun Conference | J11: 13 | K11: 15 | L11: 13 | M11: 13.7 | N11: Basketball
A12: https://www.sports-reference.com/cbb/schools/ball-state/men/ | B12: Ball State University | C12: Ball State | D12: Cardinals | E12: Muncie | F12: IN | G12: Public | H12: FBS | I12: Mid-American Conference | J12: 14 | K12: 13 | L12: 13 | M12: 13.3 | N12: Basketball
A13: https://www.sports-reference.com/cbb/schools/baylor/men/ | B13: Baylor University | C13: Baylor | D13: Bears | E13: Waco | F13: TX | G13: Private | H13: FBS | I13: Big 12 Conference | J13: 16 | K13: 12 | L13: 12 | M13: 13.3 | N13: Basketball
... A362: https://www.sports-reference.com/cbb/schools/youngstown-state/men/ | B362: Youngstown State University | C362: Youngstown State | D362: Penguins | E362: Youngstown | F362: OH | G362: Public | H362: FCS | I362: Horizon League | J362: 15 | K362: 12 | L362: 11 | M362: 12.7 | N362: Basketball

Sheet programs-raw
A1: University URL wiki | B1: Source URL | C1: University | D1: School name | E1: Nickname | F1: City | G1: State | H1: Type | I1: Division | J1: Conference | K1: Roster count 2026 | L1: Roster count 2025 | M1: Roster count 2024 | N1: Avg Roster Count Last 3 years | O1: Sport | P1: Num of seasons | Q1: Estimated Athlete pool
A2: https://en.wikipedia.org/wiki/Appalachian_State_University | B2: https://www.sports-reference.com/cfb/schools/appalachian-state/ | C2: Appalachian State University | D2: Appalachian State | E2: Mountaineers | F2: Boone | G2: NC | H2: Public | I2: FBS | J2: Sun Belt Conference | L2: 120 | M2: 114 | N2: 117 | O2: American Football | P2: 10 | Q2: =P2*N2 -> 1170
A3: https://en.wikipedia.org/wiki/Arizona_State_University | B3: https://www.sports-reference.com/cfb/schools/arizona-state/ | C3: Arizona State University | D3: Arizona State | E3: Sun Devils | F3: Tempe | G3: AZ | H3: Public | I3: FBS | J3: Big 12 Conference | K3: 107 | L3: 119 | M3: 116 | N3: 114 | O3: American Football | P3: 10 | Q3: =P3*N3 -> 1140
A4: https://en.wikipedia.org/wiki/Arkansas_State_University | B4: https://www.sports-reference.com/cfb/schools/arkansas-state/ | C4: Arkansas State University | D4: Arkansas State | E4: Red Wolves | F4: Jonesboro | G4: AR | H4: Public | I4: FBS | J4: Sun Belt Conference | K4: 122 | L4: 130 | M4: 121 | N4: 124.3 | O4: American Football | P4: 10 | Q4: =P4*N4 -> 1243
A5: https://en.wikipedia.org/wiki/Auburn_University | B5: https://www.sports-reference.com/cfb/schools/auburn/ | C5: Auburn University | D5: Auburn | E5: Tigers | F5: Auburn | G5: AL | H5: Public | I5: FBS | J5: Southeastern Conference | K5: 114 | L5: 121 | M5: 119 | N5: 118 | O5: American Football | P5: 10 | Q5: =P5*N5 -> 1180
A6: https://en.wikipedia.org/wiki/Ball_State_University | B6: https://www.sports-reference.com/cfb/schools/ball-state/ | C6: Ball State University | D6: Ball State | E6: Cardinals | F6: Muncie | G6: IN | H6: Public | I6: FBS | J6: Mid-American Conference | K6: 106 | L6: 119 | M6: 118 | N6: 114.3 | O6: American Football | P6: 10 | Q6: =P6*N6 -> 1143
A7: https://en.wikipedia.org/wiki/Baylor_University | B7: https://www.sports-reference.com/cfb/schools/baylor/ | C7: Baylor University | D7: Baylor | E7: Bears | F7: Waco | G7: TX | H7: Private | I7: FBS | J7: Big 12 Conference | K7: 115 | L7: 113 | M7: 109 | N7: 112.3 | O7: American Football | P7: 10 | Q7: =P7*N7 -> 1123
A8: https://en.wikipedia.org/wiki/Boise_State_University | B8: https://www.sports-reference.com/cfb/schools/boise-state/ | C8: Boise State University | D8: Boise State | E8: Broncos | F8: Boise | G8: ID | H8: Public | I8: FBS | J8: Mountain West Conference | K8: 108 | L8: 115 | M8: 113 | N8: 112 | O8: American Football | P8: 10 | Q8: =P8*N8 -> 1120
A9: https://en.wikipedia.org/wiki/Boston_College | B9: https://www.sports-reference.com/cfb/schools/boston-college/ | C9: Boston College | D9: Boston College | E9: Eagles | F9: Chestnut Hill | G9: MA | H9: Private | I9: FBS | J9: Atlantic Coast Conference | K9: 127 | L9: 117 | M9: 117 | N9: 120.3 | O9: American Football | P9: 10 | Q9: =P9*N9 -> 1203
A10: https://en.wikipedia.org/wiki/Bowling_Green_State_University | B10: https://www.sports-reference.com/cfb/schools/bowling-green-state/ | C10: Bowling Green State University | D10: Bowling Green | E10: Falcons | F10: Bowling Green | G10: OH | H10: Public | I10: FBS | J10: Mid-American Conference | K10: 107 | L10: 109 | M10: 107 | N10: 107.7 | O10: American Football | P10: 10 | Q10: =P10*N10 -> 1077
A11: https://en.wikipedia.org/wiki/Brigham_Young_University | B11: https://www.sports-reference.com/cfb/schools/brigham-young/ | C11: Brigham Young University | D11: BYU | E11: Cougars | F11: Provo | G11: UT | H11: Private | I11: FBS | J11: Big 12 Conference | K11: 115 | L11: 121 | M11: 119 | N11: 118.3 | O11: American Football | P11: 10 | Q11: =P11*N11 -> 1183
A12: https://en.wikipedia.org/wiki/California_State_University,_Fresno | B12: https://www.sports-reference.com/cfb/schools/fresno-state/ | C12: California State University, Fresno | D12: Fresno State | E12: Bulldogs | F12: Fresno | G12: CA | H12: Public | I12: FBS | J12: Mountain West Conference | K12: 113 | L12: 115 | M12: 112 | N12: 113.3 | O12: American Football | P12: 10 | Q12: =P12*N12 -> 1133
A13: https://en.wikipedia.org/wiki/Central_Michigan_University | B13: https://www.sports-reference.com/cfb/schools/central-michigan/ | C13: Central Michigan University | D13: Central Michigan | E13: Chippewas | F13: Mount Pleasant | G13: MI | H13: Public | I13: FBS | J13: Mid-American Conference | K13: 104 | L13: 120 | M13: 115 | N13: 113 | O13: American Football | P13: 10 | Q13: =P13*N13 -> 1130
A14: https://en.wikipedia.org/wiki/Clemson_University | B14: https://www.sports-reference.com/cfb/schools/clemson/ | C14: Clemson University | D14: Clemson | E14: Tigers | F14: Clemson | G14: SC | H14: Public | I14: FBS | J14: Atlantic Coast Conference | K14: 126 | L14: 136 | M14: 136 | N14: 132.7 | O14: American Football | P14: 10 | Q14: =P14*N14 -> 1327
... A30: https://en.wikipedia.org/wiki/Kansas_State_University | B30: https://www.sports-reference.com/cfb/schools/kansas-state/ | C30: Kansas State University | D30: Kansas State | E30: Wildcats | F30: Manhattan | G30: KS | H30: Public | I30: FBS | J30: Big 12 Conference | K30: 110 | L30: 126 | M30: 124 | N30: 120 | O30: American Football | P30: 10 | Q30: =P30*N30 -> 1200
A31: https://en.wikipedia.org/wiki/Kennesaw_State_University | B31: https://www.sports-reference.com/cfb/schools/kennesaw-state/ | C31: Kennesaw State University | D31: Kennesaw State | E31: Owls | F31: Kennesaw | G31: GA | H31: Public | I31: FBS | J31: Conference USA | K31: 101 | L31: 120 | N31: 110.5 | O31: American Football | P31: 10 | Q31: =P31*N31 -> 1105
A32: https://en.wikipedia.org/wiki/Kent_State_University | B32: https://www.sports-reference.com/cfb/schools/kent-state/ | C32: Kent State University | D32: Kent State | E32: Golden Flashes | F32: Kent | G32: OH | H32: Public | I32: FBS | J32: Mid-American Conference | K32: 103 | L32: 107 | M32: 99 | N32: 103 | O32: American Football | P32: 10 | Q32: =P32*N32 -> 1030
A33: https://en.wikipedia.org/wiki/Stanford_University | B33: https://www.sports-reference.com/cfb/schools/stanford/ | C33: Leland Stanford Junior University | D33: Stanford | E33: Cardinal | F33: Stanford | G33: CA | H33: Private | I33: FBS | J33: Atlantic Coast Conference | K33: 109 | L33: 108 | M33: 106 | N33: 107.7 | O33: American Football | P33: 10 | Q33: =P33*N33 -> 1077
A34: https://en.wikipedia.org/wiki/Liberty_University | B34: https://www.sports-reference.com/cfb/schools/liberty/ | C34: Liberty University | D34: Liberty | E34: Flames | F34: Lynchburg | G34: VA | H34: Private | I34: FBS | J34: Conference USA | K34: 105 | L34: 118 | M34: 116 | N34: 113 | O34: American Football | P34: 10 | Q34: =P34*N34 -> 1130
A35: https://en.wikipedia.org/wiki/Louisiana_Tech_University | B35: https://www.sports-reference.com/cfb/schools/louisiana-tech/ | C35: Louisiana Tech University | D35: Louisiana Tech | E35: Bulldogs | F35: Ruston | G35: LA | H35: Public | I35: FBS | J35: Conference USA | K35: 107 | L35: 119 | M35: 115 | N35: 113.7 | O35: American Football | P35: 10 | Q35: =P35*N35 -> 1137
A36: https://en.wikipedia.org/wiki/Marshall_University | B36: https://www.sports-reference.com/cfb/schools/marshall/ | C36: Marshall University | D36: Marshall | E36: Thundering Herd | F36: Huntington | G36: WV | H36: Public | I36: FBS | J36: Sun Belt Conference | K36: 106 | L36: 115 | M36: 126 | N36: 115.7 | O36: American Football | P36: 10 | Q36: =P36*N36 -> 1157
A37: https://en.wikipedia.org/wiki/Miami_University | B37: https://www.sports-reference.com/cfb/schools/miami-oh/ | C37: Miami University | D37: Miami (Ohio) | E37: RedHawks | F37: Oxford | G37: OH | H37: Public | I37: FBS | J37: Mid-American Conference | K37: 109 | L37: 116 | M37: 118 | N37: 114.3 | O37: American Football | P37: 10 | Q37: =P37*N37 -> 1143
A38: https://en.wikipedia.org/wiki/Michigan_State_University | B38: https://www.sports-reference.com/cfb/schools/michigan-state/ | C38: Michigan State University | D38: Michigan State | E38: Spartans | F38: East Lansing | G38: MI | H38: Public | I38: FBS | J38: Big Ten Conference | K38: 117 | L38: 115 | M38: 115 | N38: 115.7 | O38: American Football | P38: 10 | Q38: =P38*N38 -> 1157
A39: https://en.wikipedia.org/wiki/Middle_Tennessee_State_University | B39: https://www.sports-reference.com/cfb/schools/middle-tennessee-state/ | C39: Middle Tennessee State University | D39: Middle Tennessee | E39: Blue Raiders | F39: Murfreesboro | G39: TN | H39: Public | I39: FBS | J39: Conference USA | K39: 110 | L39: 113 | M39: 112 | N39: 111.7 | O39: American Football | P39: 10 | Q39: =P39*N39 -> 1117
A40: https://en.wikipedia.org/wiki/Mississippi_State_University | B40: https://www.sports-reference.com/cfb/schools/mississippi-state/ | C40: Mississippi State University | D40: Mississippi State | E40: Bulldogs | F40: Mississippi State | G40: MS | H40: Public | I40: FBS | J40: Southeastern Conference | K40: 115 | L40: 114 | M40: 110 | N40: 113 | O40: American Football | P40: 10 | Q40: =P40*N40 -> 1130
A41: https://en.wikipedia.org/wiki/Missouri_State_University | B41: https://www.sports-reference.com/cfb/schools/missouri-state/ | C41: Missouri State University | D41: Missouri State | E41: Bears | F41: Springfield | G41: MO | H41: Public | I41: FBS | J41: Conference USA | K41: 102 | N41: 102 | O41: American Football | P41: 10 | Q41: =P41*N41 -> 1020
A42: https://en.wikipedia.org/wiki/New_Mexico_State_University | B42: https://www.sports-reference.com/cfb/schools/new-mexico-state/ | C42: New Mexico State University | D42: New Mexico State | E42: Aggies | F42: Las Cruces | G42: NM | H42: Public | I42: FBS | J42: Conference USA | K42: 105 | L42: 113 | M42: 128 | N42: 115.3 | O42: American Football | P42: 10 | Q42: =P42*N42 -> 1153
A43: https://en.wikipedia.org/wiki/North_Carolina_State_University | B43: https://www.sports-reference.com/cfb/schools/north-carolina-state/ | C43: North Carolina State University | D43: NC State | E43: Wolfpack | F43: Raleigh | G43: NC | H43: Public | I43: FBS | J43: Atlantic Coast Conference | K43: 124 | L43: 122 | M43: 124 | N43: 123.3 | O43: American Football | P43: 10 | Q43: =P43*N43 -> 1233
A44: https://en.wikipedia.org/wiki/Northern_Illinois_University | B44: https://www.sports-reference.com/cfb/schools/northern-illinois/ | C44: Northern Illinois University | D44: Northern Illinois | E44: Huskies | F44: DeKalb | G44: IL | H44: Public | I44: FBS | J44: Mid-American Conference | K44: 112 | L44: 119 | M44: 119 | N44: 116.7 | O44: American Football | P44: 10 | Q44: =P44*N44 -> 1167
A45: https://en.wikipedia.org/wiki/Northwestern_University | B45: https://www.sports-reference.com/cfb/schools/northwestern/ | C45: Northwestern University | D45: Northwestern | E45: Wildcats | F45: Evanston | G45: IL | H45: Private | I45: FBS | J45: Big Ten Conference | K45: 110 | L45: 111 | M45: 102 | N45: 107.7 | O45: American Football | P45: 10 | Q45: =P45*N45 -> 1077
A46: https://en.wikipedia.org/wiki/Oklahoma_State_Cowboys_and_Cowgirls | B46: https://www.sports-reference.com/cfb/schools/oklahoma-state/ | C46: Oklahoma State University–Stillwater | D46: Oklahoma State | E46: Cowboys | F46: Stillwater | G46: OK | H46: Public | I46: FBS | J46: Big 12 Conference | K46: 114 | L46: 143 | M46: 125 | N46: 127.3 | O46: American Football | P46: 10 | Q46: =P46*N46 -> 1273
A47: https://en.wikipedia.org/wiki/Old_Dominion_University | B47: https://www.sports-reference.com/cfb/schools/old-dominion/ | C47: Old Dominion University | D47: Old Dominion | E47: Monarchs | F47: Norfolk | G47: VA | H47: Public | I47: FBS | J47: Sun Belt Conference | K47: 113 | L47: 114 | M47: 115 | N47: 114 | O47: American Football | P47: 10 | Q47: =P47*N47 -> 1140
A48: https://en.wikipedia.org/wiki/Oregon_State_University | B48: https://www.sports-reference.com/cfb/schools/oregon-state/ | C48: Oregon State University | D48: Oregon State | E48: Beavers | F48: Corvallis | G48: OR | H48: Public | I48: FBS | J48: Pac-12 Conference | K48: 113 | L48: 113 | M48: 125 | N48: 117 | O48: American Football | P48: 10 | Q48: =P48*N48 -> 1170
A49: https://en.wikipedia.org/wiki/Purdue_University | B49: https://www.sports-reference.com/cfb/schools/purdue/ | C49: Purdue University | D49: Purdue | E49: Boilermakers | F49: West Lafayette | G49: IN | H49: Public | I49: FBS | J49: Big Ten Conference | K49: 118 | L49: 121 | M49: 117 | N49: 118.7 | O49: American Football | P49: 10 | Q49: =P49*N49 -> 1187
A50: https://en.wikipedia.org/wiki/Rutgers_University%E2%80%93New_Brunswick | B50: https://www.sports-reference.com/cfb/schools/rutgers/ | C50: Rutgers University–New Brunswick | D50: Rutgers | E50: Scarlet Knights | F50: New Brunswick | G50: NJ | H50: Public | I50: FBS | J50: Big Ten Conference | K50: 133 | L50: 134 | M50: 131 | N50: 132.7 | O50: American Football | P50: 10 | Q50: =P50*N50 -> 1327
A51: https://en.wikipedia.org/wiki/Sam_Houston_State_University | B51: https://www.sports-reference.com/cfb/schools/sam-houston-state/ | C51: Sam Houston State University | D51: Sam Houston | E51: Bearkats | F51: Huntsville | G51: TX | H51: Public | I51: FBS | J51: Conference USA | K51: 103 | L51: 119 | M51: 112 | N51: 111.3 | O51: American Football | P51: 10 | Q51: =P51*N51 -> 1113
A52: https://en.wikipedia.org/wiki/San_Diego_State_University | B52: https://www.sports-reference.com/cfb/schools/san-diego-state/ | C52: San Diego State University | D52: San Diego State | E52: Aztecs | F52: San Diego | G52: CA | H52: Public | I52: FBS | J52: Mountain West Conference | K52: 105 | L52: 112 | M52: 109 | N52: 108.7 | O52: American Football | P52: 10 | Q52: =P52*N52 -> 1087
A53: https://en.wikipedia.org/wiki/San_Jose_State_University | B53: https://www.sports-reference.com/cfb/schools/san-jose-state/ | C53: San Jose State University | D53: San Jose State | E53: Spartans | F53: San Jose | G53: CA | H53: Public | I53: FBS | J53: Mountain West Conference | K53: 103 | L53: 102 | M53: 106 | N53: 103.7 | O53: American Football | P53: 10 | Q53: =P53*N53 -> 1037
... A81: https://en.wikipedia.org/wiki/University_of_Connecticut | B81: https://www.sports-reference.com/cfb/schools/connecticut/ | C81: University of Connecticut | D81: UConn | E81: Huskies | F81: Storrs | G81: CT | H81: Public | I81: FBS | J81: Big East Conference | K81: 113 | L81: 109 | M81: 113 | N81: 111.7 | O81: American Football | P81: 10 | Q81: =P81*N81 -> 1117
A82: https://en.wikipedia.org/wiki/University_of_Delaware | B82: https://www.sports-reference.com/cfb/schools/delaware/ | C82: University of Delaware | D82: Delaware | E82: Fightin' Blue Hens | F82: Newark | G82: DE | H82: Public | I82: FBS | J82: Conference USA | K82: 110 | N82: 110 | O82: American Football | P82: 10 | Q82: =P82*N82 -> 1100
A83: https://en.wikipedia.org/wiki/University_of_Florida | B83: https://www.sports-reference.com/cfb/schools/florida/ | C83: University of Florida | D83: Florida | E83: Gators | F83: Gainesville | G83: FL | H83: Public | I83: FBS | J83: Southeastern Conference | K83: 119 | L83: 132 | M83: 119 | N83: 123.3 | O83: American Football | P83: 10 | Q83: =P83*N83 -> 1233
A84: https://en.wikipedia.org/wiki/University_of_Georgia | B84: https://www.sports-reference.com/cfb/schools/georgia/ | C84: University of Georgia | D84: Georgia | E84: Bulldogs | F84: Athens | G84: GA | H84: Public | I84: FBS | J84: Southeastern Conference | K84: 129 | L84: 132 | M84: 127 | N84: 129.3 | O84: American Football | P84: 10 | Q84: =P84*N84 -> 1293
A85: https://en.wikipedia.org/wiki/University_of_Hawai%CA%BBi_at_M%C4%81noa | B85: https://www.sports-reference.com/cfb/schools/hawaii/ | C85: University of Hawaiʻi at Mānoa | D85: Hawaiʻi | E85: Rainbow Warriors | F85: Honolulu | G85: HI | H85: Public | I85: FBS | J85: Big West Conference | K85: 109 | L85: 124 | M85: 117 | N85: 116.7 | O85: American Football | P85: 10 | Q85: =P85*N85 -> 1167
A86: https://en.wikipedia.org/wiki/University_of_Houston | B86: https://www.sports-reference.com/cfb/schools/houston/ | C86: University of Houston | D86: Houston | E86: Cougars | F86: Houston | G86: TX | H86: Public | I86: FBS | J86: Big 12 Conference | K86: 112 | L86: 115 | M86: 111 | N86: 112.7 | O86: American Football | P86: 10 | Q86: =P86*N86 -> 1127
A87: https://en.wikipedia.org/wiki/University_of_Illinois_Urbana-Champaign | B87: https://www.sports-reference.com/cfb/schools/illinois/ | C87: University of Illinois Urbana-Champaign | D87: Illinois | E87: Fighting Illini | F87: Urbana | G87: IL | H87: Public | I87: FBS | J87: Big Ten Conference | K87: 115 | L87: 119 | M87: 119 | N87: 117.7 | O87: American Football | P87: 10 | Q87: =P87*N87 -> 1177
A88: https://en.wikipedia.org/wiki/University_of_Kansas | B88: https://www.sports-reference.com/cfb/schools/kansas/ | C88: University of Kansas | D88: Kansas | E88: Jayhawks | F88: Lawrence | G88: KS | H88: Public | I88: FBS | J88: Big 12 Conference | K88: 112 | L88: 121 | M88: 117 | N88: 116.7 | O88: American Football | P88: 10 | Q88: =P88*N88 -> 1167
A89: https://en.wikipedia.org/wiki/University_of_Kentucky | B89: https://www.sports-reference.com/cfb/schools/kentucky/ | C89: University of Kentucky | D89: Kentucky | E89: Wildcats | F89: Lexington | G89: KY | H89: Public | I89: FBS | J89: Southeastern Conference | K89: 113 | L89: 118 | M89: 119 | N89: 116.7 | O89: American Football | P89: 10 | Q89: =P89*N89 -> 1167
A90: https://en.wikipedia.org/wiki/University_of_Louisiana_at_Lafayette | B90: https://www.sports-reference.com/cfb/schools/louisiana-lafayette/ | C90: University of Louisiana at Lafayette | D90: Louisiana | E90: Ragin' Cajuns | F90: Lafayette | G90: LA | H90: Public | I90: FBS | J90: Sun Belt Conference | K90: 107 | L90: 133 | M90: 136 | N90: 125.3 | O90: American Football | P90: 10 | Q90: =P90*N90 -> 1253
A91: https://en.wikipedia.org/wiki/University_of_Louisiana_at_Monroe | B91: https://www.sports-reference.com/cfb/schools/louisiana-monroe/ | C91: University of Louisiana at Monroe | D91: ULM | E91: Warhawks | F91: Monroe | G91: LA | H91: Public | I91: FBS | J91: Sun Belt Conference | K91: 103 | L91: 120 | M91: 114 | N91: 112.3 | O91: American Football | P91: 10 | Q91: =P91*N91 -> 1123
A92: https://en.wikipedia.org/wiki/University_of_Louisville | B92: https://www.sports-reference.com/cfb/schools/louisville/ | C92: University of Louisville | D92: Louisville | E92: Cardinals | F92: Louisville | G92: KY | H92: Public | I92: FBS | J92: Atlantic Coast Conference | K92: 106 | L92: 116 | M92: 113 | N92: 111.7 | O92: American Football | P92: 10 | Q92: =P92*N92 -> 1117
A93: https://en.wikipedia.org/wiki/University_of_Maryland,_College_Park | B93: https://www.sports-reference.com/cfb/schools/maryland/ | C93: University of Maryland, College Park | D93: Maryland | E93: Terrapins | F93: College Park | G93: MD | H93: Public | I93: FBS | J93: Big Ten Conference | K93: 102 | L93: 119 | M93: 120 | N93: 113.7 | O93: American Football | P93: 10 | Q93: =P93*N93 -> 1137
A94: https://en.wikipedia.org/wiki/University_of_Massachusetts_Amherst | B94: https://www.sports-reference.com/cfb/schools/massachusetts/ | C94: University of Massachusetts Amherst | D94: UMass / Massachusetts | E94: Minutemen | F94: Amherst | G94: MA | H94: Public | I94: FBS | J94: Mid-American Conference | K94: 101 | L94: 112 | M94: 113 | N94: 108.7 | O94: American Football | P94: 10 | Q94: =P94*N94 -> 1087
... A129: https://en.wikipedia.org/wiki/Rice_University | B129: https://www.sports-reference.com/cfb/schools/rice/ | C129: William Marsh Rice University | D129: Rice | E129: Owls | F129: Houston | G129: TX | H129: Private | I129: FBS | J129: American Conference | K129: 107 | L129: 121 | M129: 111 | N129: 113 | O129: American Football | P129: 10 | Q129: =P129*N129 -> 1130
C130: Abilene Christian University | D130: Abilene Christian | E130: Wildcats | F130: Abilene | G130: TX | H130: Private | I130: FCS | J130: Western Athletic Conference | K130: 13 | L130: 14 | M130: 14 | N130: 13.7 | O130: Basketball | P130: 10 | Q130: =P130*N130 -> 137
C131: Alabama Agricultural and Mechanical University | D131: Alabama A&M | E131: Bulldogs | F131: Normal | G131: AL | H131: Public | I131: FCS | J131: Southwestern Athletic Conference | K131: 16 | L131: 20 | M131: 17 | N131: 17.7 | O131: Basketball | P131: 10 | Q131: =P131*N131 -> 177
C132: Alabama State University | D132: Alabama State | E132: Hornets | F132: Montgomery | G132: AL | H132: Public | I132: FCS | J132: Southwestern Athletic Conference | K132: 16 | L132: 13 | M132: 15 | N132: 14.7 | O132: Basketball | P132: 10 | Q132: =P132*N132 -> 147
C133: Alcorn State University | D133: Alcorn State | E133: Braves | F133: Lorman | G133: MS | H133: Public | I133: FCS | J133: Southwestern Athletic Conference | K133: 12 | L133: 17 | M133: 16 | N133: 15 | O133: Basketball | P133: 10 | Q133: =P133*N133 -> 150
C134: American University | D134: American | E134: Eagles | F134: Washington | G134: DC | H134: Private | I134: Non-football | J134: Patriot League | K134: 19 | L134: 15 | M134: 16 | N134: 16.7 | O134: Basketball | P134: 10 | Q134: =P134*N134 -> 167
C135: Appalachian State University | D135: Appalachian State | E135: Mountaineers | F135: Boone | G135: NC | H135: Public | I135: FBS | J135: Sun Belt Conference | K135: 16 | L135: 16 | M135: 13 | N135: 15 | O135: Basketball | P135: 10 | Q135: =P135*N135 -> 150
C136: Arizona State University | D136: Arizona State | E136: Sun Devils | F136: Tempe | G136: AZ | H136: Public | I136: FBS | J136: Big 12 Conference | K136: 16 | L136: 15 | M136: 16 | N136: 15.7 | O136: Basketball | P136: 10 | Q136: =P136*N136 -> 157
C137: Arkansas State University | D137: Arkansas State | E137: Red Wolves | F137: Jonesboro | G137: AR | H137: Public | I137: FBS | J137: Sun Belt Conference | K137: 16 | L137: 15 | M137: 13 | N137: 14.7 | O137: Basketball | P137: 10 | Q137: =P137*N137 -> 147
C138: Auburn University | D138: Auburn | E138: Tigers | F138: Auburn | G138: AL | H138: Public | I138: FBS | J138: Southeastern Conference | K138: 18 | L138: 15 | M138: 17 | N138: 16.7 | O138: Basketball | P138: 10 | Q138: =P138*N138 -> 167
C139: Austin Peay State University | D139: Austin Peay | E139: Governors | F139: Clarksville | G139: TN | H139: Public | I139: FCS | J139: Atlantic Sun Conference | K139: 13 | L139: 15 | M139: 13 | N139: 13.7 | O139: Basketball | P139: 10 | Q139: =P139*N139 -> 137
C140: Ball State University | D140: Ball State | E140: Cardinals | F140: Muncie | G140: IN | H140: Public | I140: FBS | J140: Mid-American Conference | K140: 14 | L140: 13 | M140: 13 | N140: 13.3 | O140: Basketball | P140: 10 | Q140: =P140*N140 -> 133
C141: Baylor University | D141: Baylor | E141: Bears | F141: Waco | G141: TX | H141: Private | I141: FBS | J141: Big 12 Conference | K141: 16 | L141: 12 | M141: 12 | N141: 13.3 | O141: Basketball | P141: 10 | Q141: =P141*N141 -> 133
... C490: Youngstown State University | D490: Youngstown State | E490: Penguins | F490: Youngstown | G490: OH | H490: Public | I490: FCS | J490: Horizon League | K490: 15 | L490: 12 | M490: 11 | N490: 12.7 | O490: Basketball | P490: 10 | Q490: =P490*N490 -> 127

Sheet name-mapping-basketball
A1: University | B1: School name | C1: Nickname | D1: City | E1: State | F1: Type | G1: Division | H1: Conference | I1: Sport | J1: Source URL | K1: Roster count 2026 | L1: Roster count 2025 | M1: Roster count 2024 | N1: Avg Roster Count Last 3 years
A2: Abilene Christian University | B2: Abilene Christian | C2: Wildcats | D2: Abilene | E2: TX | F2: Private | G2: FCS | H2: Western Athletic Conference | I2: Basketball | J2: https://www.sports-reference.com/cbb/schools/abilene-christian/men/
A3: Alabama Agricultural and Mechanical University | B3: Alabama A&M | C3: Bulldogs | D3: Normal | E3: AL | F3: Public | G3: FCS | H3: Southwestern Athletic Conference | I3: Basketball | J3: https://www.sports-reference.com/cbb/schools/alabama-am/men/
A4: Alabama State University | B4: Alabama State | C4: Hornets | D4: Montgomery | E4: AL | F4: Public | G4: FCS | H4: Southwestern Athletic Conference | I4: Basketball | J4: https://www.sports-reference.com/cbb/schools/alabama-state/men/
A5: Alcorn State University | B5: Alcorn State | C5: Braves | D5: Lorman | E5: MS | F5: Public | G5: FCS | H5: Southwestern Athletic Conference | I5: Basketball | J5: https://www.sports-reference.com/cbb/schools/alcorn-state/men/
A6: American University | B6: American | C6: Eagles | D6: Washington | E6: DC | F6: Private | G6: Non-football | H6: Patriot League | I6: Basketball | J6: https://www.sports-reference.com/cbb/schools/american/men/
A7: Appalachian State University | B7: Appalachian State | C7: Mountaineers | D7: Boone | E7: NC | F7: Public | G7: FBS | H7: Sun Belt Conference | I7: Basketball | J7: https://www.sports-reference.com/cbb/schools/appalachian-state/men/
A8: Arizona State University | B8: Arizona State | C8: Sun Devils | D8: Tempe | E8: AZ | F8: Public | G8: FBS | H8: Big 12 Conference | I8: Basketball | J8: https://www.sports-reference.com/cbb/schools/arizona-state/men/
A9: Arkansas State University | B9: Arkansas State | C9: Red Wolves | D9: Jonesboro | E9: AR | F9: Public | G9: FBS | H9: Sun Belt Conference | I9: Basketball | J9: https://www.sports-reference.com/cbb/schools/arkansas-state/men/
A10: Auburn University | B10: Auburn | C10: Tigers | D10: Auburn | E10: AL | F10: Public | G10: FBS | H10: Southeastern Conference | I10: Basketball | J10: https://www.sports-reference.com/cbb/schools/auburn/men/
A11: Austin Peay State University | B11: Austin Peay | C11: Governors | D11: Clarksville | E11: TN | F11: Public | G11: FCS | H11: Atlantic Sun Conference | I11: Basketball | J11: https://www.sports-reference.com/cbb/schools/austin-peay/men/
A12: Ball State University | B12: Ball State | C12: Cardinals | D12: Muncie | E12: IN | F12: Public | G12: FBS | H12: Mid-American Conference | I12: Basketball | J12: https://www.sports-reference.com/cbb/schools/ball-state/men/
A13: Baylor University | B13: Baylor | C13: Bears | D13: Waco | E13: TX | F13: Private | G13: FBS | H13: Big 12 Conference | I13: Basketball | J13: https://www.sports-reference.com/cbb/schools/baylor/men/
... A362: Youngstown State University | B362: Youngstown State | C362: Penguins | D362: Youngstown | E362: OH | F362: Public | G362: FCS | H362: Horizon League | I362: Basketball | J362: https://www.sports-reference.com/cbb/schools/youngstown-state/men/

Sheet school-mapping-basketball
A1: School URL | B1: School | C1: City, State | D1: From | E1: To | F1: Yrs | G1: G | H1: W | I1: L | J1: W-L % | K1: SRS | L1: SOS | M1: AP | N1: CREG | O1: CTRN | P1: NCAA | Q1: FF | R1: NC
A2: https://www.sports-reference.com/cbb/schools/abilene-christian/men/ | B2: Abilene Christian Wildcats | C2: Abilene, Texas | D2: 1971 | E2: 2026 | F2: 16 | G2: 488 | H2: 256 | I2: 232 | J2: 0.525 | K2: -7.59 | L2: -5.11 | M2: 0 | N2: 0 | O2: 2 | P2: 2 | Q2: 0 | R2: 0
A3: https://www.sports-reference.com/cbb/schools/air-force/men/ | B3: Air Force Falcons | C3: USAF Academy, Colorado | D3: 1958 | E3: 2026 | F3: 69 | G3: 1907 | H3: 800 | I3: 1107 | J3: 0.42 | K3: -2.9 | L3: 1.56 | M3: 0 | N3: 0 | O3: 1 | P3: 4 | Q3: 0 | R3: 0
A4: https://www.sports-reference.com/cbb/schools/akron/men/ | B4: Akron Zips | C4: Akron, Ohio | D4: 1902 | E4: 2026 | F4: 75 | G4: 1788 | H4: 1084 | I4: 704 | J4: 0.606 | K4: 0.45 | L4: -1.45 | M4: 0 | N4: 0 | O4: 10 | P4: 8 | Q4: 0 | R4: 8
A5: https://www.sports-reference.com/cbb/schools/alabama-am/men/ | B5: Alabama A&M Bulldogs | C5: Normal, Alabama | D5: 2000 | E5: 2026 | F5: 27 | G5: 788 | H5: 305 | I5: 483 | J5: 0.387 | K5: -16.31 | L5: -10.69 | M5: 0 | N5: 0 | O5: 1 | P5: 1 | Q5: 0 | R5: 1
A6: https://www.sports-reference.com/cbb/schools/alabama/men/ | B6: Alabama Crimson Tide | C6: Tuscaloosa, Alabama | D6: 1913 | E6: 2026 | F6: 113 | G6: 2968 | H6: 1847 | I6: 1120 | J6: 0.623 | K6: 8.49 | L6: 5.32 | M6: 0 | N6: 27 | O6: 19 | P6: 10 | Q6: 1 | R6: 9
A7: https://www.sports-reference.com/cbb/schools/alabama-state/men/ | B7: Alabama State Hornets | C7: Montgomery, Alabama | D7: 1983 | E7: 2026 | F7: 44 | G7: 1308 | H7: 605 | I7: 703 | J7: 0.463 | K7: -12.98 | L7: -9.63 | M7: 0 | N7: 4 | O7: 5 | P7: 5 | Q7: 0 | R7: 0
A8: https://www.sports-reference.com/cbb/schools/albany-ny/men/ | B8: Albany (NY) Great Danes | C8: Albany, New York | D8: 2000 | E8: 2026 | F8: 27 | G8: 833 | H8: 395 | I8: 438 | J8: 0.474 | K8: -7.11 | L8: -5.79 | M8: 0 | N8: 2 | O8: 5 | P8: 5 | Q8: 0 | R8: 0
A9: https://www.sports-reference.com/cbb/schools/alcorn-state/men/ | B9: Alcorn State Braves | C9: Alcorn State, Mississippi | D9: 1978 | E9: 2026 | F9: 49 | G9: 1456 | H9: 627 | I9: 829 | J9: 0.431 | K9: -13.41 | L9: -8.41 | M9: 0 | N9: 12 | O9: 6 | P9: 6 | Q9: 0 | R9: 0
A10: https://www.sports-reference.com/cbb/schools/allegheny/men/ | B10: Allegheny Gators | C10: Meadville, Pennsylvania | D10: 1896 | E10: 1916 | F10: 21 | G10: 234 | H10: 191 | I10: 41 | J10: 0.823 | K10: 0 | L10: 0 | M10: 0 | N10: 0 | Q10: 0 | R10: 0
A11: https://www.sports-reference.com/cbb/schools/american/men/ | B11: American Eagles | C11: Washington, D.C. | D11: 1967 | E11: 2026 | F11: 60 | G11: 1706 | H11: 840 | I11: 866 | J11: 0.492 | K11: -5.73 | L11: -3.93 | M11: 0 | N11: 8 | O11: 4 | P11: 4 | Q11: 0 | R11: 0
A12: https://www.sports-reference.com/cbb/schools/amherst/men/ | B12: Amherst Lord Jeffs | C12: Amherst, Massachusetts | D12: 1901 | E12: 1902 | F12: 2 | G12: 12 | H12: 12 | I12: 1 | J12: 0 | K12: 0 | L12: 0 | M12: 0 | N12: 0 | Q12: 0 | R12: 0
A13: https://www.sports-reference.com/cbb/schools/appalachian-state/men/ | B13: Appalachian State Mountaineers | C13: Boone, North Carolina | D13: 1974 | E13: 2026 | F13: 53 | G13: 1577 | H13: 790 | I13: 787 | J13: 0.501 | K13: -5.23 | L13: -3.13 | M13: 0 | N13: 11 | O13: 3 | P13: 3 | Q13: 0 | R13: 0
A14: https://www.sports-reference.com/cbb/schools/arizona-state/men/ | B14: Arizona State Sun Devils | C14: Tempe, Arizona | D14: 1912 | E14: 2026 | F14: 111 | G14: 2766 | H14: 1461 | I14: 1305 | J14: 0.528 | K14: 5.37 | L14: 4.56 | M14: 0 | N14: 7 | O14: 8 | P14: 17 | Q14: 0 | R14: 0
A15: https://www.sports-reference.com/cbb/schools/arizona/men/ | B15: Arizona Wildcats | C15: Tucson, Arizona | D15: 1905 | E15: 2026 | F15: 119 | G15: 2963 | H15: 1973 | I15: 989 | J15: 0.666 | K15: 10.1 | L15: 5.54 | M15: 1 | N15: 31 | O15: 27 | P15: 10 | Q15: 40 | R15: 5
A16: https://www.sports-reference.com/cbb/schools/arkansas/men/ | B16: Arkansas Razorbacks | C16: Fayetteville, Arkansas | D16: 1924 | E16: 2026 | F16: 103 | G16: 2886 | H16: 1849 | I16: 1037 | J16: 0.641 | K16: 8.32 | L16: 3.74 | M16: 19 | N16: 24 | O16: 8 | P16: 37 | Q16: 6 | R16: 1
A17: https://www.sports-reference.com/cbb/schools/arkansas-state/men/ | B17: Arkansas State Red Wolves | C17: State University, Arkansas | D17: 1971 | E17: 2026 | F17: 56 | G17: 1643 | H17: 850 | I17: 793 | J17: 0.517 | K17: -3.29 | L17: -2.84 | M17: 0 | N17: 8 | O17: 1 | P17: 1 | Q17: 0 | R17: 0
A18: https://www.sports-reference.com/cbb/schools/arkansas-pine-bluff/men/ | B18: Arkansas-Pine Bluff Golden Lions | C18: Pine Bluff, Arkansas | D18: 1999 | E18: 2026 | F18: 28 | G18: 848 | H18: 252 | I18: 596 | J18: 0.297 | K18: -18.96 | L18: -7.85 | M18: 0 | N18: 0 | O18: 1 | P18: 1 | Q18: 0 | R18: 0
A19: https://www.sports-reference.com/cbb/schools/armstrong/men/ | B19: Armstrong Pirates | C19: Savannah, Georgia | D19: 1987 | E19: 1987 | F19: 1 | G19: 28 | H19: 6 | I19: 22 | J19: 0.214 | K19: -21.6 | L19: -4.78 | M19: 0 | N19: 0 | O19: 0 | P19: 0 | Q19: 0 | R19: 0
A20: https://www.sports-reference.com/cbb/schools/army/men/ | B20: Army Black Knights | C20: West Point, New York | D20: 1903 | E20: 2026 | F20: 124 | G20: 2699 | H20: 1332 | I20: 1367 | J20: 0.494 | K20: -9.17 | L20: -4.7 | M20: 0 | N20: 0 | O20: 0 | P20: 0 | Q20: 0 | R20: 0
A21: https://www.sports-reference.com/cbb/schools/auburn/men/ | B21: Auburn Tigers | C21: Auburn, Alabama | D21: 1906 | E21: 2026 | F21: 120 | G21: 2803 | H21: 1530 | I21: 1272 | J21: 0.546 | K21: 6.69 | L21: 4.77 | M21: 11 | N21: 6 | O21: 3 | P21: 14 | Q21: 2 | R21: 0
A22: https://www.sports-reference.com/cbb/schools/augusta-state/men/ | B22: Augusta Jaguars | C22: Augusta, Georgia | D22: 1985 | E22: 1991 | F22: 7 | G22: 197 | H22: 64 | I22: 133 | J22: 0.325 | K22: -17.3 | L22: -7.99 | M22: 0 | N22: 0 | O22: 0 | P22: 0 | Q22: 0 | R22: 0
A23: https://www.sports-reference.com/cbb/schools/augustana-il/men/ | B23: Augustana (IL) Vikings | C23: Rock Island, Illinois | D23: 1902 | E23: 1917 | F23: 12 | G23: 116 | H23: 81 | I23: 35 | J23: 0.698 | K23: 0 | L23: 0 | M23: 0 | N23: 0 | O23: 0 | P23: 0
A24: https://www.sports-reference.com/cbb/schools/austin-peay/men/ | B24: Austin Peay Governors | C24: Clarksville, Tennessee | D24: 1964 | E24: 2026 | F24: 63 | G24: 1826 | H24: 914 | I24: 912 | J24: 0.501 | K24: -5.54 | L24: -3.39 | M24: 1 | N24: 9 | O24: 5 | P24: 7 | Q24: 0 | R24: 0
A25: https://www.sports-reference.com/cbb/schools/baker/men/ | B25: Baker | C25: Baldwin City, Kansas | D25: 1903 | E25: 1908 | F25: 6 | G25: 90 | H25: 62 | I25: 28 | J25: 0.689 | K25: 0 | L25: 0 | M25: 0 | N25: 0 | O25: 0 | P25: 0
A26: https://www.sports-reference.com/cbb/schools/baldwin-wallace/men/ | B26: Baldwin-Wallace Yellow Jackets | C26: Berea, Ohio | D26: 1948 | E26: 1953 | F26: 6 | G26: 139 | H26: 82 | I26: 57 | J26: 0.59 | K26: -4.46 | L26: 1.83 | M26: 0 | N26: 0 | O26: 0 | P26: 0 | Q26: 0 | R26: 0
A27: https://www.sports-reference.com/cbb/schools/ball-state/men/ | B27: Ball State Cardinals | C27: Muncie, Indiana | D27: 1972 | E27: 2026 | F27: 55 | G27: 1622 | H27: 853 | I27: 769 | J27: 0.526 | K27: -1.22 | L27: -0.92 | M27: 1 | N27: 12 | O27: 7 | P27: 7 | Q27: 0 | R27: 0
A28: https://www.sports-reference.com/cbb/schools/baltimore/men/ | B28: Baltimore Super Bees | C28: Baltimore, Maryland | D28: 1979 | E28: 1983 | F28: 5 | G28: 133 | H28: 46 | I28: 87 | J28: 0.346 | K28: -13.75 | L28: -6.44 | M28: 0 | N28: 0 | O28: 0 | P28: 0 | Q28: 0 | R28: 0
A29: https://www.sports-reference.com/cbb/schools/baylor/men/ | B29: Baylor Bears | C29: Waco, Texas | D29: 1907 | E29: 2026 | F29: 120 | G29: 2954 | H29: 1515 | I29: 1439 | J29: 0.513 | K29: 3.15 | L29: 3.32 | M29: 11 | N29: 7 | O29: 0 | P29: 17 | Q29: 3 | R29: 1
A30: https://www.sports-reference.com/cbb/schools/bellarmine/men/ | B30: Bellarmine Knights | C30: Louisville, Kentucky | D30: 2021 | E30: 2026 | F30: 6 | G30: 182 | H30: 75 | I30: 107 | J30: 0.412 | K30: -8.22 | L30: -3.42 | M30: 0 | N30: 0 | O30: 1 | P30: 0 | Q30: 0 | R30: 0
A31: https://www.sports-reference.com/cbb/schools/belmont/men/ | B31: Belmont Bruins | C31: Nashville, Tennessee | D31: 2000 | E31: 2026 | F31: 27 | G31: 861 | H31: 581 | I31: 280 | J31: 0.675 | K31: 2.28 | L31: -2.81 | M31: 0 | N31: 15 | O31: 8 | P31: 8 | Q31: 0 | R31: 0
A32: https://www.sports-reference.com/cbb/schools/beloit/men/ | B32: Beloit Buccaneers | C32: Beloit, Wisconsin | D32: 1911 | E32: 1924 | F32: 8 | G32: 95 | H32: 66 | I32: 28 | J32: 0.702 | K32: 0 | L32: 0 | M32: 0 | N32: 0 | O32: 0 | P32: 0
A33: https://www.sports-reference.com/cbb/schools/bethune-cookman/men/ | B33: Bethune-Cookman Wildcats | C33: Daytona Beach, Florida | D33: 1981 | E33: 2026 | F33: 45 | G33: 1346 | H33: 505 | I33: 841 | J33: 0.375 | K33: -16.02 | L33: -9.49 | M33: 0 | N33: 3 | O33: 0 | P33: 0 | Q33: 0 | R33: 0
A34: https://www.sports-reference.com/cbb/schools/binghamton/men/ | B34: Binghamton Bearcats | C34: Binghamton, New York | D34: 2002 | E34: 2026 | F34: 25 | G34: 745 | H34: 272 | I34: 473 | J34: 0.365 | K34: -11.23 | L34: -5.51 | M34: 0 | N34: 1 | O34: 1 | P34: 1 | Q34: 0 | R34: 0
A35: https://www.sports-reference.com/cbb/schools/birmingham-southern/men/ | B35: Birmingham-Southern Panthers | C35: Birmingham, Alabama | D35: 1920 | E35: 2006 | F35: 7 | G35: 160 | H35: 97 | I35: 63 | J35: 0.606 | K35: -5.44 | L35: -8.72 | M35: 0 | N35: 1 | O35: 0 | P35: 0 | Q35: 0 | R35: 0
A36: https://www.sports-reference.com/cbb/schools/bloomsburg/men/ | B36: Bloomsburg Huskies | C36: Bloomsburg, Pennsylvania | D36: 1896 | E36: 1911 | F36: 15 | G36: 143 | H36: 88 | I36: 55 | J36: 0.615 | K36: 0 | L36: 0 | M36: 0 | N36: 0 | O36: 0 | P36: 0
A37: https://www.sports-reference.com/cbb/schools/boise-state/men/ | B37: Boise State Broncos | C37: Boise, Idaho | D37: 1972 | E37: 2026 | F37: 55 | G37: 1644 | H37: 941 | I37: 703 | J37: 0.572 | K37: 1.74 | L37: 0.25 | M37: 1 | N37: 7 | O37: 6 | P37: 10 | Q37: 0 | R37: 0
A38: https://www.sports-reference.com/cbb/schools/boston-college/men/ | B38: Boston College Eagles | C38: Chestnut Hill, Massachusetts | D38: 1946 | E38: 2026 | F38: 81 | G38: 2298 | H38: 1232 | I38: 1066 | J38: 0.536 | K38: 3.26 | L38: 3.53 | M38: 8 | N38: 6 | O38: 2 | P38: 18 | Q38: 0 | R38: 0
A39: https://www.sports-reference.com/cbb/schools/boston-university/men/ | B39: Boston University Terriers | C39: Boston, Massachusetts | D39: 1916 | E39: 2026 | F39: 100 | G39: 2349 | H39: 1206 | I39: 1143 | J39: 0.513 | K39: -6.7 | L39: -5.42 | M39: 0 | N39: 8 | O39: 7 | P39: 7 | Q39: 0 | R39: 0
A40: https://www.sports-reference.com/cbb/schools/bowling-green-state/men/ | B40: Bowling Green Falcons | C40: Bowling Green, Ohio | D40: 1916 | E40: 2026 | F40: 111 | G40: 2789 | H40: 1498 | I40: 1291 | J40: 0.537 | K40: -0.69 | L40: -0.13 | M40: 2 | N40: 9 | O40: 0 | P40: 4 | Q40: 0 | R40: 0
A41: https://www.sports-reference.com/cbb/schools/bradley/men/ | B41: Bradley Braves | C41: Peoria, Illinois | D41: 1903 | E41: 2026 | F41: 122 | G41: 3105 | H41: 1818 | I41: 1287 | J41: 0.586 | K41: 4.88 | L41: 2.93 | M41: 12 | N41: 8 | O41: 4 | P41: 9 | Q41: 2 | R41: 0
A42: https://www.sports-reference.com/cbb/schools/brigham-young-college/men/ | B42: Brigham Young College | C42: Logan, Utah | D42: 1908 | E42: 1908 | F42: 1 | G42: 11 | H42: 10 | I42: 1 | J42: 0.909 | K42: 0 | L42: 0 | M42: 0 | N42: 0 | O42: 0 | P42: 0
A43: https://www.sports-reference.com/cbb/schools/brigham-young/men/ | B43: Brigham Young Cougars | C43: Provo, Utah | D43: 1903 | E43: 2026 | F43: 124 | G43: 3157 | H43: 1988 | I43: 1169 | J43: 0.63 | K43: 8.44 | L43: 4.06 | M43: 13 | N43: 25 | O43: 3 | P43: 33 | Q43: 0 | R43: 0
A44: https://www.sports-reference.com/cbb/schools/brooklyn/men/ | B44: Brooklyn Bulldogs | C44: Brooklyn, New York | D44: 1934 | E44: 1992 | F44: 25 | G44: 567 | H44: 233 | I44: 334 | J44: 0.411 | K44: -19.22 | L44: -9.63 | M44: 0 | N44: 0 | O44: 0 | P44: 0 | Q44: 0 | R44: 0
A45: https://www.sports-reference.com/cbb/schools/brown/men/ | B45: Brown Bears | C45: Providence, Rhode Island | D45: 1901 | E45: 2026 | F45: 119 | G45: 2742 | H45: 1123 | I45: 1619 | J45: 0.41 | K45: -10.34 | L45: -4.35 | M45: 0 | N45: 1 | O45: 0 | P45: 2 | Q45: 0 | R45: 0
A46: https://www.sports-reference.com/cbb/schools/bryant/men/ | B46: Bryant Bulldogs | C46: Smithfield, Rhode Island | D46: 2009 | E46: 2026 | F46: 18 | G46: 552 | H46: 227 | I46: 325 | J46: 0.411 | K46: -9.09 | L46: -5.72 | M46: 0 | N46: 2 | O46: 2 | P46: 2 | Q46: 0 | R46: 0
A47: https://www.sports-reference.com/cbb/schools/bucknell/men/ | B47: Bucknell Bison | C47: Lewisburg, Pennsylvania | D47: 1896 | E47: 2026 | F47: 131 | G47: 2887 | H47: 1531 | I47: 1356 | J47: 0.53 | K47: -8.25 | L47: -6.66 | M47: 0 | N47: 19 | O47: 8 | P47: 8 | Q47: 0 | R47: 0
A48: https://www.sports-reference.com/cbb/schools/buffalo/men/ | B48: Buffalo Bulls | C48: Buffalo, New York | D48: 1907 | E48: 2026 | F48: 57 | G48: 1418 | H48: 713 | I48: 705 | J48: 0.503 | K48: -4.67 | L48: -2.13 | M48: 1 | N48: 5 | O48: 4 | P48: 4 | Q48: 0 | R48: 0
A49: https://www.sports-reference.com/cbb/schools/butler/men/ | B49: Butler Bulldogs | C49: Indianapolis, Indiana | D49: 1897 | E49: 2026 | F49: 128 | G49: 2963 | H49: 1706 | I49: 1257 | J49: 0.576 | K49: 2.47 | L49: 3.74 | M49: 8 | N49: 13 | O49: 7 | P49: 16 | Q49: 2 | R49: 0
A50: https://www.sports-reference.com/cbb/schools/cal-poly/men/ | B50: Cal Poly Mustangs | C50: San Luis Obispo, California | D50: 1995 | E50: 2026 | F50: 32 | G50: 950 | H50: 356 | I50: 594 | J50: 0.375 | K50: -6.86 | L50: -1.44 | M50: 0 | N50: 1 | O50: 1 | P50: 1 | Q50: 0 | R50: 0
A51: https://www.sports-reference.com/cbb/schools/cal-state-bakersfield/men/ | B51: Cal State Bakersfield Roadrunners | C51: Bakersfield, California | D51: 2008 | E51: 2026 | F51: 19 | G51: 588 | H51: 250 | I51: 338 | J51: 0.425 | K51: -5.7 | L51: -2.29 | M51: 0 | N51: 1 | O51: 1 | P51: 1 | Q51: 0 | R51: 0
A52: https://www.sports-reference.com/cbb/schools/cal-state-fullerton/men/ | B52: Cal State Fullerton Titans | C52: Fullerton, California | D52: 1975 | E52: 2026 | F52: 52 | G52: 1523 | H52: 720 | I52: 803 | J52: 0.473 | K52: -2.09 | L52: -0.23 | M52: 0 | N52: 2 | O52: 4 | P52: 4 | Q52: 0 | R52: 0
A53: https://www.sports-reference.com/cbb/schools/cal-state-los-angeles/men/ | B53: Cal State Los Angeles Golden Eagles | C53: Los Angeles, California | D53: 1971 | E53: 1975 | F53: 5 | G53: 130 | H53: 70 | I53: 60 | J53: 0.538 | K53: -1.89 | L53: 1.34 | M53: 0 | N53: 0 | O53: 0 | P53: 1 | Q53: 0 | R53: 0
A54: https://www.sports-reference.com/cbb/schools/cal-state-northridge/men/ | B54: Cal State Northridge Matadors | C54: Northridge, California | D54: 1991 | E54: 2026 | F54: 36 | G54: 1082 | H54: 468 | I54: 614 | J54: 0.433 | K54: -5.23 | L54: -1.73 | M54: 0 | N54: 3 | O54: 2 | P54: 2 | Q54: 0 | R54: 0
